Workbook

Sheet Read_Me
A1: Auditable Flourishing v6.2 External Pilot Aggregation Workbook
A3: Field | B3: Binding instruction
A4: Protocol status | B4: Master specification frozen; publication-integrity and provenance closure complete; Phase 0 design-ready; materials, host, reviewer pool, external reliability, validity, burden, fairness, legitimacy and decision-value evidence remain open.
A5: Purpose | B5: Prospective aggregation after source records are captured in independently controlled, timestamped and hash-bound systems.
A6: Not authorized | B6: This workbook is not an immutable deposit system, certification instrument, legal opinion, flourishing measure, due-diligence safe harbor, foreseeability finding or deployment authorization.
A7: Positive Stage A label | B7: Use exact bounded status, canonical token, candidate, scope, evidence cut-off, protocol version, CL basis, host, conditions, expiry, dissent and appeal route.
A8: Non-compensation | B8: A material C0-C5 defect cannot be offset by strength elsewhere.
A9: Burden gate | B9: Feasibility is conjunctive across numeric validity, reviewer and adjudication hours, calendar, reviewer count, access, translation, custody and governance.
A10: Independence | B10: Unknown control values route to Indeterminate; recognized capture, missing reporting protection, undisclosed model rating or publication veto routes to Inadequate.
A11: Public claims | B11: Never export bare Pass, Approved, Certified, Safe, Ethical, Legitimate, Compliant, Due-Diligence, Foreseeable/Unforeseeable or Authorized labels.
A12: Evidence | B12: Documentary and non-documentary evidence requires provenance, consent, custody, translation, challengeability, compensation, sovereignty and withdrawal conditions.
A13: Reliability | B13: Raw agreement is descriptive. Versioned external scripts compute AC1/AC2, alpha, intervals, exclusions and sensitivity analyses; negative adverse results are permitted.
A14: Configured data capacity
A15: Workbook sequence
A16: 1 | B16: Vocabulary - controlling lists, protocol version and constitutional-legitimacy basis.
A17: 2 | B17: Profile_Routing - incomplete or unrecognized routes remain undetermined; no downward default.
A18: 3 | B18: Candidate_Register - bind candidate, version, scope, authority claim, access and evidence cut-off.
A19: 4 | B19: Study_Readiness - distinguish design-ready, materials-ready, shadow-ready, pilot-ready and replication-ready.
A20: 5 | B20: Scenario_Register - bind frozen scenario-set version, equivalence criteria, calibration, access and hash.
A21: 6 | B21: Stage_A - six recognized criterion states are required. Refusal prerequisites route first; established unpatchable defects control over patchable defects; established patchable defects control over unresolved criterion evidence; only then can indeterminate or admissible outcomes be assigned.
A22: 7 | B22: Stage_A - only six recognized adequate/control-dependent findings can support admissibility; administrative statuses have an explicit derived route.
A23: 8 | B23: Verdict_Vector - separate AF eligibility from legal, moral, community and deployment findings.
A24: 9 | B24: Independence - use positive whitelists, protected reporting and anti-retaliation controls.
A25: 10 | B25: Perturbation_Register - proposals require evidence and independent admission before replay.
A26: 11 | B26: Burden_Log - test access, translation, custody, governance and capacity conjunctively.
A27: 12 | B27: Decision_Value - retain positive, null and adverse results.
... A31: Canonical registry | B31: The Core Protocol controls. release/AF_CANONICAL_REGISTRY_v6_2.json binds release version, stable component IDs, Stage A precedence, AF-SB12, and artifact authority; the workbook cannot override it.

Sheet Profile_Routing
A1: AF v6.2 Profile Routing
A3: Routing_ID | B3: Candidate_ID | C3: Declared_Scope | D3: Stakes | E3: Rights_Impact | F3: Irreversibility | G3: Population_Scale | H3: Novelty | I3: Contestation | J3: Candidate_Capacity | K3: Review_Capacity | L3: Access_Support | M3: Derived_Profile | N3: Recorded_Profile | O3: Routing_Match | P3: Rationale | Q3: Vocabulary_Check
A4: ROUTE-ILL-001 | B4: SYNTH-CAND-HC | C4: National benefits eligibility architecture | D4: High | E4: Fundamental or uncertain | F4: Difficult to reverse | G4: National/transnational/ecological | H4: Novel | I4: Affected-party dispute or unknown | J4: Constrained | K4: Adequate | L4: Yes | M4: =IF(COUNTA(A4:L4)=0,"",IF(OR(LEN(TRIM(B4))=0,LEN(TRIM(C4))=0,LEN(TRIM(D4))=0,LEN(TRIM(E4))=0,LEN(TRIM(F4))=0,LEN(TRIM(G4))=0,LEN(TRIM(H4))=0,LEN(TRIM(I4))=0,LEN(TRIM(J4))=0,LEN(TRIM(K4))=0,LEN(TRIM(L4))=0),"Undetermined - incomplete routing",IF(Q4<>"OK","Undetermined - unrecognized routing value",IF(OR(D4="High",D4="Catastrophic/systemic",E4="Material",E4="Fundamental or uncertain",F4="Difficult to reverse",F4="Irreversible or unknown",G4="National/transnational/ecological",H4="Frontier or unknown",I4="Affected-party dispute or unknown"),"AF-High-Consequence",IF(OR(D4="Moderate",E4="Limited reversible",F4="Partly reversible",G4="Regional/sectoral",H4="Novel",I4="High"),"AF-Standard","AF-Lite"))))) | N4: AF-High-Consequence | O4: =IF(AND(M4="",N4=""),"",IF(AND(M4<>"",N4=""),"UNRECORDED",IF(AND(M4="",N4<>""),"ORPHAN_RECORDED",IF(M4=N4,"MATCH","MISMATCH")))) | P4: Illustrative high-consequence route; constrained resources trigger support, not a lower standard. | Q4: =IF(COUNTA(A4:L4)=0,"",IF(AND(COUNTIF(Vocabulary!$C$5:$C$8,D4)=1,COUNTIF(Vocabulary!$D$5:$D$8,E4)=1,COUNTIF(Vocabulary!$E$5:$E$8,F4)=1,COUNTIF(Vocabulary!$F$5:$F$8,G4)=1,COUNTIF(Vocabulary!$G$5:$G$8,H4)=1,COUNTIF(Vocabulary!$H$5:$H$8,I4)=1,COUNTIF(Vocabulary!$I$5:$I$7,J4)=1,COUNTIF(Vocabulary!$I$5:$I$7,K4)=1,COUNTIF(Vocabulary!$J$5:$J$6,L4)=1),"OK","UNRECOGNISED_ROUTING_VALUE"))
A5: ROUTE-ILL-002 | B5: SYNTH-CAND-LITE | C5: Local reversible advisory workshop | D5: Low | E5: None identified | F5: Reversible | G5: Local/small | H5: Routine | I5: Low | J5: Adequate | K5: Adequate | L5: No | M5: =IF(COUNTA(A5:L5)=0,"",IF(OR(LEN(TRIM(B5))=0,LEN(TRIM(C5))=0,LEN(TRIM(D5))=0,LEN(TRIM(E5))=0,LEN(TRIM(F5))=0,LEN(TRIM(G5))=0,LEN(TRIM(H5))=0,LEN(TRIM(I5))=0,LEN(TRIM(J5))=0,LEN(TRIM(K5))=0,LEN(TRIM(L5))=0),"Undetermined - incomplete routing",IF(Q5<>"OK","Undetermined - unrecognized routing value",IF(OR(D5="High",D5="Catastrophic/systemic",E5="Material",E5="Fundamental or uncertain",F5="Difficult to reverse",F5="Irreversible or unknown",G5="National/transnational/ecological",H5="Frontier or unknown",I5="Affected-party dispute or unknown"),"AF-High-Consequence",IF(OR(D5="Moderate",E5="Limited reversible",F5="Partly reversible",G5="Regional/sectoral",H5="Novel",I5="High"),"AF-Standard","AF-Lite"))))) | N5: AF-Lite | O5: =IF(AND(M5="",N5=""),"",IF(AND(M5<>"",N5=""),"UNRECORDED",IF(AND(M5="",N5<>""),"ORPHAN_RECORDED",IF(M5=N5,"MATCH","MISMATCH")))) | P5: Illustrative low-stakes route. | Q5: =IF(COUNTA(A5:L5)=0,"",IF(AND(COUNTIF(Vocabulary!$C$5:$C$8,D5)=1,COUNTIF(Vocabulary!$D$5:$D$8,E5)=1,COUNTIF(Vocabulary!$E$5:$E$8,F5)=1,COUNTIF(Vocabulary!$F$5:$F$8,G5)=1,COUNTIF(Vocabulary!$G$5:$G$8,H5)=1,COUNTIF(Vocabulary!$H$5:$H$8,I5)=1,COUNTIF(Vocabulary!$I$5:$I$7,J5)=1,COUNTIF(Vocabulary!$I$5:$I$7,K5)=1,COUNTIF(Vocabulary!$J$5:$J$6,L5)=1),"OK","UNRECOGNISED_ROUTING_VALUE"))
M6: =IF(COUNTA(A6:L6)=0,"",IF(OR(LEN(TRIM(B6))=0,LEN(TRIM(C6))=0,LEN(TRIM(D6))=0,LEN(TRIM(E6))=0,LEN(TRIM(F6))=0,LEN(TRIM(G6))=0,LEN(TRIM(H6))=0,LEN(TRIM(I6))=0,LEN(TRIM(J6))=0,LEN(TRIM(K6))=0,LEN(TRIM(L6))=0),"Undetermined - incomplete routing",IF(Q6<>"OK","Undetermined - unrecognized routing value",IF(OR(D6="High",D6="Catastrophic/systemic",E6="Material",E6="Fundamental or uncertain",F6="Difficult to reverse",F6="Irreversible or unknown",G6="National/transnational/ecological",H6="Frontier or unknown",I6="Affected-party dispute or unknown"),"AF-High-Consequence",IF(OR(D6="Moderate",E6="Limited reversible",F6="Partly reversible",G6="Regional/sectoral",H6="Novel",I6="High"),"AF-Standard","AF-Lite"))))) | O6: =IF(AND(M6="",N6=""),"",IF(AND(M6<>"",N6=""),"UNRECORDED",IF(AND(M6="",N6<>""),"ORPHAN_RECORDED",IF(M6=N6,"MATCH","MISMATCH")))) | Q6: =IF(COUNTA(A6:L6)=0,"",IF(AND(COUNTIF(Vocabulary!$C$5:$C$8,D6)=1,COUNTIF(Vocabulary!$D$5:$D$8,E6)=1,COUNTIF(Vocabulary!$E$5:$E$8,F6)=1,COUNTIF(Vocabulary!$F$5:$F$8,G6)=1,COUNTIF(Vocabulary!$G$5:$G$8,H6)=1,COUNTIF(Vocabulary!$H$5:$H$8,I6)=1,COUNTIF(Vocabulary!$I$5:$I$7,J6)=1,COUNTIF(Vocabulary!$I$5:$I$7,K6)=1,COUNTIF(Vocabulary!$J$5:$J$6,L6)=1),"OK","UNRECOGNISED_ROUTING_VALUE"))
M7: =IF(COUNTA(A7:L7)=0,"",IF(OR(LEN(TRIM(B7))=0,LEN(TRIM(C7))=0,LEN(TRIM(D7))=0,LEN(TRIM(E7))=0,LEN(TRIM(F7))=0,LEN(TRIM(G7))=0,LEN(TRIM(H7))=0,LEN(TRIM(I7))=0,LEN(TRIM(J7))=0,LEN(TRIM(K7))=0,LEN(TRIM(L7))=0),"Undetermined - incomplete routing",IF(Q7<>"OK","Undetermined - unrecognized routing value",IF(OR(D7="High",D7="Catastrophic/systemic",E7="Material",E7="Fundamental or uncertain",F7="Difficult to reverse",F7="Irreversible or unknown",G7="National/transnational/ecological",H7="Frontier or unknown",I7="Affected-party dispute or unknown"),"AF-High-Consequence",IF(OR(D7="Moderate",E7="Limited reversible",F7="Partly reversible",G7="Regional/sectoral",H7="Novel",I7="High"),"AF-Standard","AF-Lite"))))) | O7: =IF(AND(M7="",N7=""),"",IF(AND(M7<>"",N7=""),"UNRECORDED",IF(AND(M7="",N7<>""),"ORPHAN_RECORDED",IF(M7=N7,"MATCH","MISMATCH")))) | Q7: =IF(COUNTA(A7:L7)=0,"",IF(AND(COUNTIF(Vocabulary!$C$5:$C$8,D7)=1,COUNTIF(Vocabulary!$D$5:$D$8,E7)=1,COUNTIF(Vocabulary!$E$5:$E$8,F7)=1,COUNTIF(Vocabulary!$F$5:$F$8,G7)=1,COUNTIF(Vocabulary!$G$5:$G$8,H7)=1,COUNTIF(Vocabulary!$H$5:$H$8,I7)=1,COUNTIF(Vocabulary!$I$5:$I$7,J7)=1,COUNTIF(Vocabulary!$I$5:$I$7,K7)=1,COUNTIF(Vocabulary!$J$5:$J$6,L7)=1),"OK","UNRECOGNISED_ROUTING_VALUE"))
M8: =IF(COUNTA(A8:L8)=0,"",IF(OR(LEN(TRIM(B8))=0,LEN(TRIM(C8))=0,LEN(TRIM(D8))=0,LEN(TRIM(E8))=0,LEN(TRIM(F8))=0,LEN(TRIM(G8))=0,LEN(TRIM(H8))=0,LEN(TRIM(I8))=0,LEN(TRIM(J8))=0,LEN(TRIM(K8))=0,LEN(TRIM(L8))=0),"Undetermined - incomplete routing",IF(Q8<>"OK","Undetermined - unrecognized routing value",IF(OR(D8="High",D8="Catastrophic/systemic",E8="Material",E8="Fundamental or uncertain",F8="Difficult to reverse",F8="Irreversible or unknown",G8="National/transnational/ecological",H8="Frontier or unknown",I8="Affected-party dispute or unknown"),"AF-High-Consequence",IF(OR(D8="Moderate",E8="Limited reversible",F8="Partly reversible",G8="Regional/sectoral",H8="Novel",I8="High"),"AF-Standard","AF-Lite"))))) | O8: =IF(AND(M8="",N8=""),"",IF(AND(M8<>"",N8=""),"UNRECORDED",IF(AND(M8="",N8<>""),"ORPHAN_RECORDED",IF(M8=N8,"MATCH","MISMATCH")))) | Q8: =IF(COUNTA(A8:L8)=0,"",IF(AND(COUNTIF(Vocabulary!$C$5:$C$8,D8)=1,COUNTIF(Vocabulary!$D$5:$D$8,E8)=1,COUNTIF(Vocabulary!$E$5:$E$8,F8)=1,COUNTIF(Vocabulary!$F$5:$F$8,G8)=1,COUNTIF(Vocabulary!$G$5:$G$8,H8)=1,COUNTIF(Vocabulary!$H$5:$H$8,I8)=1,COUNTIF(Vocabulary!$I$5:$I$7,J8)=1,COUNTIF(Vocabulary!$I$5:$I$7,K8)=1,COUNTIF(Vocabulary!$J$5:$J$6,L8)=1),"OK","UNRECOGNISED_ROUTING_VALUE"))
M9: =IF(COUNTA(A9:L9)=0,"",IF(OR(LEN(TRIM(B9))=0,LEN(TRIM(C9))=0,LEN(TRIM(D9))=0,LEN(TRIM(E9))=0,LEN(TRIM(F9))=0,LEN(TRIM(G9))=0,LEN(TRIM(H9))=0,LEN(TRIM(I9))=0,LEN(TRIM(J9))=0,LEN(TRIM(K9))=0,LEN(TRIM(L9))=0),"Undetermined - incomplete routing",IF(Q9<>"OK","Undetermined - unrecognized routing value",IF(OR(D9="High",D9="Catastrophic/systemic",E9="Material",E9="Fundamental or uncertain",F9="Difficult to reverse",F9="Irreversible or unknown",G9="National/transnational/ecological",H9="Frontier or unknown",I9="Affected-party dispute or unknown"),"AF-High-Consequence",IF(OR(D9="Moderate",E9="Limited reversible",F9="Partly reversible",G9="Regional/sectoral",H9="Novel",I9="High"),"AF-Standard","AF-Lite"))))) | O9: =IF(AND(M9="",N9=""),"",IF(AND(M9<>"",N9=""),"UNRECORDED",IF(AND(M9="",N9<>""),"ORPHAN_RECORDED",IF(M9=N9,"MATCH","MISMATCH")))) | Q9: =IF(COUNTA(A9:L9)=0,"",IF(AND(COUNTIF(Vocabulary!$C$5:$C$8,D9)=1,COUNTIF(Vocabulary!$D$5:$D$8,E9)=1,COUNTIF(Vocabulary!$E$5:$E$8,F9)=1,COUNTIF(Vocabulary!$F$5:$F$8,G9)=1,COUNTIF(Vocabulary!$G$5:$G$8,H9)=1,COUNTIF(Vocabulary!$H$5:$H$8,I9)=1,COUNTIF(Vocabulary!$I$5:$I$7,J9)=1,COUNTIF(Vocabulary!$I$5:$I$7,K9)=1,COUNTIF(Vocabulary!$J$5:$J$6,L9)=1),"OK","UNRECOGNISED_ROUTING_VALUE"))
M10: =IF(COUNTA(A10:L10)=0,"",IF(OR(LEN(TRIM(B10))=0,LEN(TRIM(C10))=0,LEN(TRIM(D10))=0,LEN(TRIM(E10))=0,LEN(TRIM(F10))=0,LEN(TRIM(G10))=0,LEN(TRIM(H10))=0,LEN(TRIM(I10))=0,LEN(TRIM(J10))=0,LEN(TRIM(K10))=0,LEN(TRIM(L10))=0),"Undetermined - incomplete routing",IF(Q10<>"OK","Undetermined - unrecognized routing value",IF(OR(D10="High",D10="Catastrophic/systemic",E10="Material",E10="Fundamental or uncertain",F10="Difficult to reverse",F10="Irreversible or unknown",G10="National/transnational/ecological",H10="Frontier or unknown",I10="Affected-party dispute or unknown"),"AF-High-Consequence",IF(OR(D10="Moderate",E10="Limited reversible",F10="Partly reversible",G10="Regional/sectoral",H10="Novel",I10="High"),"AF-Standard","AF-Lite"))))) | O10: =IF(AND(M10="",N10=""),"",IF(AND(M10<>"",N10=""),"UNRECORDED",IF(AND(M10="",N10<>""),"ORPHAN_RECORDED",IF(M10=N10,"MATCH","MISMATCH")))) | Q10: =IF(COUNTA(A10:L10)=0,"",IF(AND(COUNTIF(Vocabulary!$C$5:$C$8,D10)=1,COUNTIF(Vocabulary!$D$5:$D$8,E10)=1,COUNTIF(Vocabulary!$E$5:$E$8,F10)=1,COUNTIF(Vocabulary!$F$5:$F$8,G10)=1,COUNTIF(Vocabulary!$G$5:$G$8,H10)=1,COUNTIF(Vocabulary!$H$5:$H$8,I10)=1,COUNTIF(Vocabulary!$I$5:$I$7,J10)=1,COUNTIF(Vocabulary!$I$5:$I$7,K10)=1,COUNTIF(Vocabulary!$J$5:$J$6,L10)=1),"OK","UNRECOGNISED_ROUTING_VALUE"))
M11: =IF(COUNTA(A11:L11)=0,"",IF(OR(LEN(TRIM(B11))=0,LEN(TRIM(C11))=0,LEN(TRIM(D11))=0,LEN(TRIM(E11))=0,LEN(TRIM(F11))=0,LEN(TRIM(G11))=0,LEN(TRIM(H11))=0,LEN(TRIM(I11))=0,LEN(TRIM(J11))=0,LEN(TRIM(K11))=0,LEN(TRIM(L11))=0),"Undetermined - incomplete routing",IF(Q11<>"OK","Undetermined - unrecognized routing value",IF(OR(D11="High",D11="Catastrophic/systemic",E11="Material",E11="Fundamental or uncertain",F11="Difficult to reverse",F11="Irreversible or unknown",G11="National/transnational/ecological",H11="Frontier or unknown",I11="Affected-party dispute or unknown"),"AF-High-Consequence",IF(OR(D11="Moderate",E11="Limited reversible",F11="Partly reversible",G11="Regional/sectoral",H11="Novel",I11="High"),"AF-Standard","AF-Lite"))))) | O11: =IF(AND(M11="",N11=""),"",IF(AND(M11<>"",N11=""),"UNRECORDED",IF(AND(M11="",N11<>""),"ORPHAN_RECORDED",IF(M11=N11,"MATCH","MISMATCH")))) | Q11: =IF(COUNTA(A11:L11)=0,"",IF(AND(COUNTIF(Vocabulary!$C$5:$C$8,D11)=1,COUNTIF(Vocabulary!$D$5:$D$8,E11)=1,COUNTIF(Vocabulary!$E$5:$E$8,F11)=1,COUNTIF(Vocabulary!$F$5:$F$8,G11)=1,COUNTIF(Vocabulary!$G$5:$G$8,H11)=1,COUNTIF(Vocabulary!$H$5:$H$8,I11)=1,COUNTIF(Vocabulary!$I$5:$I$7,J11)=1,COUNTIF(Vocabulary!$I$5:$I$7,K11)=1,COUNTIF(Vocabulary!$J$5:$J$6,L11)=1),"OK","UNRECOGNISED_ROUTING_VALUE"))
M12: =IF(COUNTA(A12:L12)=0,"",IF(OR(LEN(TRIM(B12))=0,LEN(TRIM(C12))=0,LEN(TRIM(D12))=0,LEN(TRIM(E12))=0,LEN(TRIM(F12))=0,LEN(TRIM(G12))=0,LEN(TRIM(H12))=0,LEN(TRIM(I12))=0,LEN(TRIM(J12))=0,LEN(TRIM(K12))=0,LEN(TRIM(L12))=0),"Undetermined - incomplete routing",IF(Q12<>"OK","Undetermined - unrecognized routing value",IF(OR(D12="High",D12="Catastrophic/systemic",E12="Material",E12="Fundamental or uncertain",F12="Difficult to reverse",F12="Irreversible or unknown",G12="National/transnational/ecological",H12="Frontier or unknown",I12="Affected-party dispute or unknown"),"AF-High-Consequence",IF(OR(D12="Moderate",E12="Limited reversible",F12="Partly reversible",G12="Regional/sectoral",H12="Novel",I12="High"),"AF-Standard","AF-Lite"))))) | O12: =IF(AND(M12="",N12=""),"",IF(AND(M12<>"",N12=""),"UNRECORDED",IF(AND(M12="",N12<>""),"ORPHAN_RECORDED",IF(M12=N12,"MATCH","MISMATCH")))) | Q12: =IF(COUNTA(A12:L12)=0,"",IF(AND(COUNTIF(Vocabulary!$C$5:$C$8,D12)=1,COUNTIF(Vocabulary!$D$5:$D$8,E12)=1,COUNTIF(Vocabulary!$E$5:$E$8,F12)=1,COUNTIF(Vocabulary!$F$5:$F$8,G12)=1,COUNTIF(Vocabulary!$G$5:$G$8,H12)=1,COUNTIF(Vocabulary!$H$5:$H$8,I12)=1,COUNTIF(Vocabulary!$I$5:$I$7,J12)=1,COUNTIF(Vocabulary!$I$5:$I$7,K12)=1,COUNTIF(Vocabulary!$J$5:$J$6,L12)=1),"OK","UNRECOGNISED_ROUTING_VALUE"))
M13: =IF(COUNTA(A13:L13)=0,"",IF(OR(LEN(TRIM(B13))=0,LEN(TRIM(C13))=0,LEN(TRIM(D13))=0,LEN(TRIM(E13))=0,LEN(TRIM(F13))=0,LEN(TRIM(G13))=0,LEN(TRIM(H13))=0,LEN(TRIM(I13))=0,LEN(TRIM(J13))=0,LEN(TRIM(K13))=0,LEN(TRIM(L13))=0),"Undetermined - incomplete routing",IF(Q13<>"OK","Undetermined - unrecognized routing value",IF(OR(D13="High",D13="Catastrophic/systemic",E13="Material",E13="Fundamental or uncertain",F13="Difficult to reverse",F13="Irreversible or unknown",G13="National/transnational/ecological",H13="Frontier or unknown",I13="Affected-party dispute or unknown"),"AF-High-Consequence",IF(OR(D13="Moderate",E13="Limited reversible",F13="Partly reversible",G13="Regional/sectoral",H13="Novel",I13="High"),"AF-Standard","AF-Lite"))))) | O13: =IF(AND(M13="",N13=""),"",IF(AND(M13<>"",N13=""),"UNRECORDED",IF(AND(M13="",N13<>""),"ORPHAN_RECORDED",IF(M13=N13,"MATCH","MISMATCH")))) | Q13: =IF(COUNTA(A13:L13)=0,"",IF(AND(COUNTIF(Vocabulary!$C$5:$C$8,D13)=1,COUNTIF(Vocabulary!$D$5:$D$8,E13)=1,COUNTIF(Vocabulary!$E$5:$E$8,F13)=1,COUNTIF(Vocabulary!$F$5:$F$8,G13)=1,COUNTIF(Vocabulary!$G$5:$G$8,H13)=1,COUNTIF(Vocabulary!$H$5:$H$8,I13)=1,COUNTIF(Vocabulary!$I$5:$I$7,J13)=1,COUNTIF(Vocabulary!$I$5:$I$7,K13)=1,COUNTIF(Vocabulary!$J$5:$J$6,L13)=1),"OK","UNRECOGNISED_ROUTING_VALUE"))
M14: =IF(COUNTA(A14:L14)=0,"",IF(OR(LEN(TRIM(B14))=0,LEN(TRIM(C14))=0,LEN(TRIM(D14))=0,LEN(TRIM(E14))=0,LEN(TRIM(F14))=0,LEN(TRIM(G14))=0,LEN(TRIM(H14))=0,LEN(TRIM(I14))=0,LEN(TRIM(J14))=0,LEN(TRIM(K14))=0,LEN(TRIM(L14))=0),"Undetermined - incomplete routing",IF(Q14<>"OK","Undetermined - unrecognized routing value",IF(OR(D14="High",D14="Catastrophic/systemic",E14="Material",E14="Fundamental or uncertain",F14="Difficult to reverse",F14="Irreversible or unknown",G14="National/transnational/ecological",H14="Frontier or unknown",I14="Affected-party dispute or unknown"),"AF-High-Consequence",IF(OR(D14="Moderate",E14="Limited reversible",F14="Partly reversible",G14="Regional/sectoral",H14="Novel",I14="High"),"AF-Standard","AF-Lite"))))) | O14: =IF(AND(M14="",N14=""),"",IF(AND(M14<>"",N14=""),"UNRECORDED",IF(AND(M14="",N14<>""),"ORPHAN_RECORDED",IF(M14=N14,"MATCH","MISMATCH")))) | Q14: =IF(COUNTA(A14:L14)=0,"",IF(AND(COUNTIF(Vocabulary!$C$5:$C$8,D14)=1,COUNTIF(Vocabulary!$D$5:$D$8,E14)=1,COUNTIF(Vocabulary!$E$5:$E$8,F14)=1,COUNTIF(Vocabulary!$F$5:$F$8,G14)=1,COUNTIF(Vocabulary!$G$5:$G$8,H14)=1,COUNTIF(Vocabulary!$H$5:$H$8,I14)=1,COUNTIF(Vocabulary!$I$5:$I$7,J14)=1,COUNTIF(Vocabulary!$I$5:$I$7,K14)=1,COUNTIF(Vocabulary!$J$5:$J$6,L14)=1),"OK","UNRECOGNISED_ROUTING_VALUE"))
M15: =IF(COUNTA(A15:L15)=0,"",IF(OR(LEN(TRIM(B15))=0,LEN(TRIM(C15))=0,LEN(TRIM(D15))=0,LEN(TRIM(E15))=0,LEN(TRIM(F15))=0,LEN(TRIM(G15))=0,LEN(TRIM(H15))=0,LEN(TRIM(I15))=0,LEN(TRIM(J15))=0,LEN(TRIM(K15))=0,LEN(TRIM(L15))=0),"Undetermined - incomplete routing",IF(Q15<>"OK","Undetermined - unrecognized routing value",IF(OR(D15="High",D15="Catastrophic/systemic",E15="Material",E15="Fundamental or uncertain",F15="Difficult to reverse",F15="Irreversible or unknown",G15="National/transnational/ecological",H15="Frontier or unknown",I15="Affected-party dispute or unknown"),"AF-High-Consequence",IF(OR(D15="Moderate",E15="Limited reversible",F15="Partly reversible",G15="Regional/sectoral",H15="Novel",I15="High"),"AF-Standard","AF-Lite"))))) | O15: =IF(AND(M15="",N15=""),"",IF(AND(M15<>"",N15=""),"UNRECORDED",IF(AND(M15="",N15<>""),"ORPHAN_RECORDED",IF(M15=N15,"MATCH","MISMATCH")))) | Q15: =IF(COUNTA(A15:L15)=0,"",IF(AND(COUNTIF(Vocabulary!$C$5:$C$8,D15)=1,COUNTIF(Vocabulary!$D$5:$D$8,E15)=1,COUNTIF(Vocabulary!$E$5:$E$8,F15)=1,COUNTIF(Vocabulary!$F$5:$F$8,G15)=1,COUNTIF(Vocabulary!$G$5:$G$8,H15)=1,COUNTIF(Vocabulary!$H$5:$H$8,I15)=1,COUNTIF(Vocabulary!$I$5:$I$7,J15)=1,COUNTIF(Vocabulary!$I$5:$I$7,K15)=1,COUNTIF(Vocabulary!$J$5:$J$6,L15)=1),"OK","UNRECOGNISED_ROUTING_VALUE"))
M16: =IF(COUNTA(A16:L16)=0,"",IF(OR(LEN(TRIM(B16))=0,LEN(TRIM(C16))=0,LEN(TRIM(D16))=0,LEN(TRIM(E16))=0,LEN(TRIM(F16))=0,LEN(TRIM(G16))=0,LEN(TRIM(H16))=0,LEN(TRIM(I16))=0,LEN(TRIM(J16))=0,LEN(TRIM(K16))=0,LEN(TRIM(L16))=0),"Undetermined - incomplete routing",IF(Q16<>"OK","Undetermined - unrecognized routing value",IF(OR(D16="High",D16="Catastrophic/systemic",E16="Material",E16="Fundamental or uncertain",F16="Difficult to reverse",F16="Irreversible or unknown",G16="National/transnational/ecological",H16="Frontier or unknown",I16="Affected-party dispute or unknown"),"AF-High-Consequence",IF(OR(D16="Moderate",E16="Limited reversible",F16="Partly reversible",G16="Regional/sectoral",H16="Novel",I16="High"),"AF-Standard","AF-Lite"))))) | O16: =IF(AND(M16="",N16=""),"",IF(AND(M16<>"",N16=""),"UNRECORDED",IF(AND(M16="",N16<>""),"ORPHAN_RECORDED",IF(M16=N16,"MATCH","MISMATCH")))) | Q16: =IF(COUNTA(A16:L16)=0,"",IF(AND(COUNTIF(Vocabulary!$C$5:$C$8,D16)=1,COUNTIF(Vocabulary!$D$5:$D$8,E16)=1,COUNTIF(Vocabulary!$E$5:$E$8,F16)=1,COUNTIF(Vocabulary!$F$5:$F$8,G16)=1,COUNTIF(Vocabulary!$G$5:$G$8,H16)=1,COUNTIF(Vocabulary!$H$5:$H$8,I16)=1,COUNTIF(Vocabulary!$I$5:$I$7,J16)=1,COUNTIF(Vocabulary!$I$5:$I$7,K16)=1,COUNTIF(Vocabulary!$J$5:$J$6,L16)=1),"OK","UNRECOGNISED_ROUTING_VALUE"))
M17: =IF(COUNTA(A17:L17)=0,"",IF(OR(LEN(TRIM(B17))=0,LEN(TRIM(C17))=0,LEN(TRIM(D17))=0,LEN(TRIM(E17))=0,LEN(TRIM(F17))=0,LEN(TRIM(G17))=0,LEN(TRIM(H17))=0,LEN(TRIM(I17))=0,LEN(TRIM(J17))=0,LEN(TRIM(K17))=0,LEN(TRIM(L17))=0),"Undetermined - incomplete routing",IF(Q17<>"OK","Undetermined - unrecognized routing value",IF(OR(D17="High",D17="Catastrophic/systemic",E17="Material",E17="Fundamental or uncertain",F17="Difficult to reverse",F17="Irreversible or unknown",G17="National/transnational/ecological",H17="Frontier or unknown",I17="Affected-party dispute or unknown"),"AF-High-Consequence",IF(OR(D17="Moderate",E17="Limited reversible",F17="Partly reversible",G17="Regional/sectoral",H17="Novel",I17="High"),"AF-Standard","AF-Lite"))))) | O17: =IF(AND(M17="",N17=""),"",IF(AND(M17<>"",N17=""),"UNRECORDED",IF(AND(M17="",N17<>""),"ORPHAN_RECORDED",IF(M17=N17,"MATCH","MISMATCH")))) | Q17: =IF(COUNTA(A17:L17)=0,"",IF(AND(COUNTIF(Vocabulary!$C$5:$C$8,D17)=1,COUNTIF(Vocabulary!$D$5:$D$8,E17)=1,COUNTIF(Vocabulary!$E$5:$E$8,F17)=1,COUNTIF(Vocabulary!$F$5:$F$8,G17)=1,COUNTIF(Vocabulary!$G$5:$G$8,H17)=1,COUNTIF(Vocabulary!$H$5:$H$8,I17)=1,COUNTIF(Vocabulary!$I$5:$I$7,J17)=1,COUNTIF(Vocabulary!$I$5:$I$7,K17)=1,COUNTIF(Vocabulary!$J$5:$J$6,L17)=1),"OK","UNRECOGNISED_ROUTING_VALUE"))
... M250: =IF(COUNTA(A250:L250)=0,"",IF(OR(LEN(TRIM(B250))=0,LEN(TRIM(C250))=0,LEN(TRIM(D250))=0,LEN(TRIM(E250))=0,LEN(TRIM(F250))=0,LEN(TRIM(G250))=0,LEN(TRIM(H250))=0,LEN(TRIM(I250))=0,LEN(TRIM(J250))=0,LEN(TRIM(K250))=0,LEN(TRIM(L250))=0),"Undetermined - incomplete routing",IF(Q250<>"OK","Undetermined - unrecognized routing value",IF(OR(D250="High",D250="Catastrophic/systemic",E250="Material",E250="Fundamental or uncertain",F250="Difficult to reverse",F250="Irreversible or unknown",G250="National/transnational/ecological",H250="Frontier or unknown",I250="Affected-party dispute or unknown"),"AF-High-Consequence",IF(OR(D250="Moderate",E250="Limited reversible",F250="Partly reversible",G250="Regional/sectoral",H250="Novel",I250="High"),"AF-Standard","AF-Lite"))))) | O250: =IF(AND(M250="",N250=""),"",IF(AND(M250<>"",N250=""),"UNRECORDED",IF(AND(M250="",N250<>""),"ORPHAN_RECORDED",IF(M250=N250,"MATCH","MISMATCH")))) | Q250: =IF(COUNTA(A250:L250)=0,"",IF(AND(COUNTIF(Vocabulary!$C$5:$C$8,D250)=1,COUNTIF(Vocabulary!$D$5:$D$8,E250)=1,COUNTIF(Vocabulary!$E$5:$E$8,F250)=1,COUNTIF(Vocabulary!$F$5:$F$8,G250)=1,COUNTIF(Vocabulary!$G$5:$G$8,H250)=1,COUNTIF(Vocabulary!$H$5:$H$8,I250)=1,COUNTIF(Vocabulary!$I$5:$I$7,J250)=1,COUNTIF(Vocabulary!$I$5:$I$7,K250)=1,COUNTIF(Vocabulary!$J$5:$J$6,L250)=1),"OK","UNRECOGNISED_ROUTING_VALUE"))

Sheet Candidate_Register
A1: Candidate and Scope Register - AF v6.2
A3: Candidate_ID | B3: Candidate_Name | C3: Version_or_Hash | D3: Architecture_Family | E3: Declared_Authority_Claim | F3: Scope_ID | G3: Population | H3: Jurisdiction_or_Community | I3: Evidence_Cutoff | J3: Candidate_Contact | K3: Affected_Party_Liaison | L3: Access_Needs | M3: Data_Sovereignty_Constraints | N3: Profile | O3: Record_Status
A4: SYNTH-CAND-HC | B4: Synthetic benefits architecture | C4: hash:illustrative | D4: legal-institutional | E4: Advisory recommendation only | F4: SCOPE-ILL-001 | G4: Synthetic national population | H4: Synthetic jurisdiction | I4: 2026-08-11 | J4: candidate@example.invalid | K4: liaison@example.invalid | L4: Interpretation and accessible formats | M4: No raw community evidence outside host repository | N4: AF-High-Consequence | O4: Illustrative

Sheet Stage_A
A1: Stage A Non-Compensatory Eligibility Record - AF v6.2
A3: Review_ID | B3: Candidate_ID | C3: Scope_ID | D3: Profile | E3: Evidence_Cutoff | F3: Host_ID | G3: Independence_Dossier_ID | H3: Administration_Valid | I3: Burden_Feasibility | J3: Protected_Floor_Unresolved | K3: C0_Inspectability | L3: C1_Rights | M3: C2_Auditability | N3: C3_Measurement | O3: C4_Corrigibility | P3: C5_Refusal_Authority | Q3: Derived_Overall_Status | R3: Recorded_Overall_Status | S3: Status_Match | T3: Public_Status_String | U3: Root_Cause_Map_ID | V3: Dissent_Refs | W3: Affected_Party_Refs | X3: Appeal_Route | Y3: Issued_At | Z3: Expiry_or_Requalification | AA3: Unpatchable_Count | AB3: Patchable_Count | AC3: Indeterminate_Count | AD3: Controlled_Adequacy_Count | AE3: Eligibility_Gate | AF3: Canonical_Status_Token | AG3: Public_String_Check | AH3: Adequate_Count | AI3: Criterion_Value_Check | AJ3: Administrative_Disposition | AK3: Protocol_Version | AL3: Constitutional_Legitimacy_Basis | AM3: Administrative_Disposition_Check
A4: SAR-ILL-001 | B4: SYNTH-CAND-HC | C4: SCOPE-ILL-001 | D4: AF-High-Consequence | E4: 2026-08-11 | F4: HOST-INDEPENDENT-01 | G4: IND-ILL-001 | H4: Yes | I4: Feasible with verified support | J4: No | K4: Adequate for scope | L4: Adequate for scope | M4: Adequate for scope | N4: Material defect - patchable | O4: Adequate for scope | P4: Adequate for scope | Q4: =IF(AE4="","",IF(AE4="ADMIN_DISPOSITION",AJ4,IF(OR(AE4="ADMIN_INCOMPLETE",AE4="ADMIN_INVALID",AE4="BURDEN_NOT_FEASIBLE",AE4="UNRECOGNISED_VALUE",AE4="UNRECOGNISED_ADMIN_DISPOSITION"),"Protocol refusal to evaluate",IF(AA4>0,"Stage-A non-admissible - unpatchable for stated claim",IF(AB4>0,"Stage-A non-admissible - patchable",IF(OR(J4="Yes",I4="Indeterminate",AC4>0),"Indeterminate - insufficient evidence",IF(AND(AH4=6,AD4=0),"Stage-A admissible - scoped",IF(AND(AH4+AD4=6,AD4>0),"Stage-A admissible - scoped, control-dependent","Protocol refusal to evaluate")))))))) | R4: Stage-A non-admissible - patchable | S4: =IF(AND(Q4="",R4=""),"",IF(AND(Q4<>"",R4=""),"UNRECORDED",IF(AND(Q4="",R4<>""),"ORPHAN_RECORDED",IF(Q4=R4,"MATCH","MISMATCH")))) | T4: Stage-A non-admissible - patchable | token=stage_a_non_admissible_patchable; | Candidate SYNTH-CAND-HC | Scope SCOPE-ILL-001 | Evidence cutoff 2026-08-11 | AF v6.2 | CL basis=CL1 self-assessment; CL2 design materials only; | U4: RCM-ILL-001 | V4: DISSENT-ILL-001 | W4: AP-ILL-001 | X4: Independent appeal panel | Y4: 2026-08-11 12:00Z | Z4: 2027-02-11 12:00Z | AA4: =COUNTIF(K4:P4,"Material defect - unpatchable for stated claim") | AB4: =COUNTIF(K4:P4,"Material defect - patchable") | AC4: =COUNTIF(K4:P4,"Indeterminate")+COUNTIF(K4:P4,"Not reviewed") | AD4: =COUNTIF(K4:P4,"Adequate - control-dependent") | AE4: =IF(COUNTA(A4:P4)+COUNTA(AJ4)=0,"",IF(AM4<>"OK","UNRECOGNISED_ADMIN_DISPOSITION",IF(AND(AJ4<>"",AJ4<>"None"),IF(OR(LEN(TRIM(A4))=0,LEN(TRIM(B4))=0,LEN(TRIM(C4))=0,LEN(TRIM(F4))=0),"ADMIN_INCOMPLETE","ADMIN_DISPOSITION"),IF(OR(LEN(TRIM(A4))=0,LEN(TRIM(B4))=0,LEN(TRIM(C4))=0,LEN(TRIM(D4))=0,LEN(TRIM(E4))=0,LEN(TRIM(F4))=0,LEN(TRIM(G4))=0,LEN(TRIM(H4))=0,LEN(TRIM(I4))=0,LEN(TRIM(J4))=0,LEN(TRIM(K4))=0,LEN(TRIM(L4))=0,LEN(TRIM(M4))=0,LEN(TRIM(N4))=0,LEN(TRIM(O4))=0,LEN(TRIM(P4))=0),"ADMIN_INCOMPLETE",IF(H4<>"Yes","ADMIN_INVALID",IF(I4="Not feasible","BURDEN_NOT_FEASIBLE",IF(AI4<>"OK","UNRECOGNISED_VALUE","CLEAR"))))))) | AF4: =IF(AND(Q4="",R4=""),"",IF(IF(Q4<>"",Q4,R4)="Stage-A admissible - scoped","stage_a_admissible_scoped",IF(IF(Q4<>"",Q4,R4)="Stage-A admissible - scoped, control-dependent","stage_a_admissible_scoped_control_dependent",IF(IF(Q4<>"",Q4,R4)="Stage-A non-admissible - patchable","stage_a_non_admissible_patchable",IF(IF(Q4<>"",Q4,R4)="Stage-A non-admissible - unpatchable for stated claim","stage_a_non_admissible_unpatchable_for_stated_claim",IF(IF(Q4<>"",Q4,R4)="Indeterminate - insufficient evidence","indeterminate_insufficient_evidence",IF(IF(Q4<>"",Q4,R4)="Protocol refusal to evaluate","protocol_refusal_to_evaluate",IF(IF(Q4<>"",Q4,R4)="Out of scope","out_of_scope",IF(IF(Q4<>"",Q4,R4)="Withdrawn","withdrawn",IF(IF(Q4<>"",Q4,R4)="Not reviewed","not_reviewed","unknown_status")))))))))) | AG4: =IF(AND(AF4="",T4=""),"",IF(AND(AF4<>"",ISNUMBER(SEARCH("token="&AF4&";",T4)),ISNUMBER(SEARCH(AK4,T4)),ISNUMBER(SEARCH("CL basis="&AL4&";",T4))),"VALID","INVALID_OR_INCOMPLETE")) | AH4: =COUNTIF(K4:P4,"Adequate for scope") | AI4: =IF(COUNTA(K4:P4)=0,"",IF(AA4+AB4+AC4+AD4+AH4=6,"OK","UNRECOGNISED_VALUE")) | AK4: =IF(A4="","",Vocabulary!$B$5) | AL4: =IF(A4="","",Vocabulary!$B$6) | AM4: =IF(AJ4="","OK",IF(COUNTIF(Vocabulary!$O$5:$O$8,AJ4)=1,"OK","UNRECOGNISED_ADMIN_DISPOSITION"))
Q5: =IF(AE5="","",IF(AE5="ADMIN_DISPOSITION",AJ5,IF(OR(AE5="ADMIN_INCOMPLETE",AE5="ADMIN_INVALID",AE5="BURDEN_NOT_FEASIBLE",AE5="UNRECOGNISED_VALUE",AE5="UNRECOGNISED_ADMIN_DISPOSITION"),"Protocol refusal to evaluate",IF(AA5>0,"Stage-A non-admissible - unpatchable for stated claim",IF(AB5>0,"Stage-A non-admissible - patchable",IF(OR(J5="Yes",I5="Indeterminate",AC5>0),"Indeterminate - insufficient evidence",IF(AND(AH5=6,AD5=0),"Stage-A admissible - scoped",IF(AND(AH5+AD5=6,AD5>0),"Stage-A admissible - scoped, control-dependent","Protocol refusal to evaluate")))))))) | S5: =IF(AND(Q5="",R5=""),"",IF(AND(Q5<>"",R5=""),"UNRECORDED",IF(AND(Q5="",R5<>""),"ORPHAN_RECORDED",IF(Q5=R5,"MATCH","MISMATCH")))) | AA5: =COUNTIF(K5:P5,"Material defect - unpatchable for stated claim") | AB5: =COUNTIF(K5:P5,"Material defect - patchable") | AC5: =COUNTIF(K5:P5,"Indeterminate")+COUNTIF(K5:P5,"Not reviewed") | AD5: =COUNTIF(K5:P5,"Adequate - control-dependent") | AE5: =IF(COUNTA(A5:P5)+COUNTA(AJ5)=0,"",IF(AM5<>"OK","UNRECOGNISED_ADMIN_DISPOSITION",IF(AND(AJ5<>"",AJ5<>"None"),IF(OR(LEN(TRIM(A5))=0,LEN(TRIM(B5))=0,LEN(TRIM(C5))=0,LEN(TRIM(F5))=0),"ADMIN_INCOMPLETE","ADMIN_DISPOSITION"),IF(OR(LEN(TRIM(A5))=0,LEN(TRIM(B5))=0,LEN(TRIM(C5))=0,LEN(TRIM(D5))=0,LEN(TRIM(E5))=0,LEN(TRIM(F5))=0,LEN(TRIM(G5))=0,LEN(TRIM(H5))=0,LEN(TRIM(I5))=0,LEN(TRIM(J5))=0,LEN(TRIM(K5))=0,LEN(TRIM(L5))=0,LEN(TRIM(M5))=0,LEN(TRIM(N5))=0,LEN(TRIM(O5))=0,LEN(TRIM(P5))=0),"ADMIN_INCOMPLETE",IF(H5<>"Yes","ADMIN_INVALID",IF(I5="Not feasible","BURDEN_NOT_FEASIBLE",IF(AI5<>"OK","UNRECOGNISED_VALUE","CLEAR"))))))) | AF5: =IF(AND(Q5="",R5=""),"",IF(IF(Q5<>"",Q5,R5)="Stage-A admissible - scoped","stage_a_admissible_scoped",IF(IF(Q5<>"",Q5,R5)="Stage-A admissible - scoped, control-dependent","stage_a_admissible_scoped_control_dependent",IF(IF(Q5<>"",Q5,R5)="Stage-A non-admissible - patchable","stage_a_non_admissible_patchable",IF(IF(Q5<>"",Q5,R5)="Stage-A non-admissible - unpatchable for stated claim","stage_a_non_admissible_unpatchable_for_stated_claim",IF(IF(Q5<>"",Q5,R5)="Indeterminate - insufficient evidence","indeterminate_insufficient_evidence",IF(IF(Q5<>"",Q5,R5)="Protocol refusal to evaluate","protocol_refusal_to_evaluate",IF(IF(Q5<>"",Q5,R5)="Out of scope","out_of_scope",IF(IF(Q5<>"",Q5,R5)="Withdrawn","withdrawn",IF(IF(Q5<>"",Q5,R5)="Not reviewed","not_reviewed","unknown_status")))))))))) | AG5: =IF(AND(AF5="",T5=""),"",IF(AND(AF5<>"",ISNUMBER(SEARCH("token="&AF5&";",T5)),ISNUMBER(SEARCH(AK5,T5)),ISNUMBER(SEARCH("CL basis="&AL5&";",T5))),"VALID","INVALID_OR_INCOMPLETE")) | AH5: =COUNTIF(K5:P5,"Adequate for scope") | AI5: =IF(COUNTA(K5:P5)=0,"",IF(AA5+AB5+AC5+AD5+AH5=6,"OK","UNRECOGNISED_VALUE")) | AK5: =IF(A5="","",Vocabulary!$B$5) | AL5: =IF(A5="","",Vocabulary!$B$6) | AM5: =IF(AJ5="","OK",IF(COUNTIF(Vocabulary!$O$5:$O$8,AJ5)=1,"OK","UNRECOGNISED_ADMIN_DISPOSITION"))
Q6: =IF(AE6="","",IF(AE6="ADMIN_DISPOSITION",AJ6,IF(OR(AE6="ADMIN_INCOMPLETE",AE6="ADMIN_INVALID",AE6="BURDEN_NOT_FEASIBLE",AE6="UNRECOGNISED_VALUE",AE6="UNRECOGNISED_ADMIN_DISPOSITION"),"Protocol refusal to evaluate",IF(AA6>0,"Stage-A non-admissible - unpatchable for stated claim",IF(AB6>0,"Stage-A non-admissible - patchable",IF(OR(J6="Yes",I6="Indeterminate",AC6>0),"Indeterminate - insufficient evidence",IF(AND(AH6=6,AD6=0),"Stage-A admissible - scoped",IF(AND(AH6+AD6=6,AD6>0),"Stage-A admissible - scoped, control-dependent","Protocol refusal to evaluate")))))))) | S6: =IF(AND(Q6="",R6=""),"",IF(AND(Q6<>"",R6=""),"UNRECORDED",IF(AND(Q6="",R6<>""),"ORPHAN_RECORDED",IF(Q6=R6,"MATCH","MISMATCH")))) | AA6: =COUNTIF(K6:P6,"Material defect - unpatchable for stated claim") | AB6: =COUNTIF(K6:P6,"Material defect - patchable") | AC6: =COUNTIF(K6:P6,"Indeterminate")+COUNTIF(K6:P6,"Not reviewed") | AD6: =COUNTIF(K6:P6,"Adequate - control-dependent") | AE6: =IF(COUNTA(A6:P6)+COUNTA(AJ6)=0,"",IF(AM6<>"OK","UNRECOGNISED_ADMIN_DISPOSITION",IF(AND(AJ6<>"",AJ6<>"None"),IF(OR(LEN(TRIM(A6))=0,LEN(TRIM(B6))=0,LEN(TRIM(C6))=0,LEN(TRIM(F6))=0),"ADMIN_INCOMPLETE","ADMIN_DISPOSITION"),IF(OR(LEN(TRIM(A6))=0,LEN(TRIM(B6))=0,LEN(TRIM(C6))=0,LEN(TRIM(D6))=0,LEN(TRIM(E6))=0,LEN(TRIM(F6))=0,LEN(TRIM(G6))=0,LEN(TRIM(H6))=0,LEN(TRIM(I6))=0,LEN(TRIM(J6))=0,LEN(TRIM(K6))=0,LEN(TRIM(L6))=0,LEN(TRIM(M6))=0,LEN(TRIM(N6))=0,LEN(TRIM(O6))=0,LEN(TRIM(P6))=0),"ADMIN_INCOMPLETE",IF(H6<>"Yes","ADMIN_INVALID",IF(I6="Not feasible","BURDEN_NOT_FEASIBLE",IF(AI6<>"OK","UNRECOGNISED_VALUE","CLEAR"))))))) | AF6: =IF(AND(Q6="",R6=""),"",IF(IF(Q6<>"",Q6,R6)="Stage-A admissible - scoped","stage_a_admissible_scoped",IF(IF(Q6<>"",Q6,R6)="Stage-A admissible - scoped, control-dependent","stage_a_admissible_scoped_control_dependent",IF(IF(Q6<>"",Q6,R6)="Stage-A non-admissible - patchable","stage_a_non_admissible_patchable",IF(IF(Q6<>"",Q6,R6)="Stage-A non-admissible - unpatchable for stated claim","stage_a_non_admissible_unpatchable_for_stated_claim",IF(IF(Q6<>"",Q6,R6)="Indeterminate - insufficient evidence","indeterminate_insufficient_evidence",IF(IF(Q6<>"",Q6,R6)="Protocol refusal to evaluate","protocol_refusal_to_evaluate",IF(IF(Q6<>"",Q6,R6)="Out of scope","out_of_scope",IF(IF(Q6<>"",Q6,R6)="Withdrawn","withdrawn",IF(IF(Q6<>"",Q6,R6)="Not reviewed","not_reviewed","unknown_status")))))))))) | AG6: =IF(AND(AF6="",T6=""),"",IF(AND(AF6<>"",ISNUMBER(SEARCH("token="&AF6&";",T6)),ISNUMBER(SEARCH(AK6,T6)),ISNUMBER(SEARCH("CL basis="&AL6&";",T6))),"VALID","INVALID_OR_INCOMPLETE")) | AH6: =COUNTIF(K6:P6,"Adequate for scope") | AI6: =IF(COUNTA(K6:P6)=0,"",IF(AA6+AB6+AC6+AD6+AH6=6,"OK","UNRECOGNISED_VALUE")) | AK6: =IF(A6="","",Vocabulary!$B$5) | AL6: =IF(A6="","",Vocabulary!$B$6) | AM6: =IF(AJ6="","OK",IF(COUNTIF(Vocabulary!$O$5:$O$8,AJ6)=1,"OK","UNRECOGNISED_ADMIN_DISPOSITION"))
Q7: =IF(AE7="","",IF(AE7="ADMIN_DISPOSITION",AJ7,IF(OR(AE7="ADMIN_INCOMPLETE",AE7="ADMIN_INVALID",AE7="BURDEN_NOT_FEASIBLE",AE7="UNRECOGNISED_VALUE",AE7="UNRECOGNISED_ADMIN_DISPOSITION"),"Protocol refusal to evaluate",IF(AA7>0,"Stage-A non-admissible - unpatchable for stated claim",IF(AB7>0,"Stage-A non-admissible - patchable",IF(OR(J7="Yes",I7="Indeterminate",AC7>0),"Indeterminate - insufficient evidence",IF(AND(AH7=6,AD7=0),"Stage-A admissible - scoped",IF(AND(AH7+AD7=6,AD7>0),"Stage-A admissible - scoped, control-dependent","Protocol refusal to evaluate")))))))) | S7: =IF(AND(Q7="",R7=""),"",IF(AND(Q7<>"",R7=""),"UNRECORDED",IF(AND(Q7="",R7<>""),"ORPHAN_RECORDED",IF(Q7=R7,"MATCH","MISMATCH")))) | AA7: =COUNTIF(K7:P7,"Material defect - unpatchable for stated claim") | AB7: =COUNTIF(K7:P7,"Material defect - patchable") | AC7: =COUNTIF(K7:P7,"Indeterminate")+COUNTIF(K7:P7,"Not reviewed") | AD7: =COUNTIF(K7:P7,"Adequate - control-dependent") | AE7: =IF(COUNTA(A7:P7)+COUNTA(AJ7)=0,"",IF(AM7<>"OK","UNRECOGNISED_ADMIN_DISPOSITION",IF(AND(AJ7<>"",AJ7<>"None"),IF(OR(LEN(TRIM(A7))=0,LEN(TRIM(B7))=0,LEN(TRIM(C7))=0,LEN(TRIM(F7))=0),"ADMIN_INCOMPLETE","ADMIN_DISPOSITION"),IF(OR(LEN(TRIM(A7))=0,LEN(TRIM(B7))=0,LEN(TRIM(C7))=0,LEN(TRIM(D7))=0,LEN(TRIM(E7))=0,LEN(TRIM(F7))=0,LEN(TRIM(G7))=0,LEN(TRIM(H7))=0,LEN(TRIM(I7))=0,LEN(TRIM(J7))=0,LEN(TRIM(K7))=0,LEN(TRIM(L7))=0,LEN(TRIM(M7))=0,LEN(TRIM(N7))=0,LEN(TRIM(O7))=0,LEN(TRIM(P7))=0),"ADMIN_INCOMPLETE",IF(H7<>"Yes","ADMIN_INVALID",IF(I7="Not feasible","BURDEN_NOT_FEASIBLE",IF(AI7<>"OK","UNRECOGNISED_VALUE","CLEAR"))))))) | AF7: =IF(AND(Q7="",R7=""),"",IF(IF(Q7<>"",Q7,R7)="Stage-A admissible - scoped","stage_a_admissible_scoped",IF(IF(Q7<>"",Q7,R7)="Stage-A admissible - scoped, control-dependent","stage_a_admissible_scoped_control_dependent",IF(IF(Q7<>"",Q7,R7)="Stage-A non-admissible - patchable","stage_a_non_admissible_patchable",IF(IF(Q7<>"",Q7,R7)="Stage-A non-admissible - unpatchable for stated claim","stage_a_non_admissible_unpatchable_for_stated_claim",IF(IF(Q7<>"",Q7,R7)="Indeterminate - insufficient evidence","indeterminate_insufficient_evidence",IF(IF(Q7<>"",Q7,R7)="Protocol refusal to evaluate","protocol_refusal_to_evaluate",IF(IF(Q7<>"",Q7,R7)="Out of scope","out_of_scope",IF(IF(Q7<>"",Q7,R7)="Withdrawn","withdrawn",IF(IF(Q7<>"",Q7,R7)="Not reviewed","not_reviewed","unknown_status")))))))))) | AG7: =IF(AND(AF7="",T7=""),"",IF(AND(AF7<>"",ISNUMBER(SEARCH("token="&AF7&";",T7)),ISNUMBER(SEARCH(AK7,T7)),ISNUMBER(SEARCH("CL basis="&AL7&";",T7))),"VALID","INVALID_OR_INCOMPLETE")) | AH7: =COUNTIF(K7:P7,"Adequate for scope") | AI7: =IF(COUNTA(K7:P7)=0,"",IF(AA7+AB7+AC7+AD7+AH7=6,"OK","UNRECOGNISED_VALUE")) | AK7: =IF(A7="","",Vocabulary!$B$5) | AL7: =IF(A7="","",Vocabulary!$B$6) | AM7: =IF(AJ7="","OK",IF(COUNTIF(Vocabulary!$O$5:$O$8,AJ7)=1,"OK","UNRECOGNISED_ADMIN_DISPOSITION"))
Q8: =IF(AE8="","",IF(AE8="ADMIN_DISPOSITION",AJ8,IF(OR(AE8="ADMIN_INCOMPLETE",AE8="ADMIN_INVALID",AE8="BURDEN_NOT_FEASIBLE",AE8="UNRECOGNISED_VALUE",AE8="UNRECOGNISED_ADMIN_DISPOSITION"),"Protocol refusal to evaluate",IF(AA8>0,"Stage-A non-admissible - unpatchable for stated claim",IF(AB8>0,"Stage-A non-admissible - patchable",IF(OR(J8="Yes",I8="Indeterminate",AC8>0),"Indeterminate - insufficient evidence",IF(AND(AH8=6,AD8=0),"Stage-A admissible - scoped",IF(AND(AH8+AD8=6,AD8>0),"Stage-A admissible - scoped, control-dependent","Protocol refusal to evaluate")))))))) | S8: =IF(AND(Q8="",R8=""),"",IF(AND(Q8<>"",R8=""),"UNRECORDED",IF(AND(Q8="",R8<>""),"ORPHAN_RECORDED",IF(Q8=R8,"MATCH","MISMATCH")))) | AA8: =COUNTIF(K8:P8,"Material defect - unpatchable for stated claim") | AB8: =COUNTIF(K8:P8,"Material defect - patchable") | AC8: =COUNTIF(K8:P8,"Indeterminate")+COUNTIF(K8:P8,"Not reviewed") | AD8: =COUNTIF(K8:P8,"Adequate - control-dependent") | AE8: =IF(COUNTA(A8:P8)+COUNTA(AJ8)=0,"",IF(AM8<>"OK","UNRECOGNISED_ADMIN_DISPOSITION",IF(AND(AJ8<>"",AJ8<>"None"),IF(OR(LEN(TRIM(A8))=0,LEN(TRIM(B8))=0,LEN(TRIM(C8))=0,LEN(TRIM(F8))=0),"ADMIN_INCOMPLETE","ADMIN_DISPOSITION"),IF(OR(LEN(TRIM(A8))=0,LEN(TRIM(B8))=0,LEN(TRIM(C8))=0,LEN(TRIM(D8))=0,LEN(TRIM(E8))=0,LEN(TRIM(F8))=0,LEN(TRIM(G8))=0,LEN(TRIM(H8))=0,LEN(TRIM(I8))=0,LEN(TRIM(J8))=0,LEN(TRIM(K8))=0,LEN(TRIM(L8))=0,LEN(TRIM(M8))=0,LEN(TRIM(N8))=0,LEN(TRIM(O8))=0,LEN(TRIM(P8))=0),"ADMIN_INCOMPLETE",IF(H8<>"Yes","ADMIN_INVALID",IF(I8="Not feasible","BURDEN_NOT_FEASIBLE",IF(AI8<>"OK","UNRECOGNISED_VALUE","CLEAR"))))))) | AF8: =IF(AND(Q8="",R8=""),"",IF(IF(Q8<>"",Q8,R8)="Stage-A admissible - scoped","stage_a_admissible_scoped",IF(IF(Q8<>"",Q8,R8)="Stage-A admissible - scoped, control-dependent","stage_a_admissible_scoped_control_dependent",IF(IF(Q8<>"",Q8,R8)="Stage-A non-admissible - patchable","stage_a_non_admissible_patchable",IF(IF(Q8<>"",Q8,R8)="Stage-A non-admissible - unpatchable for stated claim","stage_a_non_admissible_unpatchable_for_stated_claim",IF(IF(Q8<>"",Q8,R8)="Indeterminate - insufficient evidence","indeterminate_insufficient_evidence",IF(IF(Q8<>"",Q8,R8)="Protocol refusal to evaluate","protocol_refusal_to_evaluate",IF(IF(Q8<>"",Q8,R8)="Out of scope","out_of_scope",IF(IF(Q8<>"",Q8,R8)="Withdrawn","withdrawn",IF(IF(Q8<>"",Q8,R8)="Not reviewed","not_reviewed","unknown_status")))))))))) | AG8: =IF(AND(AF8="",T8=""),"",IF(AND(AF8<>"",ISNUMBER(SEARCH("token="&AF8&";",T8)),ISNUMBER(SEARCH(AK8,T8)),ISNUMBER(SEARCH("CL basis="&AL8&";",T8))),"VALID","INVALID_OR_INCOMPLETE")) | AH8: =COUNTIF(K8:P8,"Adequate for scope") | AI8: =IF(COUNTA(K8:P8)=0,"",IF(AA8+AB8+AC8+AD8+AH8=6,"OK","UNRECOGNISED_VALUE")) | AK8: =IF(A8="","",Vocabulary!$B$5) | AL8: =IF(A8="","",Vocabulary!$B$6) | AM8: =IF(AJ8="","OK",IF(COUNTIF(Vocabulary!$O$5:$O$8,AJ8)=1,"OK","UNRECOGNISED_ADMIN_DISPOSITION"))
Q9: =IF(AE9="","",IF(AE9="ADMIN_DISPOSITION",AJ9,IF(OR(AE9="ADMIN_INCOMPLETE",AE9="ADMIN_INVALID",AE9="BURDEN_NOT_FEASIBLE",AE9="UNRECOGNISED_VALUE",AE9="UNRECOGNISED_ADMIN_DISPOSITION"),"Protocol refusal to evaluate",IF(AA9>0,"Stage-A non-admissible - unpatchable for stated claim",IF(AB9>0,"Stage-A non-admissible - patchable",IF(OR(J9="Yes",I9="Indeterminate",AC9>0),"Indeterminate - insufficient evidence",IF(AND(AH9=6,AD9=0),"Stage-A admissible - scoped",IF(AND(AH9+AD9=6,AD9>0),"Stage-A admissible - scoped, control-dependent","Protocol refusal to evaluate")))))))) | S9: =IF(AND(Q9="",R9=""),"",IF(AND(Q9<>"",R9=""),"UNRECORDED",IF(AND(Q9="",R9<>""),"ORPHAN_RECORDED",IF(Q9=R9,"MATCH","MISMATCH")))) | AA9: =COUNTIF(K9:P9,"Material defect - unpatchable for stated claim") | AB9: =COUNTIF(K9:P9,"Material defect - patchable") | AC9: =COUNTIF(K9:P9,"Indeterminate")+COUNTIF(K9:P9,"Not reviewed") | AD9: =COUNTIF(K9:P9,"Adequate - control-dependent") | AE9: =IF(COUNTA(A9:P9)+COUNTA(AJ9)=0,"",IF(AM9<>"OK","UNRECOGNISED_ADMIN_DISPOSITION",IF(AND(AJ9<>"",AJ9<>"None"),IF(OR(LEN(TRIM(A9))=0,LEN(TRIM(B9))=0,LEN(TRIM(C9))=0,LEN(TRIM(F9))=0),"ADMIN_INCOMPLETE","ADMIN_DISPOSITION"),IF(OR(LEN(TRIM(A9))=0,LEN(TRIM(B9))=0,LEN(TRIM(C9))=0,LEN(TRIM(D9))=0,LEN(TRIM(E9))=0,LEN(TRIM(F9))=0,LEN(TRIM(G9))=0,LEN(TRIM(H9))=0,LEN(TRIM(I9))=0,LEN(TRIM(J9))=0,LEN(TRIM(K9))=0,LEN(TRIM(L9))=0,LEN(TRIM(M9))=0,LEN(TRIM(N9))=0,LEN(TRIM(O9))=0,LEN(TRIM(P9))=0),"ADMIN_INCOMPLETE",IF(H9<>"Yes","ADMIN_INVALID",IF(I9="Not feasible","BURDEN_NOT_FEASIBLE",IF(AI9<>"OK","UNRECOGNISED_VALUE","CLEAR"))))))) | AF9: =IF(AND(Q9="",R9=""),"",IF(IF(Q9<>"",Q9,R9)="Stage-A admissible - scoped","stage_a_admissible_scoped",IF(IF(Q9<>"",Q9,R9)="Stage-A admissible - scoped, control-dependent","stage_a_admissible_scoped_control_dependent",IF(IF(Q9<>"",Q9,R9)="Stage-A non-admissible - patchable","stage_a_non_admissible_patchable",IF(IF(Q9<>"",Q9,R9)="Stage-A non-admissible - unpatchable for stated claim","stage_a_non_admissible_unpatchable_for_stated_claim",IF(IF(Q9<>"",Q9,R9)="Indeterminate - insufficient evidence","indeterminate_insufficient_evidence",IF(IF(Q9<>"",Q9,R9)="Protocol refusal to evaluate","protocol_refusal_to_evaluate",IF(IF(Q9<>"",Q9,R9)="Out of scope","out_of_scope",IF(IF(Q9<>"",Q9,R9)="Withdrawn","withdrawn",IF(IF(Q9<>"",Q9,R9)="Not reviewed","not_reviewed","unknown_status")))))))))) | AG9: =IF(AND(AF9="",T9=""),"",IF(AND(AF9<>"",ISNUMBER(SEARCH("token="&AF9&";",T9)),ISNUMBER(SEARCH(AK9,T9)),ISNUMBER(SEARCH("CL basis="&AL9&";",T9))),"VALID","INVALID_OR_INCOMPLETE")) | AH9: =COUNTIF(K9:P9,"Adequate for scope") | AI9: =IF(COUNTA(K9:P9)=0,"",IF(AA9+AB9+AC9+AD9+AH9=6,"OK","UNRECOGNISED_VALUE")) | AK9: =IF(A9="","",Vocabulary!$B$5) | AL9: =IF(A9="","",Vocabulary!$B$6) | AM9: =IF(AJ9="","OK",IF(COUNTIF(Vocabulary!$O$5:$O$8,AJ9)=1,"OK","UNRECOGNISED_ADMIN_DISPOSITION"))
Q10: =IF(AE10="","",IF(AE10="ADMIN_DISPOSITION",AJ10,IF(OR(AE10="ADMIN_INCOMPLETE",AE10="ADMIN_INVALID",AE10="BURDEN_NOT_FEASIBLE",AE10="UNRECOGNISED_VALUE",AE10="UNRECOGNISED_ADMIN_DISPOSITION"),"Protocol refusal to evaluate",IF(AA10>0,"Stage-A non-admissible - unpatchable for stated claim",IF(AB10>0,"Stage-A non-admissible - patchable",IF(OR(J10="Yes",I10="Indeterminate",AC10>0),"Indeterminate - insufficient evidence",IF(AND(AH10=6,AD10=0),"Stage-A admissible - scoped",IF(AND(AH10+AD10=6,AD10>0),"Stage-A admissible - scoped, control-dependent","Protocol refusal to evaluate")))))))) | S10: =IF(AND(Q10="",R10=""),"",IF(AND(Q10<>"",R10=""),"UNRECORDED",IF(AND(Q10="",R10<>""),"ORPHAN_RECORDED",IF(Q10=R10,"MATCH","MISMATCH")))) | AA10: =COUNTIF(K10:P10,"Material defect - unpatchable for stated claim") | AB10: =COUNTIF(K10:P10,"Material defect - patchable") | AC10: =COUNTIF(K10:P10,"Indeterminate")+COUNTIF(K10:P10,"Not reviewed") | AD10: =COUNTIF(K10:P10,"Adequate - control-dependent") | AE10: =IF(COUNTA(A10:P10)+COUNTA(AJ10)=0,"",IF(AM10<>"OK","UNRECOGNISED_ADMIN_DISPOSITION",IF(AND(AJ10<>"",AJ10<>"None"),IF(OR(LEN(TRIM(A10))=0,LEN(TRIM(B10))=0,LEN(TRIM(C10))=0,LEN(TRIM(F10))=0),"ADMIN_INCOMPLETE","ADMIN_DISPOSITION"),IF(OR(LEN(TRIM(A10))=0,LEN(TRIM(B10))=0,LEN(TRIM(C10))=0,LEN(TRIM(D10))=0,LEN(TRIM(E10))=0,LEN(TRIM(F10))=0,LEN(TRIM(G10))=0,LEN(TRIM(H10))=0,LEN(TRIM(I10))=0,LEN(TRIM(J10))=0,LEN(TRIM(K10))=0,LEN(TRIM(L10))=0,LEN(TRIM(M10))=0,LEN(TRIM(N10))=0,LEN(TRIM(O10))=0,LEN(TRIM(P10))=0),"ADMIN_INCOMPLETE",IF(H10<>"Yes","ADMIN_INVALID",IF(I10="Not feasible","BURDEN_NOT_FEASIBLE",IF(AI10<>"OK","UNRECOGNISED_VALUE","CLEAR"))))))) | AF10: =IF(AND(Q10="",R10=""),"",IF(IF(Q10<>"",Q10,R10)="Stage-A admissible - scoped","stage_a_admissible_scoped",IF(IF(Q10<>"",Q10,R10)="Stage-A admissible - scoped, control-dependent","stage_a_admissible_scoped_control_dependent",IF(IF(Q10<>"",Q10,R10)="Stage-A non-admissible - patchable","stage_a_non_admissible_patchable",IF(IF(Q10<>"",Q10,R10)="Stage-A non-admissible - unpatchable for stated claim","stage_a_non_admissible_unpatchable_for_stated_claim",IF(IF(Q10<>"",Q10,R10)="Indeterminate - insufficient evidence","indeterminate_insufficient_evidence",IF(IF(Q10<>"",Q10,R10)="Protocol refusal to evaluate","protocol_refusal_to_evaluate",IF(IF(Q10<>"",Q10,R10)="Out of scope","out_of_scope",IF(IF(Q10<>"",Q10,R10)="Withdrawn","withdrawn",IF(IF(Q10<>"",Q10,R10)="Not reviewed","not_reviewed","unknown_status")))))))))) | AG10: =IF(AND(AF10="",T10=""),"",IF(AND(AF10<>"",ISNUMBER(SEARCH("token="&AF10&";",T10)),ISNUMBER(SEARCH(AK10,T10)),ISNUMBER(SEARCH("CL basis="&AL10&";",T10))),"VALID","INVALID_OR_INCOMPLETE")) | AH10: =COUNTIF(K10:P10,"Adequate for scope") | AI10: =IF(COUNTA(K10:P10)=0,"",IF(AA10+AB10+AC10+AD10+AH10=6,"OK","UNRECOGNISED_VALUE")) | AK10: =IF(A10="","",Vocabulary!$B$5) | AL10: =IF(A10="","",Vocabulary!$B$6) | AM10: =IF(AJ10="","OK",IF(COUNTIF(Vocabulary!$O$5:$O$8,AJ10)=1,"OK","UNRECOGNISED_ADMIN_DISPOSITION"))
Q11: =IF(AE11="","",IF(AE11="ADMIN_DISPOSITION",AJ11,IF(OR(AE11="ADMIN_INCOMPLETE",AE11="ADMIN_INVALID",AE11="BURDEN_NOT_FEASIBLE",AE11="UNRECOGNISED_VALUE",AE11="UNRECOGNISED_ADMIN_DISPOSITION"),"Protocol refusal to evaluate",IF(AA11>0,"Stage-A non-admissible - unpatchable for stated claim",IF(AB11>0,"Stage-A non-admissible - patchable",IF(OR(J11="Yes",I11="Indeterminate",AC11>0),"Indeterminate - insufficient evidence",IF(AND(AH11=6,AD11=0),"Stage-A admissible - scoped",IF(AND(AH11+AD11=6,AD11>0),"Stage-A admissible - scoped, control-dependent","Protocol refusal to evaluate")))))))) | S11: =IF(AND(Q11="",R11=""),"",IF(AND(Q11<>"",R11=""),"UNRECORDED",IF(AND(Q11="",R11<>""),"ORPHAN_RECORDED",IF(Q11=R11,"MATCH","MISMATCH")))) | AA11: =COUNTIF(K11:P11,"Material defect - unpatchable for stated claim") | AB11: =COUNTIF(K11:P11,"Material defect - patchable") | AC11: =COUNTIF(K11:P11,"Indeterminate")+COUNTIF(K11:P11,"Not reviewed") | AD11: =COUNTIF(K11:P11,"Adequate - control-dependent") | AE11: =IF(COUNTA(A11:P11)+COUNTA(AJ11)=0,"",IF(AM11<>"OK","UNRECOGNISED_ADMIN_DISPOSITION",IF(AND(AJ11<>"",AJ11<>"None"),IF(OR(LEN(TRIM(A11))=0,LEN(TRIM(B11))=0,LEN(TRIM(C11))=0,LEN(TRIM(F11))=0),"ADMIN_INCOMPLETE","ADMIN_DISPOSITION"),IF(OR(LEN(TRIM(A11))=0,LEN(TRIM(B11))=0,LEN(TRIM(C11))=0,LEN(TRIM(D11))=0,LEN(TRIM(E11))=0,LEN(TRIM(F11))=0,LEN(TRIM(G11))=0,LEN(TRIM(H11))=0,LEN(TRIM(I11))=0,LEN(TRIM(J11))=0,LEN(TRIM(K11))=0,LEN(TRIM(L11))=0,LEN(TRIM(M11))=0,LEN(TRIM(N11))=0,LEN(TRIM(O11))=0,LEN(TRIM(P11))=0),"ADMIN_INCOMPLETE",IF(H11<>"Yes","ADMIN_INVALID",IF(I11="Not feasible","BURDEN_NOT_FEASIBLE",IF(AI11<>"OK","UNRECOGNISED_VALUE","CLEAR"))))))) | AF11: =IF(AND(Q11="",R11=""),"",IF(IF(Q11<>"",Q11,R11)="Stage-A admissible - scoped","stage_a_admissible_scoped",IF(IF(Q11<>"",Q11,R11)="Stage-A admissible - scoped, control-dependent","stage_a_admissible_scoped_control_dependent",IF(IF(Q11<>"",Q11,R11)="Stage-A non-admissible - patchable","stage_a_non_admissible_patchable",IF(IF(Q11<>"",Q11,R11)="Stage-A non-admissible - unpatchable for stated claim","stage_a_non_admissible_unpatchable_for_stated_claim",IF(IF(Q11<>"",Q11,R11)="Indeterminate - insufficient evidence","indeterminate_insufficient_evidence",IF(IF(Q11<>"",Q11,R11)="Protocol refusal to evaluate","protocol_refusal_to_evaluate",IF(IF(Q11<>"",Q11,R11)="Out of scope","out_of_scope",IF(IF(Q11<>"",Q11,R11)="Withdrawn","withdrawn",IF(IF(Q11<>"",Q11,R11)="Not reviewed","not_reviewed","unknown_status")))))))))) | AG11: =IF(AND(AF11="",T11=""),"",IF(AND(AF11<>"",ISNUMBER(SEARCH("token="&AF11&";",T11)),ISNUMBER(SEARCH(AK11,T11)),ISNUMBER(SEARCH("CL basis="&AL11&";",T11))),"VALID","INVALID_OR_INCOMPLETE")) | AH11: =COUNTIF(K11:P11,"Adequate for scope") | AI11: =IF(COUNTA(K11:P11)=0,"",IF(AA11+AB11+AC11+AD11+AH11=6,"OK","UNRECOGNISED_VALUE")) | AK11: =IF(A11="","",Vocabulary!$B$5) | AL11: =IF(A11="","",Vocabulary!$B$6) | AM11: =IF(AJ11="","OK",IF(COUNTIF(Vocabulary!$O$5:$O$8,AJ11)=1,"OK","UNRECOGNISED_ADMIN_DISPOSITION"))
Q12: =IF(AE12="","",IF(AE12="ADMIN_DISPOSITION",AJ12,IF(OR(AE12="ADMIN_INCOMPLETE",AE12="ADMIN_INVALID",AE12="BURDEN_NOT_FEASIBLE",AE12="UNRECOGNISED_VALUE",AE12="UNRECOGNISED_ADMIN_DISPOSITION"),"Protocol refusal to evaluate",IF(AA12>0,"Stage-A non-admissible - unpatchable for stated claim",IF(AB12>0,"Stage-A non-admissible - patchable",IF(OR(J12="Yes",I12="Indeterminate",AC12>0),"Indeterminate - insufficient evidence",IF(AND(AH12=6,AD12=0),"Stage-A admissible - scoped",IF(AND(AH12+AD12=6,AD12>0),"Stage-A admissible - scoped, control-dependent","Protocol refusal to evaluate")))))))) | S12: =IF(AND(Q12="",R12=""),"",IF(AND(Q12<>"",R12=""),"UNRECORDED",IF(AND(Q12="",R12<>""),"ORPHAN_RECORDED",IF(Q12=R12,"MATCH","MISMATCH")))) | AA12: =COUNTIF(K12:P12,"Material defect - unpatchable for stated claim") | AB12: =COUNTIF(K12:P12,"Material defect - patchable") | AC12: =COUNTIF(K12:P12,"Indeterminate")+COUNTIF(K12:P12,"Not reviewed") | AD12: =COUNTIF(K12:P12,"Adequate - control-dependent") | AE12: =IF(COUNTA(A12:P12)+COUNTA(AJ12)=0,"",IF(AM12<>"OK","UNRECOGNISED_ADMIN_DISPOSITION",IF(AND(AJ12<>"",AJ12<>"None"),IF(OR(LEN(TRIM(A12))=0,LEN(TRIM(B12))=0,LEN(TRIM(C12))=0,LEN(TRIM(F12))=0),"ADMIN_INCOMPLETE","ADMIN_DISPOSITION"),IF(OR(LEN(TRIM(A12))=0,LEN(TRIM(B12))=0,LEN(TRIM(C12))=0,LEN(TRIM(D12))=0,LEN(TRIM(E12))=0,LEN(TRIM(F12))=0,LEN(TRIM(G12))=0,LEN(TRIM(H12))=0,LEN(TRIM(I12))=0,LEN(TRIM(J12))=0,LEN(TRIM(K12))=0,LEN(TRIM(L12))=0,LEN(TRIM(M12))=0,LEN(TRIM(N12))=0,LEN(TRIM(O12))=0,LEN(TRIM(P12))=0),"ADMIN_INCOMPLETE",IF(H12<>"Yes","ADMIN_INVALID",IF(I12="Not feasible","BURDEN_NOT_FEASIBLE",IF(AI12<>"OK","UNRECOGNISED_VALUE","CLEAR"))))))) | AF12: =IF(AND(Q12="",R12=""),"",IF(IF(Q12<>"",Q12,R12)="Stage-A admissible - scoped","stage_a_admissible_scoped",IF(IF(Q12<>"",Q12,R12)="Stage-A admissible - scoped, control-dependent","stage_a_admissible_scoped_control_dependent",IF(IF(Q12<>"",Q12,R12)="Stage-A non-admissible - patchable","stage_a_non_admissible_patchable",IF(IF(Q12<>"",Q12,R12)="Stage-A non-admissible - unpatchable for stated claim","stage_a_non_admissible_unpatchable_for_stated_claim",IF(IF(Q12<>"",Q12,R12)="Indeterminate - insufficient evidence","indeterminate_insufficient_evidence",IF(IF(Q12<>"",Q12,R12)="Protocol refusal to evaluate","protocol_refusal_to_evaluate",IF(IF(Q12<>"",Q12,R12)="Out of scope","out_of_scope",IF(IF(Q12<>"",Q12,R12)="Withdrawn","withdrawn",IF(IF(Q12<>"",Q12,R12)="Not reviewed","not_reviewed","unknown_status")))))))))) | AG12: =IF(AND(AF12="",T12=""),"",IF(AND(AF12<>"",ISNUMBER(SEARCH("token="&AF12&";",T12)),ISNUMBER(SEARCH(AK12,T12)),ISNUMBER(SEARCH("CL basis="&AL12&";",T12))),"VALID","INVALID_OR_INCOMPLETE")) | AH12: =COUNTIF(K12:P12,"Adequate for scope") | AI12: =IF(COUNTA(K12:P12)=0,"",IF(AA12+AB12+AC12+AD12+AH12=6,"OK","UNRECOGNISED_VALUE")) | AK12: =IF(A12="","",Vocabulary!$B$5) | AL12: =IF(A12="","",Vocabulary!$B$6) | AM12: =IF(AJ12="","OK",IF(COUNTIF(Vocabulary!$O$5:$O$8,AJ12)=1,"OK","UNRECOGNISED_ADMIN_DISPOSITION"))
Q13: =IF(AE13="","",IF(AE13="ADMIN_DISPOSITION",AJ13,IF(OR(AE13="ADMIN_INCOMPLETE",AE13="ADMIN_INVALID",AE13="BURDEN_NOT_FEASIBLE",AE13="UNRECOGNISED_VALUE",AE13="UNRECOGNISED_ADMIN_DISPOSITION"),"Protocol refusal to evaluate",IF(AA13>0,"Stage-A non-admissible - unpatchable for stated claim",IF(AB13>0,"Stage-A non-admissible - patchable",IF(OR(J13="Yes",I13="Indeterminate",AC13>0),"Indeterminate - insufficient evidence",IF(AND(AH13=6,AD13=0),"Stage-A admissible - scoped",IF(AND(AH13+AD13=6,AD13>0),"Stage-A admissible - scoped, control-dependent","Protocol refusal to evaluate")))))))) | S13: =IF(AND(Q13="",R13=""),"",IF(AND(Q13<>"",R13=""),"UNRECORDED",IF(AND(Q13="",R13<>""),"ORPHAN_RECORDED",IF(Q13=R13,"MATCH","MISMATCH")))) | AA13: =COUNTIF(K13:P13,"Material defect - unpatchable for stated claim") | AB13: =COUNTIF(K13:P13,"Material defect - patchable") | AC13: =COUNTIF(K13:P13,"Indeterminate")+COUNTIF(K13:P13,"Not reviewed") | AD13: =COUNTIF(K13:P13,"Adequate - control-dependent") | AE13: =IF(COUNTA(A13:P13)+COUNTA(AJ13)=0,"",IF(AM13<>"OK","UNRECOGNISED_ADMIN_DISPOSITION",IF(AND(AJ13<>"",AJ13<>"None"),IF(OR(LEN(TRIM(A13))=0,LEN(TRIM(B13))=0,LEN(TRIM(C13))=0,LEN(TRIM(F13))=0),"ADMIN_INCOMPLETE","ADMIN_DISPOSITION"),IF(OR(LEN(TRIM(A13))=0,LEN(TRIM(B13))=0,LEN(TRIM(C13))=0,LEN(TRIM(D13))=0,LEN(TRIM(E13))=0,LEN(TRIM(F13))=0,LEN(TRIM(G13))=0,LEN(TRIM(H13))=0,LEN(TRIM(I13))=0,LEN(TRIM(J13))=0,LEN(TRIM(K13))=0,LEN(TRIM(L13))=0,LEN(TRIM(M13))=0,LEN(TRIM(N13))=0,LEN(TRIM(O13))=0,LEN(TRIM(P13))=0),"ADMIN_INCOMPLETE",IF(H13<>"Yes","ADMIN_INVALID",IF(I13="Not feasible","BURDEN_NOT_FEASIBLE",IF(AI13<>"OK","UNRECOGNISED_VALUE","CLEAR"))))))) | AF13: =IF(AND(Q13="",R13=""),"",IF(IF(Q13<>"",Q13,R13)="Stage-A admissible - scoped","stage_a_admissible_scoped",IF(IF(Q13<>"",Q13,R13)="Stage-A admissible - scoped, control-dependent","stage_a_admissible_scoped_control_dependent",IF(IF(Q13<>"",Q13,R13)="Stage-A non-admissible - patchable","stage_a_non_admissible_patchable",IF(IF(Q13<>"",Q13,R13)="Stage-A non-admissible - unpatchable for stated claim","stage_a_non_admissible_unpatchable_for_stated_claim",IF(IF(Q13<>"",Q13,R13)="Indeterminate - insufficient evidence","indeterminate_insufficient_evidence",IF(IF(Q13<>"",Q13,R13)="Protocol refusal to evaluate","protocol_refusal_to_evaluate",IF(IF(Q13<>"",Q13,R13)="Out of scope","out_of_scope",IF(IF(Q13<>"",Q13,R13)="Withdrawn","withdrawn",IF(IF(Q13<>"",Q13,R13)="Not reviewed","not_reviewed","unknown_status")))))))))) | AG13: =IF(AND(AF13="",T13=""),"",IF(AND(AF13<>"",ISNUMBER(SEARCH("token="&AF13&";",T13)),ISNUMBER(SEARCH(AK13,T13)),ISNUMBER(SEARCH("CL basis="&AL13&";",T13))),"VALID","INVALID_OR_INCOMPLETE")) | AH13: =COUNTIF(K13:P13,"Adequate for scope") | AI13: =IF(COUNTA(K13:P13)=0,"",IF(AA13+AB13+AC13+AD13+AH13=6,"OK","UNRECOGNISED_VALUE")) | AK13: =IF(A13="","",Vocabulary!$B$5) | AL13: =IF(A13="","",Vocabulary!$B$6) | AM13: =IF(AJ13="","OK",IF(COUNTIF(Vocabulary!$O$5:$O$8,AJ13)=1,"OK","UNRECOGNISED_ADMIN_DISPOSITION"))
Q14: =IF(AE14="","",IF(AE14="ADMIN_DISPOSITION",AJ14,IF(OR(AE14="ADMIN_INCOMPLETE",AE14="ADMIN_INVALID",AE14="BURDEN_NOT_FEASIBLE",AE14="UNRECOGNISED_VALUE",AE14="UNRECOGNISED_ADMIN_DISPOSITION"),"Protocol refusal to evaluate",IF(AA14>0,"Stage-A non-admissible - unpatchable for stated claim",IF(AB14>0,"Stage-A non-admissible - patchable",IF(OR(J14="Yes",I14="Indeterminate",AC14>0),"Indeterminate - insufficient evidence",IF(AND(AH14=6,AD14=0),"Stage-A admissible - scoped",IF(AND(AH14+AD14=6,AD14>0),"Stage-A admissible - scoped, control-dependent","Protocol refusal to evaluate")))))))) | S14: =IF(AND(Q14="",R14=""),"",IF(AND(Q14<>"",R14=""),"UNRECORDED",IF(AND(Q14="",R14<>""),"ORPHAN_RECORDED",IF(Q14=R14,"MATCH","MISMATCH")))) | AA14: =COUNTIF(K14:P14,"Material defect - unpatchable for stated claim") | AB14: =COUNTIF(K14:P14,"Material defect - patchable") | AC14: =COUNTIF(K14:P14,"Indeterminate")+COUNTIF(K14:P14,"Not reviewed") | AD14: =COUNTIF(K14:P14,"Adequate - control-dependent") | AE14: =IF(COUNTA(A14:P14)+COUNTA(AJ14)=0,"",IF(AM14<>"OK","UNRECOGNISED_ADMIN_DISPOSITION",IF(AND(AJ14<>"",AJ14<>"None"),IF(OR(LEN(TRIM(A14))=0,LEN(TRIM(B14))=0,LEN(TRIM(C14))=0,LEN(TRIM(F14))=0),"ADMIN_INCOMPLETE","ADMIN_DISPOSITION"),IF(OR(LEN(TRIM(A14))=0,LEN(TRIM(B14))=0,LEN(TRIM(C14))=0,LEN(TRIM(D14))=0,LEN(TRIM(E14))=0,LEN(TRIM(F14))=0,LEN(TRIM(G14))=0,LEN(TRIM(H14))=0,LEN(TRIM(I14))=0,LEN(TRIM(J14))=0,LEN(TRIM(K14))=0,LEN(TRIM(L14))=0,LEN(TRIM(M14))=0,LEN(TRIM(N14))=0,LEN(TRIM(O14))=0,LEN(TRIM(P14))=0),"ADMIN_INCOMPLETE",IF(H14<>"Yes","ADMIN_INVALID",IF(I14="Not feasible","BURDEN_NOT_FEASIBLE",IF(AI14<>"OK","UNRECOGNISED_VALUE","CLEAR"))))))) | AF14: =IF(AND(Q14="",R14=""),"",IF(IF(Q14<>"",Q14,R14)="Stage-A admissible - scoped","stage_a_admissible_scoped",IF(IF(Q14<>"",Q14,R14)="Stage-A admissible - scoped, control-dependent","stage_a_admissible_scoped_control_dependent",IF(IF(Q14<>"",Q14,R14)="Stage-A non-admissible - patchable","stage_a_non_admissible_patchable",IF(IF(Q14<>"",Q14,R14)="Stage-A non-admissible - unpatchable for stated claim","stage_a_non_admissible_unpatchable_for_stated_claim",IF(IF(Q14<>"",Q14,R14)="Indeterminate - insufficient evidence","indeterminate_insufficient_evidence",IF(IF(Q14<>"",Q14,R14)="Protocol refusal to evaluate","protocol_refusal_to_evaluate",IF(IF(Q14<>"",Q14,R14)="Out of scope","out_of_scope",IF(IF(Q14<>"",Q14,R14)="Withdrawn","withdrawn",IF(IF(Q14<>"",Q14,R14)="Not reviewed","not_reviewed","unknown_status")))))))))) | AG14: =IF(AND(AF14="",T14=""),"",IF(AND(AF14<>"",ISNUMBER(SEARCH("token="&AF14&";",T14)),ISNUMBER(SEARCH(AK14,T14)),ISNUMBER(SEARCH("CL basis="&AL14&";",T14))),"VALID","INVALID_OR_INCOMPLETE")) | AH14: =COUNTIF(K14:P14,"Adequate for scope") | AI14: =IF(COUNTA(K14:P14)=0,"",IF(AA14+AB14+AC14+AD14+AH14=6,"OK","UNRECOGNISED_VALUE")) | AK14: =IF(A14="","",Vocabulary!$B$5) | AL14: =IF(A14="","",Vocabulary!$B$6) | AM14: =IF(AJ14="","OK",IF(COUNTIF(Vocabulary!$O$5:$O$8,AJ14)=1,"OK","UNRECOGNISED_ADMIN_DISPOSITION"))
Q15: =IF(AE15="","",IF(AE15="ADMIN_DISPOSITION",AJ15,IF(OR(AE15="ADMIN_INCOMPLETE",AE15="ADMIN_INVALID",AE15="BURDEN_NOT_FEASIBLE",AE15="UNRECOGNISED_VALUE",AE15="UNRECOGNISED_ADMIN_DISPOSITION"),"Protocol refusal to evaluate",IF(AA15>0,"Stage-A non-admissible - unpatchable for stated claim",IF(AB15>0,"Stage-A non-admissible - patchable",IF(OR(J15="Yes",I15="Indeterminate",AC15>0),"Indeterminate - insufficient evidence",IF(AND(AH15=6,AD15=0),"Stage-A admissible - scoped",IF(AND(AH15+AD15=6,AD15>0),"Stage-A admissible - scoped, control-dependent","Protocol refusal to evaluate")))))))) | S15: =IF(AND(Q15="",R15=""),"",IF(AND(Q15<>"",R15=""),"UNRECORDED",IF(AND(Q15="",R15<>""),"ORPHAN_RECORDED",IF(Q15=R15,"MATCH","MISMATCH")))) | AA15: =COUNTIF(K15:P15,"Material defect - unpatchable for stated claim") | AB15: =COUNTIF(K15:P15,"Material defect - patchable") | AC15: =COUNTIF(K15:P15,"Indeterminate")+COUNTIF(K15:P15,"Not reviewed") | AD15: =COUNTIF(K15:P15,"Adequate - control-dependent") | AE15: =IF(COUNTA(A15:P15)+COUNTA(AJ15)=0,"",IF(AM15<>"OK","UNRECOGNISED_ADMIN_DISPOSITION",IF(AND(AJ15<>"",AJ15<>"None"),IF(OR(LEN(TRIM(A15))=0,LEN(TRIM(B15))=0,LEN(TRIM(C15))=0,LEN(TRIM(F15))=0),"ADMIN_INCOMPLETE","ADMIN_DISPOSITION"),IF(OR(LEN(TRIM(A15))=0,LEN(TRIM(B15))=0,LEN(TRIM(C15))=0,LEN(TRIM(D15))=0,LEN(TRIM(E15))=0,LEN(TRIM(F15))=0,LEN(TRIM(G15))=0,LEN(TRIM(H15))=0,LEN(TRIM(I15))=0,LEN(TRIM(J15))=0,LEN(TRIM(K15))=0,LEN(TRIM(L15))=0,LEN(TRIM(M15))=0,LEN(TRIM(N15))=0,LEN(TRIM(O15))=0,LEN(TRIM(P15))=0),"ADMIN_INCOMPLETE",IF(H15<>"Yes","ADMIN_INVALID",IF(I15="Not feasible","BURDEN_NOT_FEASIBLE",IF(AI15<>"OK","UNRECOGNISED_VALUE","CLEAR"))))))) | AF15: =IF(AND(Q15="",R15=""),"",IF(IF(Q15<>"",Q15,R15)="Stage-A admissible - scoped","stage_a_admissible_scoped",IF(IF(Q15<>"",Q15,R15)="Stage-A admissible - scoped, control-dependent","stage_a_admissible_scoped_control_dependent",IF(IF(Q15<>"",Q15,R15)="Stage-A non-admissible - patchable","stage_a_non_admissible_patchable",IF(IF(Q15<>"",Q15,R15)="Stage-A non-admissible - unpatchable for stated claim","stage_a_non_admissible_unpatchable_for_stated_claim",IF(IF(Q15<>"",Q15,R15)="Indeterminate - insufficient evidence","indeterminate_insufficient_evidence",IF(IF(Q15<>"",Q15,R15)="Protocol refusal to evaluate","protocol_refusal_to_evaluate",IF(IF(Q15<>"",Q15,R15)="Out of scope","out_of_scope",IF(IF(Q15<>"",Q15,R15)="Withdrawn","withdrawn",IF(IF(Q15<>"",Q15,R15)="Not reviewed","not_reviewed","unknown_status")))))))))) | AG15: =IF(AND(AF15="",T15=""),"",IF(AND(AF15<>"",ISNUMBER(SEARCH("token="&AF15&";",T15)),ISNUMBER(SEARCH(AK15,T15)),ISNUMBER(SEARCH("CL basis="&AL15&";",T15))),"VALID","INVALID_OR_INCOMPLETE")) | AH15: =COUNTIF(K15:P15,"Adequate for scope") | AI15: =IF(COUNTA(K15:P15)=0,"",IF(AA15+AB15+AC15+AD15+AH15=6,"OK","UNRECOGNISED_VALUE")) | AK15: =IF(A15="","",Vocabulary!$B$5) | AL15: =IF(A15="","",Vocabulary!$B$6) | AM15: =IF(AJ15="","OK",IF(COUNTIF(Vocabulary!$O$5:$O$8,AJ15)=1,"OK","UNRECOGNISED_ADMIN_DISPOSITION"))
Q16: =IF(AE16="","",IF(AE16="ADMIN_DISPOSITION",AJ16,IF(OR(AE16="ADMIN_INCOMPLETE",AE16="ADMIN_INVALID",AE16="BURDEN_NOT_FEASIBLE",AE16="UNRECOGNISED_VALUE",AE16="UNRECOGNISED_ADMIN_DISPOSITION"),"Protocol refusal to evaluate",IF(AA16>0,"Stage-A non-admissible - unpatchable for stated claim",IF(AB16>0,"Stage-A non-admissible - patchable",IF(OR(J16="Yes",I16="Indeterminate",AC16>0),"Indeterminate - insufficient evidence",IF(AND(AH16=6,AD16=0),"Stage-A admissible - scoped",IF(AND(AH16+AD16=6,AD16>0),"Stage-A admissible - scoped, control-dependent","Protocol refusal to evaluate")))))))) | S16: =IF(AND(Q16="",R16=""),"",IF(AND(Q16<>"",R16=""),"UNRECORDED",IF(AND(Q16="",R16<>""),"ORPHAN_RECORDED",IF(Q16=R16,"MATCH","MISMATCH")))) | AA16: =COUNTIF(K16:P16,"Material defect - unpatchable for stated claim") | AB16: =COUNTIF(K16:P16,"Material defect - patchable") | AC16: =COUNTIF(K16:P16,"Indeterminate")+COUNTIF(K16:P16,"Not reviewed") | AD16: =COUNTIF(K16:P16,"Adequate - control-dependent") | AE16: =IF(COUNTA(A16:P16)+COUNTA(AJ16)=0,"",IF(AM16<>"OK","UNRECOGNISED_ADMIN_DISPOSITION",IF(AND(AJ16<>"",AJ16<>"None"),IF(OR(LEN(TRIM(A16))=0,LEN(TRIM(B16))=0,LEN(TRIM(C16))=0,LEN(TRIM(F16))=0),"ADMIN_INCOMPLETE","ADMIN_DISPOSITION"),IF(OR(LEN(TRIM(A16))=0,LEN(TRIM(B16))=0,LEN(TRIM(C16))=0,LEN(TRIM(D16))=0,LEN(TRIM(E16))=0,LEN(TRIM(F16))=0,LEN(TRIM(G16))=0,LEN(TRIM(H16))=0,LEN(TRIM(I16))=0,LEN(TRIM(J16))=0,LEN(TRIM(K16))=0,LEN(TRIM(L16))=0,LEN(TRIM(M16))=0,LEN(TRIM(N16))=0,LEN(TRIM(O16))=0,LEN(TRIM(P16))=0),"ADMIN_INCOMPLETE",IF(H16<>"Yes","ADMIN_INVALID",IF(I16="Not feasible","BURDEN_NOT_FEASIBLE",IF(AI16<>"OK","UNRECOGNISED_VALUE","CLEAR"))))))) | AF16: =IF(AND(Q16="",R16=""),"",IF(IF(Q16<>"",Q16,R16)="Stage-A admissible - scoped","stage_a_admissible_scoped",IF(IF(Q16<>"",Q16,R16)="Stage-A admissible - scoped, control-dependent","stage_a_admissible_scoped_control_dependent",IF(IF(Q16<>"",Q16,R16)="Stage-A non-admissible - patchable","stage_a_non_admissible_patchable",IF(IF(Q16<>"",Q16,R16)="Stage-A non-admissible - unpatchable for stated claim","stage_a_non_admissible_unpatchable_for_stated_claim",IF(IF(Q16<>"",Q16,R16)="Indeterminate - insufficient evidence","indeterminate_insufficient_evidence",IF(IF(Q16<>"",Q16,R16)="Protocol refusal to evaluate","protocol_refusal_to_evaluate",IF(IF(Q16<>"",Q16,R16)="Out of scope","out_of_scope",IF(IF(Q16<>"",Q16,R16)="Withdrawn","withdrawn",IF(IF(Q16<>"",Q16,R16)="Not reviewed","not_reviewed","unknown_status")))))))))) | AG16: =IF(AND(AF16="",T16=""),"",IF(AND(AF16<>"",ISNUMBER(SEARCH("token="&AF16&";",T16)),ISNUMBER(SEARCH(AK16,T16)),ISNUMBER(SEARCH("CL basis="&AL16&";",T16))),"VALID","INVALID_OR_INCOMPLETE")) | AH16: =COUNTIF(K16:P16,"Adequate for scope") | AI16: =IF(COUNTA(K16:P16)=0,"",IF(AA16+AB16+AC16+AD16+AH16=6,"OK","UNRECOGNISED_VALUE")) | AK16: =IF(A16="","",Vocabulary!$B$5) | AL16: =IF(A16="","",Vocabulary!$B$6) | AM16: =IF(AJ16="","OK",IF(COUNTIF(Vocabulary!$O$5:$O$8,AJ16)=1,"OK","UNRECOGNISED_ADMIN_DISPOSITION"))
... Q239: =IF(AE239="","",IF(AE239="ADMIN_DISPOSITION",AJ239,IF(OR(AE239="ADMIN_INCOMPLETE",AE239="ADMIN_INVALID",AE239="BURDEN_NOT_FEASIBLE",AE239="UNRECOGNISED_VALUE",AE239="UNRECOGNISED_ADMIN_DISPOSITION"),"Protocol refusal to evaluate",IF(AA239>0,"Stage-A non-admissible - unpatchable for stated claim",IF(AB239>0,"Stage-A non-admissible - patchable",IF(OR(J239="Yes",I239="Indeterminate",AC239>0),"Indeterminate - insufficient evidence",IF(AND(AH239=6,AD239=0),"Stage-A admissible - scoped",IF(AND(AH239+AD239=6,AD239>0),"Stage-A admissible - scoped, control-dependent","Protocol refusal to evaluate")))))))) | S239: =IF(AND(Q239="",R239=""),"",IF(AND(Q239<>"",R239=""),"UNRECORDED",IF(AND(Q239="",R239<>""),"ORPHAN_RECORDED",IF(Q239=R239,"MATCH","MISMATCH")))) | AA239: =COUNTIF(K239:P239,"Material defect - unpatchable for stated claim") | AB239: =COUNTIF(K239:P239,"Material defect - patchable") | AC239: =COUNTIF(K239:P239,"Indeterminate")+COUNTIF(K239:P239,"Not reviewed") | AD239: =COUNTIF(K239:P239,"Adequate - control-dependent") | AE239: =IF(COUNTA(A239:P239)+COUNTA(AJ239)=0,"",IF(AM239<>"OK","UNRECOGNISED_ADMIN_DISPOSITION",IF(AND(AJ239<>"",AJ239<>"None"),IF(OR(LEN(TRIM(A239))=0,LEN(TRIM(B239))=0,LEN(TRIM(C239))=0,LEN(TRIM(F239))=0),"ADMIN_INCOMPLETE","ADMIN_DISPOSITION"),IF(OR(LEN(TRIM(A239))=0,LEN(TRIM(B239))=0,LEN(TRIM(C239))=0,LEN(TRIM(D239))=0,LEN(TRIM(E239))=0,LEN(TRIM(F239))=0,LEN(TRIM(G239))=0,LEN(TRIM(H239))=0,LEN(TRIM(I239))=0,LEN(TRIM(J239))=0,LEN(TRIM(K239))=0,LEN(TRIM(L239))=0,LEN(TRIM(M239))=0,LEN(TRIM(N239))=0,LEN(TRIM(O239))=0,LEN(TRIM(P239))=0),"ADMIN_INCOMPLETE",IF(H239<>"Yes","ADMIN_INVALID",IF(I239="Not feasible","BURDEN_NOT_FEASIBLE",IF(AI239<>"OK","UNRECOGNISED_VALUE","CLEAR"))))))) | AF239: =IF(AND(Q239="",R239=""),"",IF(IF(Q239<>"",Q239,R239)="Stage-A admissible - scoped","stage_a_admissible_scoped",IF(IF(Q239<>"",Q239,R239)="Stage-A admissible - scoped, control-dependent","stage_a_admissible_scoped_control_dependent",IF(IF(Q239<>"",Q239,R239)="Stage-A non-admissible - patchable","stage_a_non_admissible_patchable",IF(IF(Q239<>"",Q239,R239)="Stage-A non-admissible - unpatchable for stated claim","stage_a_non_admissible_unpatchable_for_stated_claim",IF(IF(Q239<>"",Q239,R239)="Indeterminate - insufficient evidence","indeterminate_insufficient_evidence",IF(IF(Q239<>"",Q239,R239)="Protocol refusal to evaluate","protocol_refusal_to_evaluate",IF(IF(Q239<>"",Q239,R239)="Out of scope","out_of_scope",IF(IF(Q239<>"",Q239,R239)="Withdrawn","withdrawn",IF(IF(Q239<>"",Q239,R239)="Not reviewed","not_reviewed","unknown_status")))))))))) | AG239: =IF(AND(AF239="",T239=""),"",IF(AND(AF239<>"",ISNUMBER(SEARCH("token="&AF239&";",T239)),ISNUMBER(SEARCH(AK239,T239)),ISNUMBER(SEARCH("CL basis="&AL239&";",T239))),"VALID","INVALID_OR_INCOMPLETE")) | AH239: =COUNTIF(K239:P239,"Adequate for scope") | AI239: =IF(COUNTA(K239:P239)=0,"",IF(AA239+AB239+AC239+AD239+AH239=6,"OK","UNRECOGNISED_VALUE")) | AK239: =IF(A239="","",Vocabulary!$B$5) | AL239: =IF(A239="","",Vocabulary!$B$6) | AM239: =IF(AJ239="","OK",IF(COUNTIF(Vocabulary!$O$5:$O$8,AJ239)=1,"OK","UNRECOGNISED_ADMIN_DISPOSITION"))
Q240: =IF(AE240="","",IF(AE240="ADMIN_DISPOSITION",AJ240,IF(OR(AE240="ADMIN_INCOMPLETE",AE240="ADMIN_INVALID",AE240="BURDEN_NOT_FEASIBLE",AE240="UNRECOGNISED_VALUE",AE240="UNRECOGNISED_ADMIN_DISPOSITION"),"Protocol refusal to evaluate",IF(AA240>0,"Stage-A non-admissible - unpatchable for stated claim",IF(AB240>0,"Stage-A non-admissible - patchable",IF(OR(J240="Yes",I240="Indeterminate",AC240>0),"Indeterminate - insufficient evidence",IF(AND(AH240=6,AD240=0),"Stage-A admissible - scoped",IF(AND(AH240+AD240=6,AD240>0),"Stage-A admissible - scoped, control-dependent","Protocol refusal to evaluate")))))))) | AA240: =COUNTIF(K240:P240,"Material defect - unpatchable for stated claim") | AB240: =COUNTIF(K240:P240,"Material defect - patchable") | AC240: =COUNTIF(K240:P240,"Indeterminate")+COUNTIF(K240:P240,"Not reviewed") | AD240: =COUNTIF(K240:P240,"Adequate - control-dependent") | AE240: =IF(COUNTA(A240:P240)+COUNTA(AJ240)=0,"",IF(AM240<>"OK","UNRECOGNISED_ADMIN_DISPOSITION",IF(AND(AJ240<>"",AJ240<>"None"),IF(OR(LEN(TRIM(A240))=0,LEN(TRIM(B240))=0,LEN(TRIM(C240))=0,LEN(TRIM(F240))=0),"ADMIN_INCOMPLETE","ADMIN_DISPOSITION"),IF(OR(LEN(TRIM(A240))=0,LEN(TRIM(B240))=0,LEN(TRIM(C240))=0,LEN(TRIM(D240))=0,LEN(TRIM(E240))=0,LEN(TRIM(F240))=0,LEN(TRIM(G240))=0,LEN(TRIM(H240))=0,LEN(TRIM(I240))=0,LEN(TRIM(J240))=0,LEN(TRIM(K240))=0,LEN(TRIM(L240))=0,LEN(TRIM(M240))=0,LEN(TRIM(N240))=0,LEN(TRIM(O240))=0,LEN(TRIM(P240))=0),"ADMIN_INCOMPLETE",IF(H240<>"Yes","ADMIN_INVALID",IF(I240="Not feasible","BURDEN_NOT_FEASIBLE",IF(AI240<>"OK","UNRECOGNISED_VALUE","CLEAR"))))))) | AF240: =IF(AND(Q240="",R240=""),"",IF(IF(Q240<>"",Q240,R240)="Stage-A admissible - scoped","stage_a_admissible_scoped",IF(IF(Q240<>"",Q240,R240)="Stage-A admissible - scoped, control-dependent","stage_a_admissible_scoped_control_dependent",IF(IF(Q240<>"",Q240,R240)="Stage-A non-admissible - patchable","stage_a_non_admissible_patchable",IF(IF(Q240<>"",Q240,R240)="Stage-A non-admissible - unpatchable for stated claim","stage_a_non_admissible_unpatchable_for_stated_claim",IF(IF(Q240<>"",Q240,R240)="Indeterminate - insufficient evidence","indeterminate_insufficient_evidence",IF(IF(Q240<>"",Q240,R240)="Protocol refusal to evaluate","protocol_refusal_to_evaluate",IF(IF(Q240<>"",Q240,R240)="Out of scope","out_of_scope",IF(IF(Q240<>"",Q240,R240)="Withdrawn","withdrawn",IF(IF(Q240<>"",Q240,R240)="Not reviewed","not_reviewed","unknown_status")))))))))) | AG240: =IF(AND(AF240="",T240=""),"",IF(AND(AF240<>"",ISNUMBER(SEARCH("token="&AF240&";",T240)),ISNUMBER(SEARCH(AK240,T240)),ISNUMBER(SEARCH("CL basis="&AL240&";",T240))),"VALID","INVALID_OR_INCOMPLETE")) | AH240: =COUNTIF(K240:P240,"Adequate for scope") | AI240: =IF(COUNTA(K240:P240)=0,"",IF(AA240+AB240+AC240+AD240+AH240=6,"OK","UNRECOGNISED_VALUE")) | AK240: =IF(A240="","",Vocabulary!$B$5) | AL240: =IF(A240="","",Vocabulary!$B$6) | AM240: =IF(AJ240="","OK",IF(COUNTIF(Vocabulary!$O$5:$O$8,AJ240)=1,"OK","UNRECOGNISED_ADMIN_DISPOSITION"))
Q241: =IF(AE241="","",IF(AE241="ADMIN_DISPOSITION",AJ241,IF(OR(AE241="ADMIN_INCOMPLETE",AE241="ADMIN_INVALID",AE241="BURDEN_NOT_FEASIBLE",AE241="UNRECOGNISED_VALUE",AE241="UNRECOGNISED_ADMIN_DISPOSITION"),"Protocol refusal to evaluate",IF(AA241>0,"Stage-A non-admissible - unpatchable for stated claim",IF(AB241>0,"Stage-A non-admissible - patchable",IF(OR(J241="Yes",I241="Indeterminate",AC241>0),"Indeterminate - insufficient evidence",IF(AND(AH241=6,AD241=0),"Stage-A admissible - scoped",IF(AND(AH241+AD241=6,AD241>0),"Stage-A admissible - scoped, control-dependent","Protocol refusal to evaluate")))))))) | S241: =IF(AND(Q241="",R241=""),"",IF(AND(Q241<>"",R241=""),"UNRECORDED",IF(AND(Q241="",R241<>""),"ORPHAN_RECORDED",IF(Q241=R241,"MATCH","MISMATCH")))) | AA241: =COUNTIF(K241:P241,"Material defect - unpatchable for stated claim") | AB241: =COUNTIF(K241:P241,"Material defect - patchable") | AC241: =COUNTIF(K241:P241,"Indeterminate")+COUNTIF(K241:P241,"Not reviewed") | AD241: =COUNTIF(K241:P241,"Adequate - control-dependent") | AE241: =IF(COUNTA(A241:P241)+COUNTA(AJ241)=0,"",IF(AM241<>"OK","UNRECOGNISED_ADMIN_DISPOSITION",IF(AND(AJ241<>"",AJ241<>"None"),IF(OR(LEN(TRIM(A241))=0,LEN(TRIM(B241))=0,LEN(TRIM(C241))=0,LEN(TRIM(F241))=0),"ADMIN_INCOMPLETE","ADMIN_DISPOSITION"),IF(OR(LEN(TRIM(A241))=0,LEN(TRIM(B241))=0,LEN(TRIM(C241))=0,LEN(TRIM(D241))=0,LEN(TRIM(E241))=0,LEN(TRIM(F241))=0,LEN(TRIM(G241))=0,LEN(TRIM(H241))=0,LEN(TRIM(I241))=0,LEN(TRIM(J241))=0,LEN(TRIM(K241))=0,LEN(TRIM(L241))=0,LEN(TRIM(M241))=0,LEN(TRIM(N241))=0,LEN(TRIM(O241))=0,LEN(TRIM(P241))=0),"ADMIN_INCOMPLETE",IF(H241<>"Yes","ADMIN_INVALID",IF(I241="Not feasible","BURDEN_NOT_FEASIBLE",IF(AI241<>"OK","UNRECOGNISED_VALUE","CLEAR"))))))) | AF241: =IF(AND(Q241="",R241=""),"",IF(IF(Q241<>"",Q241,R241)="Stage-A admissible - scoped","stage_a_admissible_scoped",IF(IF(Q241<>"",Q241,R241)="Stage-A admissible - scoped, control-dependent","stage_a_admissible_scoped_control_dependent",IF(IF(Q241<>"",Q241,R241)="Stage-A non-admissible - patchable","stage_a_non_admissible_patchable",IF(IF(Q241<>"",Q241,R241)="Stage-A non-admissible - unpatchable for stated claim","stage_a_non_admissible_unpatchable_for_stated_claim",IF(IF(Q241<>"",Q241,R241)="Indeterminate - insufficient evidence","indeterminate_insufficient_evidence",IF(IF(Q241<>"",Q241,R241)="Protocol refusal to evaluate","protocol_refusal_to_evaluate",IF(IF(Q241<>"",Q241,R241)="Out of scope","out_of_scope",IF(IF(Q241<>"",Q241,R241)="Withdrawn","withdrawn",IF(IF(Q241<>"",Q241,R241)="Not reviewed","not_reviewed","unknown_status")))))))))) | AG241: =IF(AND(AF241="",T241=""),"",IF(AND(AF241<>"",ISNUMBER(SEARCH("token="&AF241&";",T241)),ISNUMBER(SEARCH(AK241,T241)),ISNUMBER(SEARCH("CL basis="&AL241&";",T241))),"VALID","INVALID_OR_INCOMPLETE")) | AH241: =COUNTIF(K241:P241,"Adequate for scope") | AI241: =IF(COUNTA(K241:P241)=0,"",IF(AA241+AB241+AC241+AD241+AH241=6,"OK","UNRECOGNISED_VALUE")) | AK241: =IF(A241="","",Vocabulary!$B$5) | AL241: =IF(A241="","",Vocabulary!$B$6) | AM241: =IF(AJ241="","OK",IF(COUNTIF(Vocabulary!$O$5:$O$8,AJ241)=1,"OK","UNRECOGNISED_ADMIN_DISPOSITION"))
Q242: =IF(AE242="","",IF(AE242="ADMIN_DISPOSITION",AJ242,IF(OR(AE242="ADMIN_INCOMPLETE",AE242="ADMIN_INVALID",AE242="BURDEN_NOT_FEASIBLE",AE242="UNRECOGNISED_VALUE",AE242="UNRECOGNISED_ADMIN_DISPOSITION"),"Protocol refusal to evaluate",IF(AA242>0,"Stage-A non-admissible - unpatchable for stated claim",IF(AB242>0,"Stage-A non-admissible - patchable",IF(OR(J242="Yes",I242="Indeterminate",AC242>0),"Indeterminate - insufficient evidence",IF(AND(AH242=6,AD242=0),"Stage-A admissible - scoped",IF(AND(AH242+AD242=6,AD242>0),"Stage-A admissible - scoped, control-dependent","Protocol refusal to evaluate")))))))) | S242: =IF(AND(Q242="",R242=""),"",IF(AND(Q242<>"",R242=""),"UNRECORDED",IF(AND(Q242="",R242<>""),"ORPHAN_RECORDED",IF(Q242=R242,"MATCH","MISMATCH")))) | AA242: =COUNTIF(K242:P242,"Material defect - unpatchable for stated claim") | AB242: =COUNTIF(K242:P242,"Material defect - patchable") | AC242: =COUNTIF(K242:P242,"Indeterminate")+COUNTIF(K242:P242,"Not reviewed") | AD242: =COUNTIF(K242:P242,"Adequate - control-dependent") | AE242: =IF(COUNTA(A242:P242)+COUNTA(AJ242)=0,"",IF(AM242<>"OK","UNRECOGNISED_ADMIN_DISPOSITION",IF(AND(AJ242<>"",AJ242<>"None"),IF(OR(LEN(TRIM(A242))=0,LEN(TRIM(B242))=0,LEN(TRIM(C242))=0,LEN(TRIM(F242))=0),"ADMIN_INCOMPLETE","ADMIN_DISPOSITION"),IF(OR(LEN(TRIM(A242))=0,LEN(TRIM(B242))=0,LEN(TRIM(C242))=0,LEN(TRIM(D242))=0,LEN(TRIM(E242))=0,LEN(TRIM(F242))=0,LEN(TRIM(G242))=0,LEN(TRIM(H242))=0,LEN(TRIM(I242))=0,LEN(TRIM(J242))=0,LEN(TRIM(K242))=0,LEN(TRIM(L242))=0,LEN(TRIM(M242))=0,LEN(TRIM(N242))=0,LEN(TRIM(O242))=0,LEN(TRIM(P242))=0),"ADMIN_INCOMPLETE",IF(H242<>"Yes","ADMIN_INVALID",IF(I242="Not feasible","BURDEN_NOT_FEASIBLE",IF(AI242<>"OK","UNRECOGNISED_VALUE","CLEAR"))))))) | AF242: =IF(AND(Q242="",R242=""),"",IF(IF(Q242<>"",Q242,R242)="Stage-A admissible - scoped","stage_a_admissible_scoped",IF(IF(Q242<>"",Q242,R242)="Stage-A admissible - scoped, control-dependent","stage_a_admissible_scoped_control_dependent",IF(IF(Q242<>"",Q242,R242)="Stage-A non-admissible - patchable","stage_a_non_admissible_patchable",IF(IF(Q242<>"",Q242,R242)="Stage-A non-admissible - unpatchable for stated claim","stage_a_non_admissible_unpatchable_for_stated_claim",IF(IF(Q242<>"",Q242,R242)="Indeterminate - insufficient evidence","indeterminate_insufficient_evidence",IF(IF(Q242<>"",Q242,R242)="Protocol refusal to evaluate","protocol_refusal_to_evaluate",IF(IF(Q242<>"",Q242,R242)="Out of scope","out_of_scope",IF(IF(Q242<>"",Q242,R242)="Withdrawn","withdrawn",IF(IF(Q242<>"",Q242,R242)="Not reviewed","not_reviewed","unknown_status")))))))))) | AG242: =IF(AND(AF242="",T242=""),"",IF(AND(AF242<>"",ISNUMBER(SEARCH("token="&AF242&";",T242)),ISNUMBER(SEARCH(AK242,T242)),ISNUMBER(SEARCH("CL basis="&AL242&";",T242))),"VALID","INVALID_OR_INCOMPLETE")) | AH242: =COUNTIF(K242:P242,"Adequate for scope") | AI242: =IF(COUNTA(K242:P242)=0,"",IF(AA242+AB242+AC242+AD242+AH242=6,"OK","UNRECOGNISED_VALUE")) | AK242: =IF(A242="","",Vocabulary!$B$5) | AL242: =IF(A242="","",Vocabulary!$B$6) | AM242: =IF(AJ242="","OK",IF(COUNTIF(Vocabulary!$O$5:$O$8,AJ242)=1,"OK","UNRECOGNISED_ADMIN_DISPOSITION"))
Q243: =IF(AE243="","",IF(AE243="ADMIN_DISPOSITION",AJ243,IF(OR(AE243="ADMIN_INCOMPLETE",AE243="ADMIN_INVALID",AE243="BURDEN_NOT_FEASIBLE",AE243="UNRECOGNISED_VALUE",AE243="UNRECOGNISED_ADMIN_DISPOSITION"),"Protocol refusal to evaluate",IF(AA243>0,"Stage-A non-admissible - unpatchable for stated claim",IF(AB243>0,"Stage-A non-admissible - patchable",IF(OR(J243="Yes",I243="Indeterminate",AC243>0),"Indeterminate - insufficient evidence",IF(AND(AH243=6,AD243=0),"Stage-A admissible - scoped",IF(AND(AH243+AD243=6,AD243>0),"Stage-A admissible - scoped, control-dependent","Protocol refusal to evaluate")))))))) | S243: =IF(AND(Q243="",R243=""),"",IF(AND(Q243<>"",R243=""),"UNRECORDED",IF(AND(Q243="",R243<>""),"ORPHAN_RECORDED",IF(Q243=R243,"MATCH","MISMATCH")))) | AA243: =COUNTIF(K243:P243,"Material defect - unpatchable for stated claim") | AB243: =COUNTIF(K243:P243,"Material defect - patchable") | AC243: =COUNTIF(K243:P243,"Indeterminate")+COUNTIF(K243:P243,"Not reviewed") | AD243: =COUNTIF(K243:P243,"Adequate - control-dependent") | AE243: =IF(COUNTA(A243:P243)+COUNTA(AJ243)=0,"",IF(AM243<>"OK","UNRECOGNISED_ADMIN_DISPOSITION",IF(AND(AJ243<>"",AJ243<>"None"),IF(OR(LEN(TRIM(A243))=0,LEN(TRIM(B243))=0,LEN(TRIM(C243))=0,LEN(TRIM(F243))=0),"ADMIN_INCOMPLETE","ADMIN_DISPOSITION"),IF(OR(LEN(TRIM(A243))=0,LEN(TRIM(B243))=0,LEN(TRIM(C243))=0,LEN(TRIM(D243))=0,LEN(TRIM(E243))=0,LEN(TRIM(F243))=0,LEN(TRIM(G243))=0,LEN(TRIM(H243))=0,LEN(TRIM(I243))=0,LEN(TRIM(J243))=0,LEN(TRIM(K243))=0,LEN(TRIM(L243))=0,LEN(TRIM(M243))=0,LEN(TRIM(N243))=0,LEN(TRIM(O243))=0,LEN(TRIM(P243))=0),"ADMIN_INCOMPLETE",IF(H243<>"Yes","ADMIN_INVALID",IF(I243="Not feasible","BURDEN_NOT_FEASIBLE",IF(AI243<>"OK","UNRECOGNISED_VALUE","CLEAR"))))))) | AF243: =IF(AND(Q243="",R243=""),"",IF(IF(Q243<>"",Q243,R243)="Stage-A admissible - scoped","stage_a_admissible_scoped",IF(IF(Q243<>"",Q243,R243)="Stage-A admissible - scoped, control-dependent","stage_a_admissible_scoped_control_dependent",IF(IF(Q243<>"",Q243,R243)="Stage-A non-admissible - patchable","stage_a_non_admissible_patchable",IF(IF(Q243<>"",Q243,R243)="Stage-A non-admissible - unpatchable for stated claim","stage_a_non_admissible_unpatchable_for_stated_claim",IF(IF(Q243<>"",Q243,R243)="Indeterminate - insufficient evidence","indeterminate_insufficient_evidence",IF(IF(Q243<>"",Q243,R243)="Protocol refusal to evaluate","protocol_refusal_to_evaluate",IF(IF(Q243<>"",Q243,R243)="Out of scope","out_of_scope",IF(IF(Q243<>"",Q243,R243)="Withdrawn","withdrawn",IF(IF(Q243<>"",Q243,R243)="Not reviewed","not_reviewed","unknown_status")))))))))) | AG243: =IF(AND(AF243="",T243=""),"",IF(AND(AF243<>"",ISNUMBER(SEARCH("token="&AF243&";",T243)),ISNUMBER(SEARCH(AK243,T243)),ISNUMBER(SEARCH("CL basis="&AL243&";",T243))),"VALID","INVALID_OR_INCOMPLETE")) | AH243: =COUNTIF(K243:P243,"Adequate for scope") | AI243: =IF(COUNTA(K243:P243)=0,"",IF(AA243+AB243+AC243+AD243+AH243=6,"OK","UNRECOGNISED_VALUE")) | AK243: =IF(A243="","",Vocabulary!$B$5) | AL243: =IF(A243="","",Vocabulary!$B$6) | AM243: =IF(AJ243="","OK",IF(COUNTIF(Vocabulary!$O$5:$O$8,AJ243)=1,"OK","UNRECOGNISED_ADMIN_DISPOSITION"))
Q244: =IF(AE244="","",IF(AE244="ADMIN_DISPOSITION",AJ244,IF(OR(AE244="ADMIN_INCOMPLETE",AE244="ADMIN_INVALID",AE244="BURDEN_NOT_FEASIBLE",AE244="UNRECOGNISED_VALUE",AE244="UNRECOGNISED_ADMIN_DISPOSITION"),"Protocol refusal to evaluate",IF(AA244>0,"Stage-A non-admissible - unpatchable for stated claim",IF(AB244>0,"Stage-A non-admissible - patchable",IF(OR(J244="Yes",I244="Indeterminate",AC244>0),"Indeterminate - insufficient evidence",IF(AND(AH244=6,AD244=0),"Stage-A admissible - scoped",IF(AND(AH244+AD244=6,AD244>0),"Stage-A admissible - scoped, control-dependent","Protocol refusal to evaluate")))))))) | S244: =IF(AND(Q244="",R244=""),"",IF(AND(Q244<>"",R244=""),"UNRECORDED",IF(AND(Q244="",R244<>""),"ORPHAN_RECORDED",IF(Q244=R244,"MATCH","MISMATCH")))) | AA244: =COUNTIF(K244:P244,"Material defect - unpatchable for stated claim") | AB244: =COUNTIF(K244:P244,"Material defect - patchable") | AC244: =COUNTIF(K244:P244,"Indeterminate")+COUNTIF(K244:P244,"Not reviewed") | AD244: =COUNTIF(K244:P244,"Adequate - control-dependent") | AE244: =IF(COUNTA(A244:P244)+COUNTA(AJ244)=0,"",IF(AM244<>"OK","UNRECOGNISED_ADMIN_DISPOSITION",IF(AND(AJ244<>"",AJ244<>"None"),IF(OR(LEN(TRIM(A244))=0,LEN(TRIM(B244))=0,LEN(TRIM(C244))=0,LEN(TRIM(F244))=0),"ADMIN_INCOMPLETE","ADMIN_DISPOSITION"),IF(OR(LEN(TRIM(A244))=0,LEN(TRIM(B244))=0,LEN(TRIM(C244))=0,LEN(TRIM(D244))=0,LEN(TRIM(E244))=0,LEN(TRIM(F244))=0,LEN(TRIM(G244))=0,LEN(TRIM(H244))=0,LEN(TRIM(I244))=0,LEN(TRIM(J244))=0,LEN(TRIM(K244))=0,LEN(TRIM(L244))=0,LEN(TRIM(M244))=0,LEN(TRIM(N244))=0,LEN(TRIM(O244))=0,LEN(TRIM(P244))=0),"ADMIN_INCOMPLETE",IF(H244<>"Yes","ADMIN_INVALID",IF(I244="Not feasible","BURDEN_NOT_FEASIBLE",IF(AI244<>"OK","UNRECOGNISED_VALUE","CLEAR"))))))) | AF244: =IF(AND(Q244="",R244=""),"",IF(IF(Q244<>"",Q244,R244)="Stage-A admissible - scoped","stage_a_admissible_scoped",IF(IF(Q244<>"",Q244,R244)="Stage-A admissible - scoped, control-dependent","stage_a_admissible_scoped_control_dependent",IF(IF(Q244<>"",Q244,R244)="Stage-A non-admissible - patchable","stage_a_non_admissible_patchable",IF(IF(Q244<>"",Q244,R244)="Stage-A non-admissible - unpatchable for stated claim","stage_a_non_admissible_unpatchable_for_stated_claim",IF(IF(Q244<>"",Q244,R244)="Indeterminate - insufficient evidence","indeterminate_insufficient_evidence",IF(IF(Q244<>"",Q244,R244)="Protocol refusal to evaluate","protocol_refusal_to_evaluate",IF(IF(Q244<>"",Q244,R244)="Out of scope","out_of_scope",IF(IF(Q244<>"",Q244,R244)="Withdrawn","withdrawn",IF(IF(Q244<>"",Q244,R244)="Not reviewed","not_reviewed","unknown_status")))))))))) | AG244: =IF(AND(AF244="",T244=""),"",IF(AND(AF244<>"",ISNUMBER(SEARCH("token="&AF244&";",T244)),ISNUMBER(SEARCH(AK244,T244)),ISNUMBER(SEARCH("CL basis="&AL244&";",T244))),"VALID","INVALID_OR_INCOMPLETE")) | AH244: =COUNTIF(K244:P244,"Adequate for scope") | AI244: =IF(COUNTA(K244:P244)=0,"",IF(AA244+AB244+AC244+AD244+AH244=6,"OK","UNRECOGNISED_VALUE")) | AK244: =IF(A244="","",Vocabulary!$B$5) | AL244: =IF(A244="","",Vocabulary!$B$6) | AM244: =IF(AJ244="","OK",IF(COUNTIF(Vocabulary!$O$5:$O$8,AJ244)=1,"OK","UNRECOGNISED_ADMIN_DISPOSITION"))
Q245: =IF(AE245="","",IF(AE245="ADMIN_DISPOSITION",AJ245,IF(OR(AE245="ADMIN_INCOMPLETE",AE245="ADMIN_INVALID",AE245="BURDEN_NOT_FEASIBLE",AE245="UNRECOGNISED_VALUE",AE245="UNRECOGNISED_ADMIN_DISPOSITION"),"Protocol refusal to evaluate",IF(AA245>0,"Stage-A non-admissible - unpatchable for stated claim",IF(AB245>0,"Stage-A non-admissible - patchable",IF(OR(J245="Yes",I245="Indeterminate",AC245>0),"Indeterminate - insufficient evidence",IF(AND(AH245=6,AD245=0),"Stage-A admissible - scoped",IF(AND(AH245+AD245=6,AD245>0),"Stage-A admissible - scoped, control-dependent","Protocol refusal to evaluate")))))))) | S245: =IF(AND(Q245="",R245=""),"",IF(AND(Q245<>"",R245=""),"UNRECORDED",IF(AND(Q245="",R245<>""),"ORPHAN_RECORDED",IF(Q245=R245,"MATCH","MISMATCH")))) | AA245: =COUNTIF(K245:P245,"Material defect - unpatchable for stated claim") | AB245: =COUNTIF(K245:P245,"Material defect - patchable") | AC245: =COUNTIF(K245:P245,"Indeterminate")+COUNTIF(K245:P245,"Not reviewed") | AD245: =COUNTIF(K245:P245,"Adequate - control-dependent") | AE245: =IF(COUNTA(A245:P245)+COUNTA(AJ245)=0,"",IF(AM245<>"OK","UNRECOGNISED_ADMIN_DISPOSITION",IF(AND(AJ245<>"",AJ245<>"None"),IF(OR(LEN(TRIM(A245))=0,LEN(TRIM(B245))=0,LEN(TRIM(C245))=0,LEN(TRIM(F245))=0),"ADMIN_INCOMPLETE","ADMIN_DISPOSITION"),IF(OR(LEN(TRIM(A245))=0,LEN(TRIM(B245))=0,LEN(TRIM(C245))=0,LEN(TRIM(D245))=0,LEN(TRIM(E245))=0,LEN(TRIM(F245))=0,LEN(TRIM(G245))=0,LEN(TRIM(H245))=0,LEN(TRIM(I245))=0,LEN(TRIM(J245))=0,LEN(TRIM(K245))=0,LEN(TRIM(L245))=0,LEN(TRIM(M245))=0,LEN(TRIM(N245))=0,LEN(TRIM(O245))=0,LEN(TRIM(P245))=0),"ADMIN_INCOMPLETE",IF(H245<>"Yes","ADMIN_INVALID",IF(I245="Not feasible","BURDEN_NOT_FEASIBLE",IF(AI245<>"OK","UNRECOGNISED_VALUE","CLEAR"))))))) | AF245: =IF(AND(Q245="",R245=""),"",IF(IF(Q245<>"",Q245,R245)="Stage-A admissible - scoped","stage_a_admissible_scoped",IF(IF(Q245<>"",Q245,R245)="Stage-A admissible - scoped, control-dependent","stage_a_admissible_scoped_control_dependent",IF(IF(Q245<>"",Q245,R245)="Stage-A non-admissible - patchable","stage_a_non_admissible_patchable",IF(IF(Q245<>"",Q245,R245)="Stage-A non-admissible - unpatchable for stated claim","stage_a_non_admissible_unpatchable_for_stated_claim",IF(IF(Q245<>"",Q245,R245)="Indeterminate - insufficient evidence","indeterminate_insufficient_evidence",IF(IF(Q245<>"",Q245,R245)="Protocol refusal to evaluate","protocol_refusal_to_evaluate",IF(IF(Q245<>"",Q245,R245)="Out of scope","out_of_scope",IF(IF(Q245<>"",Q245,R245)="Withdrawn","withdrawn",IF(IF(Q245<>"",Q245,R245)="Not reviewed","not_reviewed","unknown_status")))))))))) | AG245: =IF(AND(AF245="",T245=""),"",IF(AND(AF245<>"",ISNUMBER(SEARCH("token="&AF245&";",T245)),ISNUMBER(SEARCH(AK245,T245)),ISNUMBER(SEARCH("CL basis="&AL245&";",T245))),"VALID","INVALID_OR_INCOMPLETE")) | AH245: =COUNTIF(K245:P245,"Adequate for scope") | AI245: =IF(COUNTA(K245:P245)=0,"",IF(AA245+AB245+AC245+AD245+AH245=6,"OK","UNRECOGNISED_VALUE")) | AK245: =IF(A245="","",Vocabulary!$B$5) | AL245: =IF(A245="","",Vocabulary!$B$6) | AM245: =IF(AJ245="","OK",IF(COUNTIF(Vocabulary!$O$5:$O$8,AJ245)=1,"OK","UNRECOGNISED_ADMIN_DISPOSITION"))
Q246: =IF(AE246="","",IF(AE246="ADMIN_DISPOSITION",AJ246,IF(OR(AE246="ADMIN_INCOMPLETE",AE246="ADMIN_INVALID",AE246="BURDEN_NOT_FEASIBLE",AE246="UNRECOGNISED_VALUE",AE246="UNRECOGNISED_ADMIN_DISPOSITION"),"Protocol refusal to evaluate",IF(AA246>0,"Stage-A non-admissible - unpatchable for stated claim",IF(AB246>0,"Stage-A non-admissible - patchable",IF(OR(J246="Yes",I246="Indeterminate",AC246>0),"Indeterminate - insufficient evidence",IF(AND(AH246=6,AD246=0),"Stage-A admissible - scoped",IF(AND(AH246+AD246=6,AD246>0),"Stage-A admissible - scoped, control-dependent","Protocol refusal to evaluate")))))))) | S246: =IF(AND(Q246="",R246=""),"",IF(AND(Q246<>"",R246=""),"UNRECORDED",IF(AND(Q246="",R246<>""),"ORPHAN_RECORDED",IF(Q246=R246,"MATCH","MISMATCH")))) | AA246: =COUNTIF(K246:P246,"Material defect - unpatchable for stated claim") | AB246: =COUNTIF(K246:P246,"Material defect - patchable") | AC246: =COUNTIF(K246:P246,"Indeterminate")+COUNTIF(K246:P246,"Not reviewed") | AD246: =COUNTIF(K246:P246,"Adequate - control-dependent") | AE246: =IF(COUNTA(A246:P246)+COUNTA(AJ246)=0,"",IF(AM246<>"OK","UNRECOGNISED_ADMIN_DISPOSITION",IF(AND(AJ246<>"",AJ246<>"None"),IF(OR(LEN(TRIM(A246))=0,LEN(TRIM(B246))=0,LEN(TRIM(C246))=0,LEN(TRIM(F246))=0),"ADMIN_INCOMPLETE","ADMIN_DISPOSITION"),IF(OR(LEN(TRIM(A246))=0,LEN(TRIM(B246))=0,LEN(TRIM(C246))=0,LEN(TRIM(D246))=0,LEN(TRIM(E246))=0,LEN(TRIM(F246))=0,LEN(TRIM(G246))=0,LEN(TRIM(H246))=0,LEN(TRIM(I246))=0,LEN(TRIM(J246))=0,LEN(TRIM(K246))=0,LEN(TRIM(L246))=0,LEN(TRIM(M246))=0,LEN(TRIM(N246))=0,LEN(TRIM(O246))=0,LEN(TRIM(P246))=0),"ADMIN_INCOMPLETE",IF(H246<>"Yes","ADMIN_INVALID",IF(I246="Not feasible","BURDEN_NOT_FEASIBLE",IF(AI246<>"OK","UNRECOGNISED_VALUE","CLEAR"))))))) | AF246: =IF(AND(Q246="",R246=""),"",IF(IF(Q246<>"",Q246,R246)="Stage-A admissible - scoped","stage_a_admissible_scoped",IF(IF(Q246<>"",Q246,R246)="Stage-A admissible - scoped, control-dependent","stage_a_admissible_scoped_control_dependent",IF(IF(Q246<>"",Q246,R246)="Stage-A non-admissible - patchable","stage_a_non_admissible_patchable",IF(IF(Q246<>"",Q246,R246)="Stage-A non-admissible - unpatchable for stated claim","stage_a_non_admissible_unpatchable_for_stated_claim",IF(IF(Q246<>"",Q246,R246)="Indeterminate - insufficient evidence","indeterminate_insufficient_evidence",IF(IF(Q246<>"",Q246,R246)="Protocol refusal to evaluate","protocol_refusal_to_evaluate",IF(IF(Q246<>"",Q246,R246)="Out of scope","out_of_scope",IF(IF(Q246<>"",Q246,R246)="Withdrawn","withdrawn",IF(IF(Q246<>"",Q246,R246)="Not reviewed","not_reviewed","unknown_status")))))))))) | AG246: =IF(AND(AF246="",T246=""),"",IF(AND(AF246<>"",ISNUMBER(SEARCH("token="&AF246&";",T246)),ISNUMBER(SEARCH(AK246,T246)),ISNUMBER(SEARCH("CL basis="&AL246&";",T246))),"VALID","INVALID_OR_INCOMPLETE")) | AH246: =COUNTIF(K246:P246,"Adequate for scope") | AI246: =IF(COUNTA(K246:P246)=0,"",IF(AA246+AB246+AC246+AD246+AH246=6,"OK","UNRECOGNISED_VALUE")) | AK246: =IF(A246="","",Vocabulary!$B$5) | AL246: =IF(A246="","",Vocabulary!$B$6) | AM246: =IF(AJ246="","OK",IF(COUNTIF(Vocabulary!$O$5:$O$8,AJ246)=1,"OK","UNRECOGNISED_ADMIN_DISPOSITION"))
Q247: =IF(AE247="","",IF(AE247="ADMIN_DISPOSITION",AJ247,IF(OR(AE247="ADMIN_INCOMPLETE",AE247="ADMIN_INVALID",AE247="BURDEN_NOT_FEASIBLE",AE247="UNRECOGNISED_VALUE",AE247="UNRECOGNISED_ADMIN_DISPOSITION"),"Protocol refusal to evaluate",IF(AA247>0,"Stage-A non-admissible - unpatchable for stated claim",IF(AB247>0,"Stage-A non-admissible - patchable",IF(OR(J247="Yes",I247="Indeterminate",AC247>0),"Indeterminate - insufficient evidence",IF(AND(AH247=6,AD247=0),"Stage-A admissible - scoped",IF(AND(AH247+AD247=6,AD247>0),"Stage-A admissible - scoped, control-dependent","Protocol refusal to evaluate")))))))) | S247: =IF(AND(Q247="",R247=""),"",IF(AND(Q247<>"",R247=""),"UNRECORDED",IF(AND(Q247="",R247<>""),"ORPHAN_RECORDED",IF(Q247=R247,"MATCH","MISMATCH")))) | AA247: =COUNTIF(K247:P247,"Material defect - unpatchable for stated claim") | AB247: =COUNTIF(K247:P247,"Material defect - patchable") | AC247: =COUNTIF(K247:P247,"Indeterminate")+COUNTIF(K247:P247,"Not reviewed") | AD247: =COUNTIF(K247:P247,"Adequate - control-dependent") | AE247: =IF(COUNTA(A247:P247)+COUNTA(AJ247)=0,"",IF(AM247<>"OK","UNRECOGNISED_ADMIN_DISPOSITION",IF(AND(AJ247<>"",AJ247<>"None"),IF(OR(LEN(TRIM(A247))=0,LEN(TRIM(B247))=0,LEN(TRIM(C247))=0,LEN(TRIM(F247))=0),"ADMIN_INCOMPLETE","ADMIN_DISPOSITION"),IF(OR(LEN(TRIM(A247))=0,LEN(TRIM(B247))=0,LEN(TRIM(C247))=0,LEN(TRIM(D247))=0,LEN(TRIM(E247))=0,LEN(TRIM(F247))=0,LEN(TRIM(G247))=0,LEN(TRIM(H247))=0,LEN(TRIM(I247))=0,LEN(TRIM(J247))=0,LEN(TRIM(K247))=0,LEN(TRIM(L247))=0,LEN(TRIM(M247))=0,LEN(TRIM(N247))=0,LEN(TRIM(O247))=0,LEN(TRIM(P247))=0),"ADMIN_INCOMPLETE",IF(H247<>"Yes","ADMIN_INVALID",IF(I247="Not feasible","BURDEN_NOT_FEASIBLE",IF(AI247<>"OK","UNRECOGNISED_VALUE","CLEAR"))))))) | AF247: =IF(AND(Q247="",R247=""),"",IF(IF(Q247<>"",Q247,R247)="Stage-A admissible - scoped","stage_a_admissible_scoped",IF(IF(Q247<>"",Q247,R247)="Stage-A admissible - scoped, control-dependent","stage_a_admissible_scoped_control_dependent",IF(IF(Q247<>"",Q247,R247)="Stage-A non-admissible - patchable","stage_a_non_admissible_patchable",IF(IF(Q247<>"",Q247,R247)="Stage-A non-admissible - unpatchable for stated claim","stage_a_non_admissible_unpatchable_for_stated_claim",IF(IF(Q247<>"",Q247,R247)="Indeterminate - insufficient evidence","indeterminate_insufficient_evidence",IF(IF(Q247<>"",Q247,R247)="Protocol refusal to evaluate","protocol_refusal_to_evaluate",IF(IF(Q247<>"",Q247,R247)="Out of scope","out_of_scope",IF(IF(Q247<>"",Q247,R247)="Withdrawn","withdrawn",IF(IF(Q247<>"",Q247,R247)="Not reviewed","not_reviewed","unknown_status")))))))))) | AG247: =IF(AND(AF247="",T247=""),"",IF(AND(AF247<>"",ISNUMBER(SEARCH("token="&AF247&";",T247)),ISNUMBER(SEARCH(AK247,T247)),ISNUMBER(SEARCH("CL basis="&AL247&";",T247))),"VALID","INVALID_OR_INCOMPLETE")) | AH247: =COUNTIF(K247:P247,"Adequate for scope") | AI247: =IF(COUNTA(K247:P247)=0,"",IF(AA247+AB247+AC247+AD247+AH247=6,"OK","UNRECOGNISED_VALUE")) | AK247: =IF(A247="","",Vocabulary!$B$5) | AL247: =IF(A247="","",Vocabulary!$B$6) | AM247: =IF(AJ247="","OK",IF(COUNTIF(Vocabulary!$O$5:$O$8,AJ247)=1,"OK","UNRECOGNISED_ADMIN_DISPOSITION"))
Q248: =IF(AE248="","",IF(AE248="ADMIN_DISPOSITION",AJ248,IF(OR(AE248="ADMIN_INCOMPLETE",AE248="ADMIN_INVALID",AE248="BURDEN_NOT_FEASIBLE",AE248="UNRECOGNISED_VALUE",AE248="UNRECOGNISED_ADMIN_DISPOSITION"),"Protocol refusal to evaluate",IF(AA248>0,"Stage-A non-admissible - unpatchable for stated claim",IF(AB248>0,"Stage-A non-admissible - patchable",IF(OR(J248="Yes",I248="Indeterminate",AC248>0),"Indeterminate - insufficient evidence",IF(AND(AH248=6,AD248=0),"Stage-A admissible - scoped",IF(AND(AH248+AD248=6,AD248>0),"Stage-A admissible - scoped, control-dependent","Protocol refusal to evaluate")))))))) | S248: =IF(AND(Q248="",R248=""),"",IF(AND(Q248<>"",R248=""),"UNRECORDED",IF(AND(Q248="",R248<>""),"ORPHAN_RECORDED",IF(Q248=R248,"MATCH","MISMATCH")))) | AA248: =COUNTIF(K248:P248,"Material defect - unpatchable for stated claim") | AB248: =COUNTIF(K248:P248,"Material defect - patchable") | AC248: =COUNTIF(K248:P248,"Indeterminate")+COUNTIF(K248:P248,"Not reviewed") | AD248: =COUNTIF(K248:P248,"Adequate - control-dependent") | AE248: =IF(COUNTA(A248:P248)+COUNTA(AJ248)=0,"",IF(AM248<>"OK","UNRECOGNISED_ADMIN_DISPOSITION",IF(AND(AJ248<>"",AJ248<>"None"),IF(OR(LEN(TRIM(A248))=0,LEN(TRIM(B248))=0,LEN(TRIM(C248))=0,LEN(TRIM(F248))=0),"ADMIN_INCOMPLETE","ADMIN_DISPOSITION"),IF(OR(LEN(TRIM(A248))=0,LEN(TRIM(B248))=0,LEN(TRIM(C248))=0,LEN(TRIM(D248))=0,LEN(TRIM(E248))=0,LEN(TRIM(F248))=0,LEN(TRIM(G248))=0,LEN(TRIM(H248))=0,LEN(TRIM(I248))=0,LEN(TRIM(J248))=0,LEN(TRIM(K248))=0,LEN(TRIM(L248))=0,LEN(TRIM(M248))=0,LEN(TRIM(N248))=0,LEN(TRIM(O248))=0,LEN(TRIM(P248))=0),"ADMIN_INCOMPLETE",IF(H248<>"Yes","ADMIN_INVALID",IF(I248="Not feasible","BURDEN_NOT_FEASIBLE",IF(AI248<>"OK","UNRECOGNISED_VALUE","CLEAR"))))))) | AF248: =IF(AND(Q248="",R248=""),"",IF(IF(Q248<>"",Q248,R248)="Stage-A admissible - scoped","stage_a_admissible_scoped",IF(IF(Q248<>"",Q248,R248)="Stage-A admissible - scoped, control-dependent","stage_a_admissible_scoped_control_dependent",IF(IF(Q248<>"",Q248,R248)="Stage-A non-admissible - patchable","stage_a_non_admissible_patchable",IF(IF(Q248<>"",Q248,R248)="Stage-A non-admissible - unpatchable for stated claim","stage_a_non_admissible_unpatchable_for_stated_claim",IF(IF(Q248<>"",Q248,R248)="Indeterminate - insufficient evidence","indeterminate_insufficient_evidence",IF(IF(Q248<>"",Q248,R248)="Protocol refusal to evaluate","protocol_refusal_to_evaluate",IF(IF(Q248<>"",Q248,R248)="Out of scope","out_of_scope",IF(IF(Q248<>"",Q248,R248)="Withdrawn","withdrawn",IF(IF(Q248<>"",Q248,R248)="Not reviewed","not_reviewed","unknown_status")))))))))) | AG248: =IF(AND(AF248="",T248=""),"",IF(AND(AF248<>"",ISNUMBER(SEARCH("token="&AF248&";",T248)),ISNUMBER(SEARCH(AK248,T248)),ISNUMBER(SEARCH("CL basis="&AL248&";",T248))),"VALID","INVALID_OR_INCOMPLETE")) | AH248: =COUNTIF(K248:P248,"Adequate for scope") | AI248: =IF(COUNTA(K248:P248)=0,"",IF(AA248+AB248+AC248+AD248+AH248=6,"OK","UNRECOGNISED_VALUE")) | AK248: =IF(A248="","",Vocabulary!$B$5) | AL248: =IF(A248="","",Vocabulary!$B$6) | AM248: =IF(AJ248="","OK",IF(COUNTIF(Vocabulary!$O$5:$O$8,AJ248)=1,"OK","UNRECOGNISED_ADMIN_DISPOSITION"))
Q249: =IF(AE249="","",IF(AE249="ADMIN_DISPOSITION",AJ249,IF(OR(AE249="ADMIN_INCOMPLETE",AE249="ADMIN_INVALID",AE249="BURDEN_NOT_FEASIBLE",AE249="UNRECOGNISED_VALUE",AE249="UNRECOGNISED_ADMIN_DISPOSITION"),"Protocol refusal to evaluate",IF(AA249>0,"Stage-A non-admissible - unpatchable for stated claim",IF(AB249>0,"Stage-A non-admissible - patchable",IF(OR(J249="Yes",I249="Indeterminate",AC249>0),"Indeterminate - insufficient evidence",IF(AND(AH249=6,AD249=0),"Stage-A admissible - scoped",IF(AND(AH249+AD249=6,AD249>0),"Stage-A admissible - scoped, control-dependent","Protocol refusal to evaluate")))))))) | S249: =IF(AND(Q249="",R249=""),"",IF(AND(Q249<>"",R249=""),"UNRECORDED",IF(AND(Q249="",R249<>""),"ORPHAN_RECORDED",IF(Q249=R249,"MATCH","MISMATCH")))) | AA249: =COUNTIF(K249:P249,"Material defect - unpatchable for stated claim") | AB249: =COUNTIF(K249:P249,"Material defect - patchable") | AC249: =COUNTIF(K249:P249,"Indeterminate")+COUNTIF(K249:P249,"Not reviewed") | AD249: =COUNTIF(K249:P249,"Adequate - control-dependent") | AE249: =IF(COUNTA(A249:P249)+COUNTA(AJ249)=0,"",IF(AM249<>"OK","UNRECOGNISED_ADMIN_DISPOSITION",IF(AND(AJ249<>"",AJ249<>"None"),IF(OR(LEN(TRIM(A249))=0,LEN(TRIM(B249))=0,LEN(TRIM(C249))=0,LEN(TRIM(F249))=0),"ADMIN_INCOMPLETE","ADMIN_DISPOSITION"),IF(OR(LEN(TRIM(A249))=0,LEN(TRIM(B249))=0,LEN(TRIM(C249))=0,LEN(TRIM(D249))=0,LEN(TRIM(E249))=0,LEN(TRIM(F249))=0,LEN(TRIM(G249))=0,LEN(TRIM(H249))=0,LEN(TRIM(I249))=0,LEN(TRIM(J249))=0,LEN(TRIM(K249))=0,LEN(TRIM(L249))=0,LEN(TRIM(M249))=0,LEN(TRIM(N249))=0,LEN(TRIM(O249))=0,LEN(TRIM(P249))=0),"ADMIN_INCOMPLETE",IF(H249<>"Yes","ADMIN_INVALID",IF(I249="Not feasible","BURDEN_NOT_FEASIBLE",IF(AI249<>"OK","UNRECOGNISED_VALUE","CLEAR"))))))) | AF249: =IF(AND(Q249="",R249=""),"",IF(IF(Q249<>"",Q249,R249)="Stage-A admissible - scoped","stage_a_admissible_scoped",IF(IF(Q249<>"",Q249,R249)="Stage-A admissible - scoped, control-dependent","stage_a_admissible_scoped_control_dependent",IF(IF(Q249<>"",Q249,R249)="Stage-A non-admissible - patchable","stage_a_non_admissible_patchable",IF(IF(Q249<>"",Q249,R249)="Stage-A non-admissible - unpatchable for stated claim","stage_a_non_admissible_unpatchable_for_stated_claim",IF(IF(Q249<>"",Q249,R249)="Indeterminate - insufficient evidence","indeterminate_insufficient_evidence",IF(IF(Q249<>"",Q249,R249)="Protocol refusal to evaluate","protocol_refusal_to_evaluate",IF(IF(Q249<>"",Q249,R249)="Out of scope","out_of_scope",IF(IF(Q249<>"",Q249,R249)="Withdrawn","withdrawn",IF(IF(Q249<>"",Q249,R249)="Not reviewed","not_reviewed","unknown_status")))))))))) | AG249: =IF(AND(AF249="",T249=""),"",IF(AND(AF249<>"",ISNUMBER(SEARCH("token="&AF249&";",T249)),ISNUMBER(SEARCH(AK249,T249)),ISNUMBER(SEARCH("CL basis="&AL249&";",T249))),"VALID","INVALID_OR_INCOMPLETE")) | AH249: =COUNTIF(K249:P249,"Adequate for scope") | AI249: =IF(COUNTA(K249:P249)=0,"",IF(AA249+AB249+AC249+AD249+AH249=6,"OK","UNRECOGNISED_VALUE")) | AK249: =IF(A249="","",Vocabulary!$B$5) | AL249: =IF(A249="","",Vocabulary!$B$6) | AM249: =IF(AJ249="","OK",IF(COUNTIF(Vocabulary!$O$5:$O$8,AJ249)=1,"OK","UNRECOGNISED_ADMIN_DISPOSITION"))
Q250: =IF(AE250="","",IF(AE250="ADMIN_DISPOSITION",AJ250,IF(OR(AE250="ADMIN_INCOMPLETE",AE250="ADMIN_INVALID",AE250="BURDEN_NOT_FEASIBLE",AE250="UNRECOGNISED_VALUE",AE250="UNRECOGNISED_ADMIN_DISPOSITION"),"Protocol refusal to evaluate",IF(AA250>0,"Stage-A non-admissible - unpatchable for stated claim",IF(AB250>0,"Stage-A non-admissible - patchable",IF(OR(J250="Yes",I250="Indeterminate",AC250>0),"Indeterminate - insufficient evidence",IF(AND(AH250=6,AD250=0),"Stage-A admissible - scoped",IF(AND(AH250+AD250=6,AD250>0),"Stage-A admissible - scoped, control-dependent","Protocol refusal to evaluate")))))))) | S250: =IF(AND(Q250="",R250=""),"",IF(AND(Q250<>"",R250=""),"UNRECORDED",IF(AND(Q250="",R250<>""),"ORPHAN_RECORDED",IF(Q250=R250,"MATCH","MISMATCH")))) | AA250: =COUNTIF(K250:P250,"Material defect - unpatchable for stated claim") | AB250: =COUNTIF(K250:P250,"Material defect - patchable") | AC250: =COUNTIF(K250:P250,"Indeterminate")+COUNTIF(K250:P250,"Not reviewed") | AD250: =COUNTIF(K250:P250,"Adequate - control-dependent") | AE250: =IF(COUNTA(A250:P250)+COUNTA(AJ250)=0,"",IF(AM250<>"OK","UNRECOGNISED_ADMIN_DISPOSITION",IF(AND(AJ250<>"",AJ250<>"None"),IF(OR(LEN(TRIM(A250))=0,LEN(TRIM(B250))=0,LEN(TRIM(C250))=0,LEN(TRIM(F250))=0),"ADMIN_INCOMPLETE","ADMIN_DISPOSITION"),IF(OR(LEN(TRIM(A250))=0,LEN(TRIM(B250))=0,LEN(TRIM(C250))=0,LEN(TRIM(D250))=0,LEN(TRIM(E250))=0,LEN(TRIM(F250))=0,LEN(TRIM(G250))=0,LEN(TRIM(H250))=0,LEN(TRIM(I250))=0,LEN(TRIM(J250))=0,LEN(TRIM(K250))=0,LEN(TRIM(L250))=0,LEN(TRIM(M250))=0,LEN(TRIM(N250))=0,LEN(TRIM(O250))=0,LEN(TRIM(P250))=0),"ADMIN_INCOMPLETE",IF(H250<>"Yes","ADMIN_INVALID",IF(I250="Not feasible","BURDEN_NOT_FEASIBLE",IF(AI250<>"OK","UNRECOGNISED_VALUE","CLEAR"))))))) | AF250: =IF(AND(Q250="",R250=""),"",IF(IF(Q250<>"",Q250,R250)="Stage-A admissible - scoped","stage_a_admissible_scoped",IF(IF(Q250<>"",Q250,R250)="Stage-A admissible - scoped, control-dependent","stage_a_admissible_scoped_control_dependent",IF(IF(Q250<>"",Q250,R250)="Stage-A non-admissible - patchable","stage_a_non_admissible_patchable",IF(IF(Q250<>"",Q250,R250)="Stage-A non-admissible - unpatchable for stated claim","stage_a_non_admissible_unpatchable_for_stated_claim",IF(IF(Q250<>"",Q250,R250)="Indeterminate - insufficient evidence","indeterminate_insufficient_evidence",IF(IF(Q250<>"",Q250,R250)="Protocol refusal to evaluate","protocol_refusal_to_evaluate",IF(IF(Q250<>"",Q250,R250)="Out of scope","out_of_scope",IF(IF(Q250<>"",Q250,R250)="Withdrawn","withdrawn",IF(IF(Q250<>"",Q250,R250)="Not reviewed","not_reviewed","unknown_status")))))))))) | AG250: =IF(AND(AF250="",T250=""),"",IF(AND(AF250<>"",ISNUMBER(SEARCH("token="&AF250&";",T250)),ISNUMBER(SEARCH(AK250,T250)),ISNUMBER(SEARCH("CL basis="&AL250&";",T250))),"VALID","INVALID_OR_INCOMPLETE")) | AH250: =COUNTIF(K250:P250,"Adequate for scope") | AI250: =IF(COUNTA(K250:P250)=0,"",IF(AA250+AB250+AC250+AD250+AH250=6,"OK","UNRECOGNISED_VALUE")) | AK250: =IF(A250="","",Vocabulary!$B$5) | AL250: =IF(A250="","",Vocabulary!$B$6) | AM250: =IF(AJ250="","OK",IF(COUNTIF(Vocabulary!$O$5:$O$8,AJ250)=1,"OK","UNRECOGNISED_ADMIN_DISPOSITION"))

Sheet Verdict_Vector
A1: Authority-Specific Verdict Vector - AF v6.2
A3: Record_ID | B3: Candidate_ID | C3: Component | D3: Status | E3: Issuing_Authority | F3: Authority_Basis | G3: Scope | H3: Evidence_Refs | I3: Issued_At | J3: Expiry_or_Review | K3: Conditions | L3: Appeal_Route | M3: Inference_Firewall_Check
A4: VV-ILL-001 | B4: SYNTH-CAND-HC | C4: AF eligibility | D4: Stage-A non-admissible - patchable | E4: Independent AF host | F4: AF v6.2 protocol-relative review | G4: SCOPE-ILL-001 | H4: SAR-ILL-001 | I4: 2026-08-11 | J4: 2027-02-11 | K4: Patch C3 defect | L4: Independent appeal panel | M4: =IF(COUNTA(A4:L4)=0,"",IF(OR(LOWER(TRIM(D4))="approved",LOWER(TRIM(D4))="certified",LOWER(TRIM(D4))="safe",LOWER(TRIM(D4))="ethical",LOWER(TRIM(D4))="legitimate",LOWER(TRIM(D4))="compliant",LOWER(TRIM(D4))="due diligence"),"PROHIBITED GENERIC STATUS","OK"))
A5: VV-ILL-001 | B5: SYNTH-CAND-HC | C5: Legal conformity | D5: Not assessed | E5: No AF legal authority | F5: Separate competent legal authority required | G5: SCOPE-ILL-001 | I5: 2026-08-11 | J5: 2027-02-11 | L5: Competent legal route | M5: =IF(COUNTA(A5:L5)=0,"",IF(OR(LOWER(TRIM(D5))="approved",LOWER(TRIM(D5))="certified",LOWER(TRIM(D5))="safe",LOWER(TRIM(D5))="ethical",LOWER(TRIM(D5))="legitimate",LOWER(TRIM(D5))="compliant",LOWER(TRIM(D5))="due diligence"),"PROHIBITED GENERIC STATUS","OK"))
A6: VV-ILL-001 | B6: SYNTH-CAND-HC | C6: Moral adequacy | D6: Not assessed | E6: No AF moral authority | F6: Separate plural moral process required | G6: SCOPE-ILL-001 | I6: 2026-08-11 | J6: 2027-02-11 | L6: Plural deliberative route | M6: =IF(COUNTA(A6:L6)=0,"",IF(OR(LOWER(TRIM(D6))="approved",LOWER(TRIM(D6))="certified",LOWER(TRIM(D6))="safe",LOWER(TRIM(D6))="ethical",LOWER(TRIM(D6))="legitimate",LOWER(TRIM(D6))="compliant",LOWER(TRIM(D6))="due diligence"),"PROHIBITED GENERIC STATUS","OK"))
A7: VV-ILL-001 | B7: SYNTH-CAND-HC | C7: Community legitimacy | D7: Consultation incomplete | E7: Affected-party body | F7: Community process record | G7: SCOPE-ILL-001 | H7: AP-ILL-001 | I7: 2026-08-11 | J7: 2027-02-11 | K7: Further consultation | L7: Community appeal route | M7: =IF(COUNTA(A7:L7)=0,"",IF(OR(LOWER(TRIM(D7))="approved",LOWER(TRIM(D7))="certified",LOWER(TRIM(D7))="safe",LOWER(TRIM(D7))="ethical",LOWER(TRIM(D7))="legitimate",LOWER(TRIM(D7))="compliant",LOWER(TRIM(D7))="due diligence"),"PROHIBITED GENERIC STATUS","OK"))
A8: VV-ILL-001 | B8: SYNTH-CAND-HC | C8: Deployment authorization | D8: Not authorized | E8: Competent operating authority | F8: Separate authorization absent | G8: SCOPE-ILL-001 | I8: 2026-08-11 | J8: 2027-02-11 | L8: Operating-authority appeal | M8: =IF(COUNTA(A8:L8)=0,"",IF(OR(LOWER(TRIM(D8))="approved",LOWER(TRIM(D8))="certified",LOWER(TRIM(D8))="safe",LOWER(TRIM(D8))="ethical",LOWER(TRIM(D8))="legitimate",LOWER(TRIM(D8))="compliant",LOWER(TRIM(D8))="due diligence"),"PROHIBITED GENERIC STATUS","OK"))
M9: =IF(COUNTA(A9:L9)=0,"",IF(OR(LOWER(TRIM(D9))="approved",LOWER(TRIM(D9))="certified",LOWER(TRIM(D9))="safe",LOWER(TRIM(D9))="ethical",LOWER(TRIM(D9))="legitimate",LOWER(TRIM(D9))="compliant",LOWER(TRIM(D9))="due diligence"),"PROHIBITED GENERIC STATUS","OK"))
M10: =IF(COUNTA(A10:L10)=0,"",IF(OR(LOWER(TRIM(D10))="approved",LOWER(TRIM(D10))="certified",LOWER(TRIM(D10))="safe",LOWER(TRIM(D10))="ethical",LOWER(TRIM(D10))="legitimate",LOWER(TRIM(D10))="compliant",LOWER(TRIM(D10))="due diligence"),"PROHIBITED GENERIC STATUS","OK"))
M11: =IF(COUNTA(A11:L11)=0,"",IF(OR(LOWER(TRIM(D11))="approved",LOWER(TRIM(D11))="certified",LOWER(TRIM(D11))="safe",LOWER(TRIM(D11))="ethical",LOWER(TRIM(D11))="legitimate",LOWER(TRIM(D11))="compliant",LOWER(TRIM(D11))="due diligence"),"PROHIBITED GENERIC STATUS","OK"))
M12: =IF(COUNTA(A12:L12)=0,"",IF(OR(LOWER(TRIM(D12))="approved",LOWER(TRIM(D12))="certified",LOWER(TRIM(D12))="safe",LOWER(TRIM(D12))="ethical",LOWER(TRIM(D12))="legitimate",LOWER(TRIM(D12))="compliant",LOWER(TRIM(D12))="due diligence"),"PROHIBITED GENERIC STATUS","OK"))
M13: =IF(COUNTA(A13:L13)=0,"",IF(OR(LOWER(TRIM(D13))="approved",LOWER(TRIM(D13))="certified",LOWER(TRIM(D13))="safe",LOWER(TRIM(D13))="ethical",LOWER(TRIM(D13))="legitimate",LOWER(TRIM(D13))="compliant",LOWER(TRIM(D13))="due diligence"),"PROHIBITED GENERIC STATUS","OK"))
M14: =IF(COUNTA(A14:L14)=0,"",IF(OR(LOWER(TRIM(D14))="approved",LOWER(TRIM(D14))="certified",LOWER(TRIM(D14))="safe",LOWER(TRIM(D14))="ethical",LOWER(TRIM(D14))="legitimate",LOWER(TRIM(D14))="compliant",LOWER(TRIM(D14))="due diligence"),"PROHIBITED GENERIC STATUS","OK"))
M15: =IF(COUNTA(A15:L15)=0,"",IF(OR(LOWER(TRIM(D15))="approved",LOWER(TRIM(D15))="certified",LOWER(TRIM(D15))="safe",LOWER(TRIM(D15))="ethical",LOWER(TRIM(D15))="legitimate",LOWER(TRIM(D15))="compliant",LOWER(TRIM(D15))="due diligence"),"PROHIBITED GENERIC STATUS","OK"))
M16: =IF(COUNTA(A16:L16)=0,"",IF(OR(LOWER(TRIM(D16))="approved",LOWER(TRIM(D16))="certified",LOWER(TRIM(D16))="safe",LOWER(TRIM(D16))="ethical",LOWER(TRIM(D16))="legitimate",LOWER(TRIM(D16))="compliant",LOWER(TRIM(D16))="due diligence"),"PROHIBITED GENERIC STATUS","OK"))
M17: =IF(COUNTA(A17:L17)=0,"",IF(OR(LOWER(TRIM(D17))="approved",LOWER(TRIM(D17))="certified",LOWER(TRIM(D17))="safe",LOWER(TRIM(D17))="ethical",LOWER(TRIM(D17))="legitimate",LOWER(TRIM(D17))="compliant",LOWER(TRIM(D17))="due diligence"),"PROHIBITED GENERIC STATUS","OK"))
M18: =IF(COUNTA(A18:L18)=0,"",IF(OR(LOWER(TRIM(D18))="approved",LOWER(TRIM(D18))="certified",LOWER(TRIM(D18))="safe",LOWER(TRIM(D18))="ethical",LOWER(TRIM(D18))="legitimate",LOWER(TRIM(D18))="compliant",LOWER(TRIM(D18))="due diligence"),"PROHIBITED GENERIC STATUS","OK"))
M19: =IF(COUNTA(A19:L19)=0,"",IF(OR(LOWER(TRIM(D19))="approved",LOWER(TRIM(D19))="certified",LOWER(TRIM(D19))="safe",LOWER(TRIM(D19))="ethical",LOWER(TRIM(D19))="legitimate",LOWER(TRIM(D19))="compliant",LOWER(TRIM(D19))="due diligence"),"PROHIBITED GENERIC STATUS","OK"))
M20: =IF(COUNTA(A20:L20)=0,"",IF(OR(LOWER(TRIM(D20))="approved",LOWER(TRIM(D20))="certified",LOWER(TRIM(D20))="safe",LOWER(TRIM(D20))="ethical",LOWER(TRIM(D20))="legitimate",LOWER(TRIM(D20))="compliant",LOWER(TRIM(D20))="due diligence"),"PROHIBITED GENERIC STATUS","OK"))
... M250: =IF(COUNTA(A250:L250)=0,"",IF(OR(LOWER(TRIM(D250))="approved",LOWER(TRIM(D250))="certified",LOWER(TRIM(D250))="safe",LOWER(TRIM(D250))="ethical",LOWER(TRIM(D250))="legitimate",LOWER(TRIM(D250))="compliant",LOWER(TRIM(D250))="due diligence"),"PROHIBITED GENERIC STATUS","OK"))

Sheet Independence
A1: Independence, Protected Reporting, Host-Interest, and AI-Assistance Dossier - AF v6.2
A3: Dossier_ID | B3: Candidate_ID | C3: Sponsor_ID | D3: Host_ID | E3: Data_Control | F3: Publication_Control | G3: Reviewer_Selection_Control | H3: Protected_Dissent | I3: Null_Adverse_Publication_Right | J3: Affected_Party_Representation | K3: Financial_Interests | L3: Intellectual_Affiliations | M3: Conflict_Adjudicator | N3: Recorded_Status | O3: Derived_Status | P3: Status_Match | Q3: Rationale | R3: Host_Interest_in_Outcome | S3: Host_Precommitment | T3: AI_Assistance_Policy | U3: Reliability_Independence_Boundary | V3: Scenario_Set_Record_Status | W3: Shared_Model_Rating_Status | X3: Vocabulary_Check | Y3: Protected_Reporting_Channel | Z3: Confidentiality_Protection | AA3: Anti_Retaliation_Safeguard
A4: IND-ILL-001 | B4: SYNTH-CAND-HC | C4: SPONSOR-ILL-001 | D4: HOST-INDEPENDENT-01 | E4: Independent host | F4: Independent unconditional | G4: Independent host | H4: Yes | I4: Yes | J4: Yes | K4: Sponsor funds study; no outcome-contingent payment | L4: None | M4: Independent research-integrity officer | N4: Adequate with declared controls | O4: =IF(COUNTA(A4:N4)+COUNTA(Q4:W4)+COUNTA(Y4:AA4)=0,"",IF(OR(LEN(TRIM(A4))=0,LEN(TRIM(B4))=0,LEN(TRIM(C4))=0,LEN(TRIM(D4))=0,LEN(TRIM(E4))=0,LEN(TRIM(F4))=0,LEN(TRIM(G4))=0,LEN(TRIM(H4))=0,LEN(TRIM(I4))=0,LEN(TRIM(J4))=0,LEN(TRIM(R4))=0,LEN(TRIM(S4))=0,LEN(TRIM(T4))=0,LEN(TRIM(V4))=0,LEN(TRIM(W4))=0,LEN(TRIM(Y4))=0,LEN(TRIM(Z4))=0,LEN(TRIM(AA4))=0),"Indeterminate",IF(X4<>"OK","Indeterminate",IF(OR(E4="Indeterminate",F4="Indeterminate",G4="Indeterminate",R4="Indeterminate",S4="Indeterminate",T4="Indeterminate",V4="Indeterminate",W4="Indeterminate",Y4="Indeterminate",Z4="Indeterminate",AA4="Indeterminate"),"Indeterminate",IF(OR(E4="Sponsor controlled - invalid",F4="Sponsor veto - invalid",G4="Sponsor/candidate controlled - invalid",H4<>"Yes",I4<>"Yes",J4<>"Yes",R4="Predetermined outcome - invalid",S4="No credible precommitment",T4="Material assistance undisclosed",V4="Missing",V4="Changed after unblinding",W4="Material shared-model generation undisclosed",Y4="No protected reporting channel",Z4="No anonymity/confidentiality protection",AA4="No anti-retaliation safeguard"),"Inadequate",IF(OR(E4="Joint with firewall",F4="Independent with security redaction only",G4="Joint with public rules",K4<>"",AND(L4<>"",LOWER(L4)<>"none"),R4="Declared interest with enforceable firewall",S4="Conditional precommitment with disclosed limits",T4="Material assistance disclosed and separated",W4="Material shared-model generation disclosed",Z4="Not applicable with recorded rationale"),"Adequate with declared controls","Adequate")))))) | P4: =IF(AND(O4="",N4=""),"",IF(AND(O4<>"",N4=""),"UNRECORDED",IF(AND(O4="",N4<>""),"ORPHAN_RECORDED",IF(O4=N4,"MATCH","MISMATCH")))) | Q4: Funding is declared and separated from data, reviewer, adjudication, and publication control. | R4: Outcome-neutral; no preferred candidate outcome | S4: Preregistered and unconditional publication | T4: Retrieval/formatting only | U4: Ratings materially generated or harmonized by a shared model are not treated as independent human judgements. | V4: Present and frozen | W4: No shared-model rating generation | X4: =IF(COUNTA(E4:J4)+COUNTA(R4:T4)+COUNTA(V4:W4)+COUNTA(Y4:AA4)=0,"",IF(AND(COUNTIF(Vocabulary!$S$5:$S$8,E4)=1,COUNTIF(Vocabulary!$T$5:$T$8,F4)=1,COUNTIF(Vocabulary!$U$5:$U$8,G4)=1,COUNTIF(Vocabulary!$J$5:$J$6,H4)=1,COUNTIF(Vocabulary!$J$5:$J$6,I4)=1,COUNTIF(Vocabulary!$J$5:$J$6,J4)=1,COUNTIF(Vocabulary!$W$5:$W$8,R4)=1,COUNTIF(Vocabulary!$X$5:$X$8,S4)=1,COUNTIF(Vocabulary!$Y$5:$Y$9,T4)=1,COUNTIF(Vocabulary!$Z$5:$Z$8,V4)=1,COUNTIF(Vocabulary!$AA$5:$AA$9,W4)=1,COUNTIF(Vocabulary!$AB$5:$AB$7,Y4)=1,COUNTIF(Vocabulary!$AC$5:$AC$8,Z4)=1,COUNTIF(Vocabulary!$AD$5:$AD$7,AA4)=1),"OK","UNRECOGNISED_CONTROL_VALUE")) | Y4: Protected reporting channel available | Z4: Anonymous or confidential reporting available | AA4: Anti-retaliation safeguard documented
O5: =IF(COUNTA(A5:N5)+COUNTA(Q5:W5)+COUNTA(Y5:AA5)=0,"",IF(OR(LEN(TRIM(A5))=0,LEN(TRIM(B5))=0,LEN(TRIM(C5))=0,LEN(TRIM(D5))=0,LEN(TRIM(E5))=0,LEN(TRIM(F5))=0,LEN(TRIM(G5))=0,LEN(TRIM(H5))=0,LEN(TRIM(I5))=0,LEN(TRIM(J5))=0,LEN(TRIM(R5))=0,LEN(TRIM(S5))=0,LEN(TRIM(T5))=0,LEN(TRIM(V5))=0,LEN(TRIM(W5))=0,LEN(TRIM(Y5))=0,LEN(TRIM(Z5))=0,LEN(TRIM(AA5))=0),"Indeterminate",IF(X5<>"OK","Indeterminate",IF(OR(E5="Indeterminate",F5="Indeterminate",G5="Indeterminate",R5="Indeterminate",S5="Indeterminate",T5="Indeterminate",V5="Indeterminate",W5="Indeterminate",Y5="Indeterminate",Z5="Indeterminate",AA5="Indeterminate"),"Indeterminate",IF(OR(E5="Sponsor controlled - invalid",F5="Sponsor veto - invalid",G5="Sponsor/candidate controlled - invalid",H5<>"Yes",I5<>"Yes",J5<>"Yes",R5="Predetermined outcome - invalid",S5="No credible precommitment",T5="Material assistance undisclosed",V5="Missing",V5="Changed after unblinding",W5="Material shared-model generation undisclosed",Y5="No protected reporting channel",Z5="No anonymity/confidentiality protection",AA5="No anti-retaliation safeguard"),"Inadequate",IF(OR(E5="Joint with firewall",F5="Independent with security redaction only",G5="Joint with public rules",K5<>"",AND(L5<>"",LOWER(L5)<>"none"),R5="Declared interest with enforceable firewall",S5="Conditional precommitment with disclosed limits",T5="Material assistance disclosed and separated",W5="Material shared-model generation disclosed",Z5="Not applicable with recorded rationale"),"Adequate with declared controls","Adequate")))))) | P5: =IF(AND(O5="",N5=""),"",IF(AND(O5<>"",N5=""),"UNRECORDED",IF(AND(O5="",N5<>""),"ORPHAN_RECORDED",IF(O5=N5,"MATCH","MISMATCH")))) | X5: =IF(COUNTA(E5:J5)+COUNTA(R5:T5)+COUNTA(V5:W5)+COUNTA(Y5:AA5)=0,"",IF(AND(COUNTIF(Vocabulary!$S$5:$S$8,E5)=1,COUNTIF(Vocabulary!$T$5:$T$8,F5)=1,COUNTIF(Vocabulary!$U$5:$U$8,G5)=1,COUNTIF(Vocabulary!$J$5:$J$6,H5)=1,COUNTIF(Vocabulary!$J$5:$J$6,I5)=1,COUNTIF(Vocabulary!$J$5:$J$6,J5)=1,COUNTIF(Vocabulary!$W$5:$W$8,R5)=1,COUNTIF(Vocabulary!$X$5:$X$8,S5)=1,COUNTIF(Vocabulary!$Y$5:$Y$9,T5)=1,COUNTIF(Vocabulary!$Z$5:$Z$8,V5)=1,COUNTIF(Vocabulary!$AA$5:$AA$9,W5)=1,COUNTIF(Vocabulary!$AB$5:$AB$7,Y5)=1,COUNTIF(Vocabulary!$AC$5:$AC$8,Z5)=1,COUNTIF(Vocabulary!$AD$5:$AD$7,AA5)=1),"OK","UNRECOGNISED_CONTROL_VALUE"))
O6: =IF(COUNTA(A6:N6)+COUNTA(Q6:W6)+COUNTA(Y6:AA6)=0,"",IF(OR(LEN(TRIM(A6))=0,LEN(TRIM(B6))=0,LEN(TRIM(C6))=0,LEN(TRIM(D6))=0,LEN(TRIM(E6))=0,LEN(TRIM(F6))=0,LEN(TRIM(G6))=0,LEN(TRIM(H6))=0,LEN(TRIM(I6))=0,LEN(TRIM(J6))=0,LEN(TRIM(R6))=0,LEN(TRIM(S6))=0,LEN(TRIM(T6))=0,LEN(TRIM(V6))=0,LEN(TRIM(W6))=0,LEN(TRIM(Y6))=0,LEN(TRIM(Z6))=0,LEN(TRIM(AA6))=0),"Indeterminate",IF(X6<>"OK","Indeterminate",IF(OR(E6="Indeterminate",F6="Indeterminate",G6="Indeterminate",R6="Indeterminate",S6="Indeterminate",T6="Indeterminate",V6="Indeterminate",W6="Indeterminate",Y6="Indeterminate",Z6="Indeterminate",AA6="Indeterminate"),"Indeterminate",IF(OR(E6="Sponsor controlled - invalid",F6="Sponsor veto - invalid",G6="Sponsor/candidate controlled - invalid",H6<>"Yes",I6<>"Yes",J6<>"Yes",R6="Predetermined outcome - invalid",S6="No credible precommitment",T6="Material assistance undisclosed",V6="Missing",V6="Changed after unblinding",W6="Material shared-model generation undisclosed",Y6="No protected reporting channel",Z6="No anonymity/confidentiality protection",AA6="No anti-retaliation safeguard"),"Inadequate",IF(OR(E6="Joint with firewall",F6="Independent with security redaction only",G6="Joint with public rules",K6<>"",AND(L6<>"",LOWER(L6)<>"none"),R6="Declared interest with enforceable firewall",S6="Conditional precommitment with disclosed limits",T6="Material assistance disclosed and separated",W6="Material shared-model generation disclosed",Z6="Not applicable with recorded rationale"),"Adequate with declared controls","Adequate")))))) | P6: =IF(AND(O6="",N6=""),"",IF(AND(O6<>"",N6=""),"UNRECORDED",IF(AND(O6="",N6<>""),"ORPHAN_RECORDED",IF(O6=N6,"MATCH","MISMATCH")))) | X6: =IF(COUNTA(E6:J6)+COUNTA(R6:T6)+COUNTA(V6:W6)+COUNTA(Y6:AA6)=0,"",IF(AND(COUNTIF(Vocabulary!$S$5:$S$8,E6)=1,COUNTIF(Vocabulary!$T$5:$T$8,F6)=1,COUNTIF(Vocabulary!$U$5:$U$8,G6)=1,COUNTIF(Vocabulary!$J$5:$J$6,H6)=1,COUNTIF(Vocabulary!$J$5:$J$6,I6)=1,COUNTIF(Vocabulary!$J$5:$J$6,J6)=1,COUNTIF(Vocabulary!$W$5:$W$8,R6)=1,COUNTIF(Vocabulary!$X$5:$X$8,S6)=1,COUNTIF(Vocabulary!$Y$5:$Y$9,T6)=1,COUNTIF(Vocabulary!$Z$5:$Z$8,V6)=1,COUNTIF(Vocabulary!$AA$5:$AA$9,W6)=1,COUNTIF(Vocabulary!$AB$5:$AB$7,Y6)=1,COUNTIF(Vocabulary!$AC$5:$AC$8,Z6)=1,COUNTIF(Vocabulary!$AD$5:$AD$7,AA6)=1),"OK","UNRECOGNISED_CONTROL_VALUE"))
O7: =IF(COUNTA(A7:N7)+COUNTA(Q7:W7)+COUNTA(Y7:AA7)=0,"",IF(OR(LEN(TRIM(A7))=0,LEN(TRIM(B7))=0,LEN(TRIM(C7))=0,LEN(TRIM(D7))=0,LEN(TRIM(E7))=0,LEN(TRIM(F7))=0,LEN(TRIM(G7))=0,LEN(TRIM(H7))=0,LEN(TRIM(I7))=0,LEN(TRIM(J7))=0,LEN(TRIM(R7))=0,LEN(TRIM(S7))=0,LEN(TRIM(T7))=0,LEN(TRIM(V7))=0,LEN(TRIM(W7))=0,LEN(TRIM(Y7))=0,LEN(TRIM(Z7))=0,LEN(TRIM(AA7))=0),"Indeterminate",IF(X7<>"OK","Indeterminate",IF(OR(E7="Indeterminate",F7="Indeterminate",G7="Indeterminate",R7="Indeterminate",S7="Indeterminate",T7="Indeterminate",V7="Indeterminate",W7="Indeterminate",Y7="Indeterminate",Z7="Indeterminate",AA7="Indeterminate"),"Indeterminate",IF(OR(E7="Sponsor controlled - invalid",F7="Sponsor veto - invalid",G7="Sponsor/candidate controlled - invalid",H7<>"Yes",I7<>"Yes",J7<>"Yes",R7="Predetermined outcome - invalid",S7="No credible precommitment",T7="Material assistance undisclosed",V7="Missing",V7="Changed after unblinding",W7="Material shared-model generation undisclosed",Y7="No protected reporting channel",Z7="No anonymity/confidentiality protection",AA7="No anti-retaliation safeguard"),"Inadequate",IF(OR(E7="Joint with firewall",F7="Independent with security redaction only",G7="Joint with public rules",K7<>"",AND(L7<>"",LOWER(L7)<>"none"),R7="Declared interest with enforceable firewall",S7="Conditional precommitment with disclosed limits",T7="Material assistance disclosed and separated",W7="Material shared-model generation disclosed",Z7="Not applicable with recorded rationale"),"Adequate with declared controls","Adequate")))))) | P7: =IF(AND(O7="",N7=""),"",IF(AND(O7<>"",N7=""),"UNRECORDED",IF(AND(O7="",N7<>""),"ORPHAN_RECORDED",IF(O7=N7,"MATCH","MISMATCH")))) | X7: =IF(COUNTA(E7:J7)+COUNTA(R7:T7)+COUNTA(V7:W7)+COUNTA(Y7:AA7)=0,"",IF(AND(COUNTIF(Vocabulary!$S$5:$S$8,E7)=1,COUNTIF(Vocabulary!$T$5:$T$8,F7)=1,COUNTIF(Vocabulary!$U$5:$U$8,G7)=1,COUNTIF(Vocabulary!$J$5:$J$6,H7)=1,COUNTIF(Vocabulary!$J$5:$J$6,I7)=1,COUNTIF(Vocabulary!$J$5:$J$6,J7)=1,COUNTIF(Vocabulary!$W$5:$W$8,R7)=1,COUNTIF(Vocabulary!$X$5:$X$8,S7)=1,COUNTIF(Vocabulary!$Y$5:$Y$9,T7)=1,COUNTIF(Vocabulary!$Z$5:$Z$8,V7)=1,COUNTIF(Vocabulary!$AA$5:$AA$9,W7)=1,COUNTIF(Vocabulary!$AB$5:$AB$7,Y7)=1,COUNTIF(Vocabulary!$AC$5:$AC$8,Z7)=1,COUNTIF(Vocabulary!$AD$5:$AD$7,AA7)=1),"OK","UNRECOGNISED_CONTROL_VALUE"))
O8: =IF(COUNTA(A8:N8)+COUNTA(Q8:W8)+COUNTA(Y8:AA8)=0,"",IF(OR(LEN(TRIM(A8))=0,LEN(TRIM(B8))=0,LEN(TRIM(C8))=0,LEN(TRIM(D8))=0,LEN(TRIM(E8))=0,LEN(TRIM(F8))=0,LEN(TRIM(G8))=0,LEN(TRIM(H8))=0,LEN(TRIM(I8))=0,LEN(TRIM(J8))=0,LEN(TRIM(R8))=0,LEN(TRIM(S8))=0,LEN(TRIM(T8))=0,LEN(TRIM(V8))=0,LEN(TRIM(W8))=0,LEN(TRIM(Y8))=0,LEN(TRIM(Z8))=0,LEN(TRIM(AA8))=0),"Indeterminate",IF(X8<>"OK","Indeterminate",IF(OR(E8="Indeterminate",F8="Indeterminate",G8="Indeterminate",R8="Indeterminate",S8="Indeterminate",T8="Indeterminate",V8="Indeterminate",W8="Indeterminate",Y8="Indeterminate",Z8="Indeterminate",AA8="Indeterminate"),"Indeterminate",IF(OR(E8="Sponsor controlled - invalid",F8="Sponsor veto - invalid",G8="Sponsor/candidate controlled - invalid",H8<>"Yes",I8<>"Yes",J8<>"Yes",R8="Predetermined outcome - invalid",S8="No credible precommitment",T8="Material assistance undisclosed",V8="Missing",V8="Changed after unblinding",W8="Material shared-model generation undisclosed",Y8="No protected reporting channel",Z8="No anonymity/confidentiality protection",AA8="No anti-retaliation safeguard"),"Inadequate",IF(OR(E8="Joint with firewall",F8="Independent with security redaction only",G8="Joint with public rules",K8<>"",AND(L8<>"",LOWER(L8)<>"none"),R8="Declared interest with enforceable firewall",S8="Conditional precommitment with disclosed limits",T8="Material assistance disclosed and separated",W8="Material shared-model generation disclosed",Z8="Not applicable with recorded rationale"),"Adequate with declared controls","Adequate")))))) | P8: =IF(AND(O8="",N8=""),"",IF(AND(O8<>"",N8=""),"UNRECORDED",IF(AND(O8="",N8<>""),"ORPHAN_RECORDED",IF(O8=N8,"MATCH","MISMATCH")))) | X8: =IF(COUNTA(E8:J8)+COUNTA(R8:T8)+COUNTA(V8:W8)+COUNTA(Y8:AA8)=0,"",IF(AND(COUNTIF(Vocabulary!$S$5:$S$8,E8)=1,COUNTIF(Vocabulary!$T$5:$T$8,F8)=1,COUNTIF(Vocabulary!$U$5:$U$8,G8)=1,COUNTIF(Vocabulary!$J$5:$J$6,H8)=1,COUNTIF(Vocabulary!$J$5:$J$6,I8)=1,COUNTIF(Vocabulary!$J$5:$J$6,J8)=1,COUNTIF(Vocabulary!$W$5:$W$8,R8)=1,COUNTIF(Vocabulary!$X$5:$X$8,S8)=1,COUNTIF(Vocabulary!$Y$5:$Y$9,T8)=1,COUNTIF(Vocabulary!$Z$5:$Z$8,V8)=1,COUNTIF(Vocabulary!$AA$5:$AA$9,W8)=1,COUNTIF(Vocabulary!$AB$5:$AB$7,Y8)=1,COUNTIF(Vocabulary!$AC$5:$AC$8,Z8)=1,COUNTIF(Vocabulary!$AD$5:$AD$7,AA8)=1),"OK","UNRECOGNISED_CONTROL_VALUE"))
O9: =IF(COUNTA(A9:N9)+COUNTA(Q9:W9)+COUNTA(Y9:AA9)=0,"",IF(OR(LEN(TRIM(A9))=0,LEN(TRIM(B9))=0,LEN(TRIM(C9))=0,LEN(TRIM(D9))=0,LEN(TRIM(E9))=0,LEN(TRIM(F9))=0,LEN(TRIM(G9))=0,LEN(TRIM(H9))=0,LEN(TRIM(I9))=0,LEN(TRIM(J9))=0,LEN(TRIM(R9))=0,LEN(TRIM(S9))=0,LEN(TRIM(T9))=0,LEN(TRIM(V9))=0,LEN(TRIM(W9))=0,LEN(TRIM(Y9))=0,LEN(TRIM(Z9))=0,LEN(TRIM(AA9))=0),"Indeterminate",IF(X9<>"OK","Indeterminate",IF(OR(E9="Indeterminate",F9="Indeterminate",G9="Indeterminate",R9="Indeterminate",S9="Indeterminate",T9="Indeterminate",V9="Indeterminate",W9="Indeterminate",Y9="Indeterminate",Z9="Indeterminate",AA9="Indeterminate"),"Indeterminate",IF(OR(E9="Sponsor controlled - invalid",F9="Sponsor veto - invalid",G9="Sponsor/candidate controlled - invalid",H9<>"Yes",I9<>"Yes",J9<>"Yes",R9="Predetermined outcome - invalid",S9="No credible precommitment",T9="Material assistance undisclosed",V9="Missing",V9="Changed after unblinding",W9="Material shared-model generation undisclosed",Y9="No protected reporting channel",Z9="No anonymity/confidentiality protection",AA9="No anti-retaliation safeguard"),"Inadequate",IF(OR(E9="Joint with firewall",F9="Independent with security redaction only",G9="Joint with public rules",K9<>"",AND(L9<>"",LOWER(L9)<>"none"),R9="Declared interest with enforceable firewall",S9="Conditional precommitment with disclosed limits",T9="Material assistance disclosed and separated",W9="Material shared-model generation disclosed",Z9="Not applicable with recorded rationale"),"Adequate with declared controls","Adequate")))))) | P9: =IF(AND(O9="",N9=""),"",IF(AND(O9<>"",N9=""),"UNRECORDED",IF(AND(O9="",N9<>""),"ORPHAN_RECORDED",IF(O9=N9,"MATCH","MISMATCH")))) | X9: =IF(COUNTA(E9:J9)+COUNTA(R9:T9)+COUNTA(V9:W9)+COUNTA(Y9:AA9)=0,"",IF(AND(COUNTIF(Vocabulary!$S$5:$S$8,E9)=1,COUNTIF(Vocabulary!$T$5:$T$8,F9)=1,COUNTIF(Vocabulary!$U$5:$U$8,G9)=1,COUNTIF(Vocabulary!$J$5:$J$6,H9)=1,COUNTIF(Vocabulary!$J$5:$J$6,I9)=1,COUNTIF(Vocabulary!$J$5:$J$6,J9)=1,COUNTIF(Vocabulary!$W$5:$W$8,R9)=1,COUNTIF(Vocabulary!$X$5:$X$8,S9)=1,COUNTIF(Vocabulary!$Y$5:$Y$9,T9)=1,COUNTIF(Vocabulary!$Z$5:$Z$8,V9)=1,COUNTIF(Vocabulary!$AA$5:$AA$9,W9)=1,COUNTIF(Vocabulary!$AB$5:$AB$7,Y9)=1,COUNTIF(Vocabulary!$AC$5:$AC$8,Z9)=1,COUNTIF(Vocabulary!$AD$5:$AD$7,AA9)=1),"OK","UNRECOGNISED_CONTROL_VALUE"))
O10: =IF(COUNTA(A10:N10)+COUNTA(Q10:W10)+COUNTA(Y10:AA10)=0,"",IF(OR(LEN(TRIM(A10))=0,LEN(TRIM(B10))=0,LEN(TRIM(C10))=0,LEN(TRIM(D10))=0,LEN(TRIM(E10))=0,LEN(TRIM(F10))=0,LEN(TRIM(G10))=0,LEN(TRIM(H10))=0,LEN(TRIM(I10))=0,LEN(TRIM(J10))=0,LEN(TRIM(R10))=0,LEN(TRIM(S10))=0,LEN(TRIM(T10))=0,LEN(TRIM(V10))=0,LEN(TRIM(W10))=0,LEN(TRIM(Y10))=0,LEN(TRIM(Z10))=0,LEN(TRIM(AA10))=0),"Indeterminate",IF(X10<>"OK","Indeterminate",IF(OR(E10="Indeterminate",F10="Indeterminate",G10="Indeterminate",R10="Indeterminate",S10="Indeterminate",T10="Indeterminate",V10="Indeterminate",W10="Indeterminate",Y10="Indeterminate",Z10="Indeterminate",AA10="Indeterminate"),"Indeterminate",IF(OR(E10="Sponsor controlled - invalid",F10="Sponsor veto - invalid",G10="Sponsor/candidate controlled - invalid",H10<>"Yes",I10<>"Yes",J10<>"Yes",R10="Predetermined outcome - invalid",S10="No credible precommitment",T10="Material assistance undisclosed",V10="Missing",V10="Changed after unblinding",W10="Material shared-model generation undisclosed",Y10="No protected reporting channel",Z10="No anonymity/confidentiality protection",AA10="No anti-retaliation safeguard"),"Inadequate",IF(OR(E10="Joint with firewall",F10="Independent with security redaction only",G10="Joint with public rules",K10<>"",AND(L10<>"",LOWER(L10)<>"none"),R10="Declared interest with enforceable firewall",S10="Conditional precommitment with disclosed limits",T10="Material assistance disclosed and separated",W10="Material shared-model generation disclosed",Z10="Not applicable with recorded rationale"),"Adequate with declared controls","Adequate")))))) | P10: =IF(AND(O10="",N10=""),"",IF(AND(O10<>"",N10=""),"UNRECORDED",IF(AND(O10="",N10<>""),"ORPHAN_RECORDED",IF(O10=N10,"MATCH","MISMATCH")))) | X10: =IF(COUNTA(E10:J10)+COUNTA(R10:T10)+COUNTA(V10:W10)+COUNTA(Y10:AA10)=0,"",IF(AND(COUNTIF(Vocabulary!$S$5:$S$8,E10)=1,COUNTIF(Vocabulary!$T$5:$T$8,F10)=1,COUNTIF(Vocabulary!$U$5:$U$8,G10)=1,COUNTIF(Vocabulary!$J$5:$J$6,H10)=1,COUNTIF(Vocabulary!$J$5:$J$6,I10)=1,COUNTIF(Vocabulary!$J$5:$J$6,J10)=1,COUNTIF(Vocabulary!$W$5:$W$8,R10)=1,COUNTIF(Vocabulary!$X$5:$X$8,S10)=1,COUNTIF(Vocabulary!$Y$5:$Y$9,T10)=1,COUNTIF(Vocabulary!$Z$5:$Z$8,V10)=1,COUNTIF(Vocabulary!$AA$5:$AA$9,W10)=1,COUNTIF(Vocabulary!$AB$5:$AB$7,Y10)=1,COUNTIF(Vocabulary!$AC$5:$AC$8,Z10)=1,COUNTIF(Vocabulary!$AD$5:$AD$7,AA10)=1),"OK","UNRECOGNISED_CONTROL_VALUE"))
O11: =IF(COUNTA(A11:N11)+COUNTA(Q11:W11)+COUNTA(Y11:AA11)=0,"",IF(OR(LEN(TRIM(A11))=0,LEN(TRIM(B11))=0,LEN(TRIM(C11))=0,LEN(TRIM(D11))=0,LEN(TRIM(E11))=0,LEN(TRIM(F11))=0,LEN(TRIM(G11))=0,LEN(TRIM(H11))=0,LEN(TRIM(I11))=0,LEN(TRIM(J11))=0,LEN(TRIM(R11))=0,LEN(TRIM(S11))=0,LEN(TRIM(T11))=0,LEN(TRIM(V11))=0,LEN(TRIM(W11))=0,LEN(TRIM(Y11))=0,LEN(TRIM(Z11))=0,LEN(TRIM(AA11))=0),"Indeterminate",IF(X11<>"OK","Indeterminate",IF(OR(E11="Indeterminate",F11="Indeterminate",G11="Indeterminate",R11="Indeterminate",S11="Indeterminate",T11="Indeterminate",V11="Indeterminate",W11="Indeterminate",Y11="Indeterminate",Z11="Indeterminate",AA11="Indeterminate"),"Indeterminate",IF(OR(E11="Sponsor controlled - invalid",F11="Sponsor veto - invalid",G11="Sponsor/candidate controlled - invalid",H11<>"Yes",I11<>"Yes",J11<>"Yes",R11="Predetermined outcome - invalid",S11="No credible precommitment",T11="Material assistance undisclosed",V11="Missing",V11="Changed after unblinding",W11="Material shared-model generation undisclosed",Y11="No protected reporting channel",Z11="No anonymity/confidentiality protection",AA11="No anti-retaliation safeguard"),"Inadequate",IF(OR(E11="Joint with firewall",F11="Independent with security redaction only",G11="Joint with public rules",K11<>"",AND(L11<>"",LOWER(L11)<>"none"),R11="Declared interest with enforceable firewall",S11="Conditional precommitment with disclosed limits",T11="Material assistance disclosed and separated",W11="Material shared-model generation disclosed",Z11="Not applicable with recorded rationale"),"Adequate with declared controls","Adequate")))))) | P11: =IF(AND(O11="",N11=""),"",IF(AND(O11<>"",N11=""),"UNRECORDED",IF(AND(O11="",N11<>""),"ORPHAN_RECORDED",IF(O11=N11,"MATCH","MISMATCH")))) | X11: =IF(COUNTA(E11:J11)+COUNTA(R11:T11)+COUNTA(V11:W11)+COUNTA(Y11:AA11)=0,"",IF(AND(COUNTIF(Vocabulary!$S$5:$S$8,E11)=1,COUNTIF(Vocabulary!$T$5:$T$8,F11)=1,COUNTIF(Vocabulary!$U$5:$U$8,G11)=1,COUNTIF(Vocabulary!$J$5:$J$6,H11)=1,COUNTIF(Vocabulary!$J$5:$J$6,I11)=1,COUNTIF(Vocabulary!$J$5:$J$6,J11)=1,COUNTIF(Vocabulary!$W$5:$W$8,R11)=1,COUNTIF(Vocabulary!$X$5:$X$8,S11)=1,COUNTIF(Vocabulary!$Y$5:$Y$9,T11)=1,COUNTIF(Vocabulary!$Z$5:$Z$8,V11)=1,COUNTIF(Vocabulary!$AA$5:$AA$9,W11)=1,COUNTIF(Vocabulary!$AB$5:$AB$7,Y11)=1,COUNTIF(Vocabulary!$AC$5:$AC$8,Z11)=1,COUNTIF(Vocabulary!$AD$5:$AD$7,AA11)=1),"OK","UNRECOGNISED_CONTROL_VALUE"))
O12: =IF(COUNTA(A12:N12)+COUNTA(Q12:W12)+COUNTA(Y12:AA12)=0,"",IF(OR(LEN(TRIM(A12))=0,LEN(TRIM(B12))=0,LEN(TRIM(C12))=0,LEN(TRIM(D12))=0,LEN(TRIM(E12))=0,LEN(TRIM(F12))=0,LEN(TRIM(G12))=0,LEN(TRIM(H12))=0,LEN(TRIM(I12))=0,LEN(TRIM(J12))=0,LEN(TRIM(R12))=0,LEN(TRIM(S12))=0,LEN(TRIM(T12))=0,LEN(TRIM(V12))=0,LEN(TRIM(W12))=0,LEN(TRIM(Y12))=0,LEN(TRIM(Z12))=0,LEN(TRIM(AA12))=0),"Indeterminate",IF(X12<>"OK","Indeterminate",IF(OR(E12="Indeterminate",F12="Indeterminate",G12="Indeterminate",R12="Indeterminate",S12="Indeterminate",T12="Indeterminate",V12="Indeterminate",W12="Indeterminate",Y12="Indeterminate",Z12="Indeterminate",AA12="Indeterminate"),"Indeterminate",IF(OR(E12="Sponsor controlled - invalid",F12="Sponsor veto - invalid",G12="Sponsor/candidate controlled - invalid",H12<>"Yes",I12<>"Yes",J12<>"Yes",R12="Predetermined outcome - invalid",S12="No credible precommitment",T12="Material assistance undisclosed",V12="Missing",V12="Changed after unblinding",W12="Material shared-model generation undisclosed",Y12="No protected reporting channel",Z12="No anonymity/confidentiality protection",AA12="No anti-retaliation safeguard"),"Inadequate",IF(OR(E12="Joint with firewall",F12="Independent with security redaction only",G12="Joint with public rules",K12<>"",AND(L12<>"",LOWER(L12)<>"none"),R12="Declared interest with enforceable firewall",S12="Conditional precommitment with disclosed limits",T12="Material assistance disclosed and separated",W12="Material shared-model generation disclosed",Z12="Not applicable with recorded rationale"),"Adequate with declared controls","Adequate")))))) | P12: =IF(AND(O12="",N12=""),"",IF(AND(O12<>"",N12=""),"UNRECORDED",IF(AND(O12="",N12<>""),"ORPHAN_RECORDED",IF(O12=N12,"MATCH","MISMATCH")))) | X12: =IF(COUNTA(E12:J12)+COUNTA(R12:T12)+COUNTA(V12:W12)+COUNTA(Y12:AA12)=0,"",IF(AND(COUNTIF(Vocabulary!$S$5:$S$8,E12)=1,COUNTIF(Vocabulary!$T$5:$T$8,F12)=1,COUNTIF(Vocabulary!$U$5:$U$8,G12)=1,COUNTIF(Vocabulary!$J$5:$J$6,H12)=1,COUNTIF(Vocabulary!$J$5:$J$6,I12)=1,COUNTIF(Vocabulary!$J$5:$J$6,J12)=1,COUNTIF(Vocabulary!$W$5:$W$8,R12)=1,COUNTIF(Vocabulary!$X$5:$X$8,S12)=1,COUNTIF(Vocabulary!$Y$5:$Y$9,T12)=1,COUNTIF(Vocabulary!$Z$5:$Z$8,V12)=1,COUNTIF(Vocabulary!$AA$5:$AA$9,W12)=1,COUNTIF(Vocabulary!$AB$5:$AB$7,Y12)=1,COUNTIF(Vocabulary!$AC$5:$AC$8,Z12)=1,COUNTIF(Vocabulary!$AD$5:$AD$7,AA12)=1),"OK","UNRECOGNISED_CONTROL_VALUE"))
O13: =IF(COUNTA(A13:N13)+COUNTA(Q13:W13)+COUNTA(Y13:AA13)=0,"",IF(OR(LEN(TRIM(A13))=0,LEN(TRIM(B13))=0,LEN(TRIM(C13))=0,LEN(TRIM(D13))=0,LEN(TRIM(E13))=0,LEN(TRIM(F13))=0,LEN(TRIM(G13))=0,LEN(TRIM(H13))=0,LEN(TRIM(I13))=0,LEN(TRIM(J13))=0,LEN(TRIM(R13))=0,LEN(TRIM(S13))=0,LEN(TRIM(T13))=0,LEN(TRIM(V13))=0,LEN(TRIM(W13))=0,LEN(TRIM(Y13))=0,LEN(TRIM(Z13))=0,LEN(TRIM(AA13))=0),"Indeterminate",IF(X13<>"OK","Indeterminate",IF(OR(E13="Indeterminate",F13="Indeterminate",G13="Indeterminate",R13="Indeterminate",S13="Indeterminate",T13="Indeterminate",V13="Indeterminate",W13="Indeterminate",Y13="Indeterminate",Z13="Indeterminate",AA13="Indeterminate"),"Indeterminate",IF(OR(E13="Sponsor controlled - invalid",F13="Sponsor veto - invalid",G13="Sponsor/candidate controlled - invalid",H13<>"Yes",I13<>"Yes",J13<>"Yes",R13="Predetermined outcome - invalid",S13="No credible precommitment",T13="Material assistance undisclosed",V13="Missing",V13="Changed after unblinding",W13="Material shared-model generation undisclosed",Y13="No protected reporting channel",Z13="No anonymity/confidentiality protection",AA13="No anti-retaliation safeguard"),"Inadequate",IF(OR(E13="Joint with firewall",F13="Independent with security redaction only",G13="Joint with public rules",K13<>"",AND(L13<>"",LOWER(L13)<>"none"),R13="Declared interest with enforceable firewall",S13="Conditional precommitment with disclosed limits",T13="Material assistance disclosed and separated",W13="Material shared-model generation disclosed",Z13="Not applicable with recorded rationale"),"Adequate with declared controls","Adequate")))))) | P13: =IF(AND(O13="",N13=""),"",IF(AND(O13<>"",N13=""),"UNRECORDED",IF(AND(O13="",N13<>""),"ORPHAN_RECORDED",IF(O13=N13,"MATCH","MISMATCH")))) | X13: =IF(COUNTA(E13:J13)+COUNTA(R13:T13)+COUNTA(V13:W13)+COUNTA(Y13:AA13)=0,"",IF(AND(COUNTIF(Vocabulary!$S$5:$S$8,E13)=1,COUNTIF(Vocabulary!$T$5:$T$8,F13)=1,COUNTIF(Vocabulary!$U$5:$U$8,G13)=1,COUNTIF(Vocabulary!$J$5:$J$6,H13)=1,COUNTIF(Vocabulary!$J$5:$J$6,I13)=1,COUNTIF(Vocabulary!$J$5:$J$6,J13)=1,COUNTIF(Vocabulary!$W$5:$W$8,R13)=1,COUNTIF(Vocabulary!$X$5:$X$8,S13)=1,COUNTIF(Vocabulary!$Y$5:$Y$9,T13)=1,COUNTIF(Vocabulary!$Z$5:$Z$8,V13)=1,COUNTIF(Vocabulary!$AA$5:$AA$9,W13)=1,COUNTIF(Vocabulary!$AB$5:$AB$7,Y13)=1,COUNTIF(Vocabulary!$AC$5:$AC$8,Z13)=1,COUNTIF(Vocabulary!$AD$5:$AD$7,AA13)=1),"OK","UNRECOGNISED_CONTROL_VALUE"))
O14: =IF(COUNTA(A14:N14)+COUNTA(Q14:W14)+COUNTA(Y14:AA14)=0,"",IF(OR(LEN(TRIM(A14))=0,LEN(TRIM(B14))=0,LEN(TRIM(C14))=0,LEN(TRIM(D14))=0,LEN(TRIM(E14))=0,LEN(TRIM(F14))=0,LEN(TRIM(G14))=0,LEN(TRIM(H14))=0,LEN(TRIM(I14))=0,LEN(TRIM(J14))=0,LEN(TRIM(R14))=0,LEN(TRIM(S14))=0,LEN(TRIM(T14))=0,LEN(TRIM(V14))=0,LEN(TRIM(W14))=0,LEN(TRIM(Y14))=0,LEN(TRIM(Z14))=0,LEN(TRIM(AA14))=0),"Indeterminate",IF(X14<>"OK","Indeterminate",IF(OR(E14="Indeterminate",F14="Indeterminate",G14="Indeterminate",R14="Indeterminate",S14="Indeterminate",T14="Indeterminate",V14="Indeterminate",W14="Indeterminate",Y14="Indeterminate",Z14="Indeterminate",AA14="Indeterminate"),"Indeterminate",IF(OR(E14="Sponsor controlled - invalid",F14="Sponsor veto - invalid",G14="Sponsor/candidate controlled - invalid",H14<>"Yes",I14<>"Yes",J14<>"Yes",R14="Predetermined outcome - invalid",S14="No credible precommitment",T14="Material assistance undisclosed",V14="Missing",V14="Changed after unblinding",W14="Material shared-model generation undisclosed",Y14="No protected reporting channel",Z14="No anonymity/confidentiality protection",AA14="No anti-retaliation safeguard"),"Inadequate",IF(OR(E14="Joint with firewall",F14="Independent with security redaction only",G14="Joint with public rules",K14<>"",AND(L14<>"",LOWER(L14)<>"none"),R14="Declared interest with enforceable firewall",S14="Conditional precommitment with disclosed limits",T14="Material assistance disclosed and separated",W14="Material shared-model generation disclosed",Z14="Not applicable with recorded rationale"),"Adequate with declared controls","Adequate")))))) | P14: =IF(AND(O14="",N14=""),"",IF(AND(O14<>"",N14=""),"UNRECORDED",IF(AND(O14="",N14<>""),"ORPHAN_RECORDED",IF(O14=N14,"MATCH","MISMATCH")))) | X14: =IF(COUNTA(E14:J14)+COUNTA(R14:T14)+COUNTA(V14:W14)+COUNTA(Y14:AA14)=0,"",IF(AND(COUNTIF(Vocabulary!$S$5:$S$8,E14)=1,COUNTIF(Vocabulary!$T$5:$T$8,F14)=1,COUNTIF(Vocabulary!$U$5:$U$8,G14)=1,COUNTIF(Vocabulary!$J$5:$J$6,H14)=1,COUNTIF(Vocabulary!$J$5:$J$6,I14)=1,COUNTIF(Vocabulary!$J$5:$J$6,J14)=1,COUNTIF(Vocabulary!$W$5:$W$8,R14)=1,COUNTIF(Vocabulary!$X$5:$X$8,S14)=1,COUNTIF(Vocabulary!$Y$5:$Y$9,T14)=1,COUNTIF(Vocabulary!$Z$5:$Z$8,V14)=1,COUNTIF(Vocabulary!$AA$5:$AA$9,W14)=1,COUNTIF(Vocabulary!$AB$5:$AB$7,Y14)=1,COUNTIF(Vocabulary!$AC$5:$AC$8,Z14)=1,COUNTIF(Vocabulary!$AD$5:$AD$7,AA14)=1),"OK","UNRECOGNISED_CONTROL_VALUE"))
O15: =IF(COUNTA(A15:N15)+COUNTA(Q15:W15)+COUNTA(Y15:AA15)=0,"",IF(OR(LEN(TRIM(A15))=0,LEN(TRIM(B15))=0,LEN(TRIM(C15))=0,LEN(TRIM(D15))=0,LEN(TRIM(E15))=0,LEN(TRIM(F15))=0,LEN(TRIM(G15))=0,LEN(TRIM(H15))=0,LEN(TRIM(I15))=0,LEN(TRIM(J15))=0,LEN(TRIM(R15))=0,LEN(TRIM(S15))=0,LEN(TRIM(T15))=0,LEN(TRIM(V15))=0,LEN(TRIM(W15))=0,LEN(TRIM(Y15))=0,LEN(TRIM(Z15))=0,LEN(TRIM(AA15))=0),"Indeterminate",IF(X15<>"OK","Indeterminate",IF(OR(E15="Indeterminate",F15="Indeterminate",G15="Indeterminate",R15="Indeterminate",S15="Indeterminate",T15="Indeterminate",V15="Indeterminate",W15="Indeterminate",Y15="Indeterminate",Z15="Indeterminate",AA15="Indeterminate"),"Indeterminate",IF(OR(E15="Sponsor controlled - invalid",F15="Sponsor veto - invalid",G15="Sponsor/candidate controlled - invalid",H15<>"Yes",I15<>"Yes",J15<>"Yes",R15="Predetermined outcome - invalid",S15="No credible precommitment",T15="Material assistance undisclosed",V15="Missing",V15="Changed after unblinding",W15="Material shared-model generation undisclosed",Y15="No protected reporting channel",Z15="No anonymity/confidentiality protection",AA15="No anti-retaliation safeguard"),"Inadequate",IF(OR(E15="Joint with firewall",F15="Independent with security redaction only",G15="Joint with public rules",K15<>"",AND(L15<>"",LOWER(L15)<>"none"),R15="Declared interest with enforceable firewall",S15="Conditional precommitment with disclosed limits",T15="Material assistance disclosed and separated",W15="Material shared-model generation disclosed",Z15="Not applicable with recorded rationale"),"Adequate with declared controls","Adequate")))))) | P15: =IF(AND(O15="",N15=""),"",IF(AND(O15<>"",N15=""),"UNRECORDED",IF(AND(O15="",N15<>""),"ORPHAN_RECORDED",IF(O15=N15,"MATCH","MISMATCH")))) | X15: =IF(COUNTA(E15:J15)+COUNTA(R15:T15)+COUNTA(V15:W15)+COUNTA(Y15:AA15)=0,"",IF(AND(COUNTIF(Vocabulary!$S$5:$S$8,E15)=1,COUNTIF(Vocabulary!$T$5:$T$8,F15)=1,COUNTIF(Vocabulary!$U$5:$U$8,G15)=1,COUNTIF(Vocabulary!$J$5:$J$6,H15)=1,COUNTIF(Vocabulary!$J$5:$J$6,I15)=1,COUNTIF(Vocabulary!$J$5:$J$6,J15)=1,COUNTIF(Vocabulary!$W$5:$W$8,R15)=1,COUNTIF(Vocabulary!$X$5:$X$8,S15)=1,COUNTIF(Vocabulary!$Y$5:$Y$9,T15)=1,COUNTIF(Vocabulary!$Z$5:$Z$8,V15)=1,COUNTIF(Vocabulary!$AA$5:$AA$9,W15)=1,COUNTIF(Vocabulary!$AB$5:$AB$7,Y15)=1,COUNTIF(Vocabulary!$AC$5:$AC$8,Z15)=1,COUNTIF(Vocabulary!$AD$5:$AD$7,AA15)=1),"OK","UNRECOGNISED_CONTROL_VALUE"))
O16: =IF(COUNTA(A16:N16)+COUNTA(Q16:W16)+COUNTA(Y16:AA16)=0,"",IF(OR(LEN(TRIM(A16))=0,LEN(TRIM(B16))=0,LEN(TRIM(C16))=0,LEN(TRIM(D16))=0,LEN(TRIM(E16))=0,LEN(TRIM(F16))=0,LEN(TRIM(G16))=0,LEN(TRIM(H16))=0,LEN(TRIM(I16))=0,LEN(TRIM(J16))=0,LEN(TRIM(R16))=0,LEN(TRIM(S16))=0,LEN(TRIM(T16))=0,LEN(TRIM(V16))=0,LEN(TRIM(W16))=0,LEN(TRIM(Y16))=0,LEN(TRIM(Z16))=0,LEN(TRIM(AA16))=0),"Indeterminate",IF(X16<>"OK","Indeterminate",IF(OR(E16="Indeterminate",F16="Indeterminate",G16="Indeterminate",R16="Indeterminate",S16="Indeterminate",T16="Indeterminate",V16="Indeterminate",W16="Indeterminate",Y16="Indeterminate",Z16="Indeterminate",AA16="Indeterminate"),"Indeterminate",IF(OR(E16="Sponsor controlled - invalid",F16="Sponsor veto - invalid",G16="Sponsor/candidate controlled - invalid",H16<>"Yes",I16<>"Yes",J16<>"Yes",R16="Predetermined outcome - invalid",S16="No credible precommitment",T16="Material assistance undisclosed",V16="Missing",V16="Changed after unblinding",W16="Material shared-model generation undisclosed",Y16="No protected reporting channel",Z16="No anonymity/confidentiality protection",AA16="No anti-retaliation safeguard"),"Inadequate",IF(OR(E16="Joint with firewall",F16="Independent with security redaction only",G16="Joint with public rules",K16<>"",AND(L16<>"",LOWER(L16)<>"none"),R16="Declared interest with enforceable firewall",S16="Conditional precommitment with disclosed limits",T16="Material assistance disclosed and separated",W16="Material shared-model generation disclosed",Z16="Not applicable with recorded rationale"),"Adequate with declared controls","Adequate")))))) | P16: =IF(AND(O16="",N16=""),"",IF(AND(O16<>"",N16=""),"UNRECORDED",IF(AND(O16="",N16<>""),"ORPHAN_RECORDED",IF(O16=N16,"MATCH","MISMATCH")))) | X16: =IF(COUNTA(E16:J16)+COUNTA(R16:T16)+COUNTA(V16:W16)+COUNTA(Y16:AA16)=0,"",IF(AND(COUNTIF(Vocabulary!$S$5:$S$8,E16)=1,COUNTIF(Vocabulary!$T$5:$T$8,F16)=1,COUNTIF(Vocabulary!$U$5:$U$8,G16)=1,COUNTIF(Vocabulary!$J$5:$J$6,H16)=1,COUNTIF(Vocabulary!$J$5:$J$6,I16)=1,COUNTIF(Vocabulary!$J$5:$J$6,J16)=1,COUNTIF(Vocabulary!$W$5:$W$8,R16)=1,COUNTIF(Vocabulary!$X$5:$X$8,S16)=1,COUNTIF(Vocabulary!$Y$5:$Y$9,T16)=1,COUNTIF(Vocabulary!$Z$5:$Z$8,V16)=1,COUNTIF(Vocabulary!$AA$5:$AA$9,W16)=1,COUNTIF(Vocabulary!$AB$5:$AB$7,Y16)=1,COUNTIF(Vocabulary!$AC$5:$AC$8,Z16)=1,COUNTIF(Vocabulary!$AD$5:$AD$7,AA16)=1),"OK","UNRECOGNISED_CONTROL_VALUE"))
... O250: =IF(COUNTA(A250:N250)+COUNTA(Q250:W250)+COUNTA(Y250:AA250)=0,"",IF(OR(LEN(TRIM(A250))=0,LEN(TRIM(B250))=0,LEN(TRIM(C250))=0,LEN(TRIM(D250))=0,LEN(TRIM(E250))=0,LEN(TRIM(F250))=0,LEN(TRIM(G250))=0,LEN(TRIM(H250))=0,LEN(TRIM(I250))=0,LEN(TRIM(J250))=0,LEN(TRIM(R250))=0,LEN(TRIM(S250))=0,LEN(TRIM(T250))=0,LEN(TRIM(V250))=0,LEN(TRIM(W250))=0,LEN(TRIM(Y250))=0,LEN(TRIM(Z250))=0,LEN(TRIM(AA250))=0),"Indeterminate",IF(X250<>"OK","Indeterminate",IF(OR(E250="Indeterminate",F250="Indeterminate",G250="Indeterminate",R250="Indeterminate",S250="Indeterminate",T250="Indeterminate",V250="Indeterminate",W250="Indeterminate",Y250="Indeterminate",Z250="Indeterminate",AA250="Indeterminate"),"Indeterminate",IF(OR(E250="Sponsor controlled - invalid",F250="Sponsor veto - invalid",G250="Sponsor/candidate controlled - invalid",H250<>"Yes",I250<>"Yes",J250<>"Yes",R250="Predetermined outcome - invalid",S250="No credible precommitment",T250="Material assistance undisclosed",V250="Missing",V250="Changed after unblinding",W250="Material shared-model generation undisclosed",Y250="No protected reporting channel",Z250="No anonymity/confidentiality protection",AA250="No anti-retaliation safeguard"),"Inadequate",IF(OR(E250="Joint with firewall",F250="Independent with security redaction only",G250="Joint with public rules",K250<>"",AND(L250<>"",LOWER(L250)<>"none"),R250="Declared interest with enforceable firewall",S250="Conditional precommitment with disclosed limits",T250="Material assistance disclosed and separated",W250="Material shared-model generation disclosed",Z250="Not applicable with recorded rationale"),"Adequate with declared controls","Adequate")))))) | P250: =IF(AND(O250="",N250=""),"",IF(AND(O250<>"",N250=""),"UNRECORDED",IF(AND(O250="",N250<>""),"ORPHAN_RECORDED",IF(O250=N250,"MATCH","MISMATCH")))) | X250: =IF(COUNTA(E250:J250)+COUNTA(R250:T250)+COUNTA(V250:W250)+COUNTA(Y250:AA250)=0,"",IF(AND(COUNTIF(Vocabulary!$S$5:$S$8,E250)=1,COUNTIF(Vocabulary!$T$5:$T$8,F250)=1,COUNTIF(Vocabulary!$U$5:$U$8,G250)=1,COUNTIF(Vocabulary!$J$5:$J$6,H250)=1,COUNTIF(Vocabulary!$J$5:$J$6,I250)=1,COUNTIF(Vocabulary!$J$5:$J$6,J250)=1,COUNTIF(Vocabulary!$W$5:$W$8,R250)=1,COUNTIF(Vocabulary!$X$5:$X$8,S250)=1,COUNTIF(Vocabulary!$Y$5:$Y$9,T250)=1,COUNTIF(Vocabulary!$Z$5:$Z$8,V250)=1,COUNTIF(Vocabulary!$AA$5:$AA$9,W250)=1,COUNTIF(Vocabulary!$AB$5:$AB$7,Y250)=1,COUNTIF(Vocabulary!$AC$5:$AC$8,Z250)=1,COUNTIF(Vocabulary!$AD$5:$AD$7,AA250)=1),"OK","UNRECOGNISED_CONTROL_VALUE"))

Sheet Burden_Log
A1: Burden, Capacity, Access, Translation, Custody, and Governance Gate - AF v6.2
A3: Record_ID | B3: Case_ID | C3: Profile | D3: Reviewer_Hours_Available | E3: Reviewer_Hours_Required | F3: Adjudication_Hours_Available | G3: Adjudication_Hours_Required | H3: Calendar_Days_Available | I3: Calendar_Days_Required | J3: Qualified_Reviewers | K3: Minimum_Reviewers | L3: Access_Support_Required | M3: Access_Support_Funded | N3: Access_Support_Delivered | O3: Unmet_Access_Needs | P3: Derived_Feasibility | Q3: Recorded_Feasibility | R3: Status_Match | S3: Total_Hours | T3: Direct_Cost | U3: Uncompensated_Hours | V3: Reported_Burden_0_10 | W3: Administration_Status | X3: Burden_Cohort | Y3: Interpretation_or_Translation_Required | Z3: Translation_Funded | AA3: Translation_Delivered | AB3: Evidence_Custody_Adequate | AC3: Governance_Capacity_Adequate | AD3: Vocabulary_Check
A4: BDV-ILL-001 | B4: CASE-ILL-001 | C4: AF-Standard | D4: 24 | E4: 18 | F4: 8 | G4: 6 | H4: 20 | I4: 14 | J4: 4 | K4: 3 | L4: Yes | M4: Yes | N4: Yes | P4: =IF(COUNTA(A4:O4)+COUNTA(Q4)+COUNTA(T4:W4)+COUNTA(Y4:AC4)=0,"",IF(OR(NOT(ISNUMBER(D4)),NOT(ISNUMBER(E4)),NOT(ISNUMBER(F4)),NOT(ISNUMBER(G4)),NOT(ISNUMBER(H4)),NOT(ISNUMBER(I4)),NOT(ISNUMBER(J4)),NOT(ISNUMBER(K4)),AD4<>"OK"),"Not feasible",IF(OR(D4<E4,F4<G4,H4<I4,J4<K4,AND(L4="Yes",OR(M4<>"Yes",N4<>"Yes")),AND(Y4="Yes",OR(Z4<>"Yes",AA4<>"Yes")),AB4<>"Yes",AC4<>"Yes"),"Not feasible",IF(OR(L4="Yes",Y4="Yes"),"Feasible with verified support","Feasible")))) | Q4: Feasible with verified support | R4: =IF(AND(P4="",Q4=""),"",IF(AND(P4<>"",Q4=""),"UNRECORDED",IF(AND(P4="",Q4<>""),"ORPHAN_RECORDED",IF(P4=Q4,"MATCH","MISMATCH")))) | S4: =IF(OR(NOT(ISNUMBER(E4)),NOT(ISNUMBER(G4))),"",E4+G4) | T4: 620 | U4: 0 | V4: 5 | W4: Completed | X4: =IF(A4="","",IF(AND(W4="Completed",OR(P4="Feasible",P4="Feasible with verified support")),"Completed feasible",IF(OR(P4="Not feasible",W4="Stopped before rating",W4="Aborted during review"),"Infeasible or aborted","Incomplete"))) | Y4: No | Z4: Yes | AA4: Yes | AB4: Yes | AC4: Yes | AD4: =IF(COUNTA(A4:O4)+COUNTA(Q4)+COUNTA(T4:W4)+COUNTA(Y4:AC4)=0,"",IF(AND(COUNTIF(Vocabulary!$J$5:$J$6,L4)=1,COUNTIF(Vocabulary!$J$5:$J$6,M4)=1,COUNTIF(Vocabulary!$J$5:$J$6,N4)=1,COUNTIF(Vocabulary!$J$5:$J$6,Y4)=1,COUNTIF(Vocabulary!$J$5:$J$6,Z4)=1,COUNTIF(Vocabulary!$J$5:$J$6,AA4)=1,COUNTIF(Vocabulary!$J$5:$J$6,AB4)=1,COUNTIF(Vocabulary!$J$5:$J$6,AC4)=1),"OK","UNRECOGNISED_BURDEN_VALUE"))
A5: BDV-ILL-002 | B5: CASE-ILL-FALSE-GREEN | C5: AF-Standard | D5: 24 | E5: 18 | F5: 8 | G5: 6 | H5: 5 | I5: 14 | J5: 1 | K5: 3 | L5: Yes | M5: Yes | N5: No | O5: Interpretation unavailable | P5: =IF(COUNTA(A5:O5)+COUNTA(Q5)+COUNTA(T5:W5)+COUNTA(Y5:AC5)=0,"",IF(OR(NOT(ISNUMBER(D5)),NOT(ISNUMBER(E5)),NOT(ISNUMBER(F5)),NOT(ISNUMBER(G5)),NOT(ISNUMBER(H5)),NOT(ISNUMBER(I5)),NOT(ISNUMBER(J5)),NOT(ISNUMBER(K5)),AD5<>"OK"),"Not feasible",IF(OR(D5<E5,F5<G5,H5<I5,J5<K5,AND(L5="Yes",OR(M5<>"Yes",N5<>"Yes")),AND(Y5="Yes",OR(Z5<>"Yes",AA5<>"Yes")),AB5<>"Yes",AC5<>"Yes"),"Not feasible",IF(OR(L5="Yes",Y5="Yes"),"Feasible with verified support","Feasible")))) | Q5: Not feasible | R5: =IF(AND(P5="",Q5=""),"",IF(AND(P5<>"",Q5=""),"UNRECORDED",IF(AND(P5="",Q5<>""),"ORPHAN_RECORDED",IF(P5=Q5,"MATCH","MISMATCH")))) | S5: =IF(OR(NOT(ISNUMBER(E5)),NOT(ISNUMBER(G5))),"",E5+G5) | T5: 300 | U5: 8 | V5: 8 | W5: Stopped before rating | X5: =IF(A5="","",IF(AND(W5="Completed",OR(P5="Feasible",P5="Feasible with verified support")),"Completed feasible",IF(OR(P5="Not feasible",W5="Stopped before rating",W5="Aborted during review"),"Infeasible or aborted","Incomplete"))) | Y5: Yes | Z5: No | AA5: No | AB5: Yes | AC5: Yes | AD5: =IF(COUNTA(A5:O5)+COUNTA(Q5)+COUNTA(T5:W5)+COUNTA(Y5:AC5)=0,"",IF(AND(COUNTIF(Vocabulary!$J$5:$J$6,L5)=1,COUNTIF(Vocabulary!$J$5:$J$6,M5)=1,COUNTIF(Vocabulary!$J$5:$J$6,N5)=1,COUNTIF(Vocabulary!$J$5:$J$6,Y5)=1,COUNTIF(Vocabulary!$J$5:$J$6,Z5)=1,COUNTIF(Vocabulary!$J$5:$J$6,AA5)=1,COUNTIF(Vocabulary!$J$5:$J$6,AB5)=1,COUNTIF(Vocabulary!$J$5:$J$6,AC5)=1),"OK","UNRECOGNISED_BURDEN_VALUE"))
P6: =IF(COUNTA(A6:O6)+COUNTA(Q6)+COUNTA(T6:W6)+COUNTA(Y6:AC6)=0,"",IF(OR(NOT(ISNUMBER(D6)),NOT(ISNUMBER(E6)),NOT(ISNUMBER(F6)),NOT(ISNUMBER(G6)),NOT(ISNUMBER(H6)),NOT(ISNUMBER(I6)),NOT(ISNUMBER(J6)),NOT(ISNUMBER(K6)),AD6<>"OK"),"Not feasible",IF(OR(D6<E6,F6<G6,H6<I6,J6<K6,AND(L6="Yes",OR(M6<>"Yes",N6<>"Yes")),AND(Y6="Yes",OR(Z6<>"Yes",AA6<>"Yes")),AB6<>"Yes",AC6<>"Yes"),"Not feasible",IF(OR(L6="Yes",Y6="Yes"),"Feasible with verified support","Feasible")))) | R6: =IF(AND(P6="",Q6=""),"",IF(AND(P6<>"",Q6=""),"UNRECORDED",IF(AND(P6="",Q6<>""),"ORPHAN_RECORDED",IF(P6=Q6,"MATCH","MISMATCH")))) | S6: =IF(OR(NOT(ISNUMBER(E6)),NOT(ISNUMBER(G6))),"",E6+G6) | X6: =IF(A6="","",IF(AND(W6="Completed",OR(P6="Feasible",P6="Feasible with verified support")),"Completed feasible",IF(OR(P6="Not feasible",W6="Stopped before rating",W6="Aborted during review"),"Infeasible or aborted","Incomplete"))) | AD6: =IF(COUNTA(A6:O6)+COUNTA(Q6)+COUNTA(T6:W6)+COUNTA(Y6:AC6)=0,"",IF(AND(COUNTIF(Vocabulary!$J$5:$J$6,L6)=1,COUNTIF(Vocabulary!$J$5:$J$6,M6)=1,COUNTIF(Vocabulary!$J$5:$J$6,N6)=1,COUNTIF(Vocabulary!$J$5:$J$6,Y6)=1,COUNTIF(Vocabulary!$J$5:$J$6,Z6)=1,COUNTIF(Vocabulary!$J$5:$J$6,AA6)=1,COUNTIF(Vocabulary!$J$5:$J$6,AB6)=1,COUNTIF(Vocabulary!$J$5:$J$6,AC6)=1),"OK","UNRECOGNISED_BURDEN_VALUE"))
P7: =IF(COUNTA(A7:O7)+COUNTA(Q7)+COUNTA(T7:W7)+COUNTA(Y7:AC7)=0,"",IF(OR(NOT(ISNUMBER(D7)),NOT(ISNUMBER(E7)),NOT(ISNUMBER(F7)),NOT(ISNUMBER(G7)),NOT(ISNUMBER(H7)),NOT(ISNUMBER(I7)),NOT(ISNUMBER(J7)),NOT(ISNUMBER(K7)),AD7<>"OK"),"Not feasible",IF(OR(D7<E7,F7<G7,H7<I7,J7<K7,AND(L7="Yes",OR(M7<>"Yes",N7<>"Yes")),AND(Y7="Yes",OR(Z7<>"Yes",AA7<>"Yes")),AB7<>"Yes",AC7<>"Yes"),"Not feasible",IF(OR(L7="Yes",Y7="Yes"),"Feasible with verified support","Feasible")))) | R7: =IF(AND(P7="",Q7=""),"",IF(AND(P7<>"",Q7=""),"UNRECORDED",IF(AND(P7="",Q7<>""),"ORPHAN_RECORDED",IF(P7=Q7,"MATCH","MISMATCH")))) | S7: =IF(OR(NOT(ISNUMBER(E7)),NOT(ISNUMBER(G7))),"",E7+G7) | X7: =IF(A7="","",IF(AND(W7="Completed",OR(P7="Feasible",P7="Feasible with verified support")),"Completed feasible",IF(OR(P7="Not feasible",W7="Stopped before rating",W7="Aborted during review"),"Infeasible or aborted","Incomplete"))) | AD7: =IF(COUNTA(A7:O7)+COUNTA(Q7)+COUNTA(T7:W7)+COUNTA(Y7:AC7)=0,"",IF(AND(COUNTIF(Vocabulary!$J$5:$J$6,L7)=1,COUNTIF(Vocabulary!$J$5:$J$6,M7)=1,COUNTIF(Vocabulary!$J$5:$J$6,N7)=1,COUNTIF(Vocabulary!$J$5:$J$6,Y7)=1,COUNTIF(Vocabulary!$J$5:$J$6,Z7)=1,COUNTIF(Vocabulary!$J$5:$J$6,AA7)=1,COUNTIF(Vocabulary!$J$5:$J$6,AB7)=1,COUNTIF(Vocabulary!$J$5:$J$6,AC7)=1),"OK","UNRECOGNISED_BURDEN_VALUE"))
P8: =IF(COUNTA(A8:O8)+COUNTA(Q8)+COUNTA(T8:W8)+COUNTA(Y8:AC8)=0,"",IF(OR(NOT(ISNUMBER(D8)),NOT(ISNUMBER(E8)),NOT(ISNUMBER(F8)),NOT(ISNUMBER(G8)),NOT(ISNUMBER(H8)),NOT(ISNUMBER(I8)),NOT(ISNUMBER(J8)),NOT(ISNUMBER(K8)),AD8<>"OK"),"Not feasible",IF(OR(D8<E8,F8<G8,H8<I8,J8<K8,AND(L8="Yes",OR(M8<>"Yes",N8<>"Yes")),AND(Y8="Yes",OR(Z8<>"Yes",AA8<>"Yes")),AB8<>"Yes",AC8<>"Yes"),"Not feasible",IF(OR(L8="Yes",Y8="Yes"),"Feasible with verified support","Feasible")))) | R8: =IF(AND(P8="",Q8=""),"",IF(AND(P8<>"",Q8=""),"UNRECORDED",IF(AND(P8="",Q8<>""),"ORPHAN_RECORDED",IF(P8=Q8,"MATCH","MISMATCH")))) | S8: =IF(OR(NOT(ISNUMBER(E8)),NOT(ISNUMBER(G8))),"",E8+G8) | X8: =IF(A8="","",IF(AND(W8="Completed",OR(P8="Feasible",P8="Feasible with verified support")),"Completed feasible",IF(OR(P8="Not feasible",W8="Stopped before rating",W8="Aborted during review"),"Infeasible or aborted","Incomplete"))) | AD8: =IF(COUNTA(A8:O8)+COUNTA(Q8)+COUNTA(T8:W8)+COUNTA(Y8:AC8)=0,"",IF(AND(COUNTIF(Vocabulary!$J$5:$J$6,L8)=1,COUNTIF(Vocabulary!$J$5:$J$6,M8)=1,COUNTIF(Vocabulary!$J$5:$J$6,N8)=1,COUNTIF(Vocabulary!$J$5:$J$6,Y8)=1,COUNTIF(Vocabulary!$J$5:$J$6,Z8)=1,COUNTIF(Vocabulary!$J$5:$J$6,AA8)=1,COUNTIF(Vocabulary!$J$5:$J$6,AB8)=1,COUNTIF(Vocabulary!$J$5:$J$6,AC8)=1),"OK","UNRECOGNISED_BURDEN_VALUE"))
P9: =IF(COUNTA(A9:O9)+COUNTA(Q9)+COUNTA(T9:W9)+COUNTA(Y9:AC9)=0,"",IF(OR(NOT(ISNUMBER(D9)),NOT(ISNUMBER(E9)),NOT(ISNUMBER(F9)),NOT(ISNUMBER(G9)),NOT(ISNUMBER(H9)),NOT(ISNUMBER(I9)),NOT(ISNUMBER(J9)),NOT(ISNUMBER(K9)),AD9<>"OK"),"Not feasible",IF(OR(D9<E9,F9<G9,H9<I9,J9<K9,AND(L9="Yes",OR(M9<>"Yes",N9<>"Yes")),AND(Y9="Yes",OR(Z9<>"Yes",AA9<>"Yes")),AB9<>"Yes",AC9<>"Yes"),"Not feasible",IF(OR(L9="Yes",Y9="Yes"),"Feasible with verified support","Feasible")))) | R9: =IF(AND(P9="",Q9=""),"",IF(AND(P9<>"",Q9=""),"UNRECORDED",IF(AND(P9="",Q9<>""),"ORPHAN_RECORDED",IF(P9=Q9,"MATCH","MISMATCH")))) | S9: =IF(OR(NOT(ISNUMBER(E9)),NOT(ISNUMBER(G9))),"",E9+G9) | X9: =IF(A9="","",IF(AND(W9="Completed",OR(P9="Feasible",P9="Feasible with verified support")),"Completed feasible",IF(OR(P9="Not feasible",W9="Stopped before rating",W9="Aborted during review"),"Infeasible or aborted","Incomplete"))) | AD9: =IF(COUNTA(A9:O9)+COUNTA(Q9)+COUNTA(T9:W9)+COUNTA(Y9:AC9)=0,"",IF(AND(COUNTIF(Vocabulary!$J$5:$J$6,L9)=1,COUNTIF(Vocabulary!$J$5:$J$6,M9)=1,COUNTIF(Vocabulary!$J$5:$J$6,N9)=1,COUNTIF(Vocabulary!$J$5:$J$6,Y9)=1,COUNTIF(Vocabulary!$J$5:$J$6,Z9)=1,COUNTIF(Vocabulary!$J$5:$J$6,AA9)=1,COUNTIF(Vocabulary!$J$5:$J$6,AB9)=1,COUNTIF(Vocabulary!$J$5:$J$6,AC9)=1),"OK","UNRECOGNISED_BURDEN_VALUE"))
P10: =IF(COUNTA(A10:O10)+COUNTA(Q10)+COUNTA(T10:W10)+COUNTA(Y10:AC10)=0,"",IF(OR(NOT(ISNUMBER(D10)),NOT(ISNUMBER(E10)),NOT(ISNUMBER(F10)),NOT(ISNUMBER(G10)),NOT(ISNUMBER(H10)),NOT(ISNUMBER(I10)),NOT(ISNUMBER(J10)),NOT(ISNUMBER(K10)),AD10<>"OK"),"Not feasible",IF(OR(D10<E10,F10<G10,H10<I10,J10<K10,AND(L10="Yes",OR(M10<>"Yes",N10<>"Yes")),AND(Y10="Yes",OR(Z10<>"Yes",AA10<>"Yes")),AB10<>"Yes",AC10<>"Yes"),"Not feasible",IF(OR(L10="Yes",Y10="Yes"),"Feasible with verified support","Feasible")))) | R10: =IF(AND(P10="",Q10=""),"",IF(AND(P10<>"",Q10=""),"UNRECORDED",IF(AND(P10="",Q10<>""),"ORPHAN_RECORDED",IF(P10=Q10,"MATCH","MISMATCH")))) | S10: =IF(OR(NOT(ISNUMBER(E10)),NOT(ISNUMBER(G10))),"",E10+G10) | X10: =IF(A10="","",IF(AND(W10="Completed",OR(P10="Feasible",P10="Feasible with verified support")),"Completed feasible",IF(OR(P10="Not feasible",W10="Stopped before rating",W10="Aborted during review"),"Infeasible or aborted","Incomplete"))) | AD10: =IF(COUNTA(A10:O10)+COUNTA(Q10)+COUNTA(T10:W10)+COUNTA(Y10:AC10)=0,"",IF(AND(COUNTIF(Vocabulary!$J$5:$J$6,L10)=1,COUNTIF(Vocabulary!$J$5:$J$6,M10)=1,COUNTIF(Vocabulary!$J$5:$J$6,N10)=1,COUNTIF(Vocabulary!$J$5:$J$6,Y10)=1,COUNTIF(Vocabulary!$J$5:$J$6,Z10)=1,COUNTIF(Vocabulary!$J$5:$J$6,AA10)=1,COUNTIF(Vocabulary!$J$5:$J$6,AB10)=1,COUNTIF(Vocabulary!$J$5:$J$6,AC10)=1),"OK","UNRECOGNISED_BURDEN_VALUE"))
P11: =IF(COUNTA(A11:O11)+COUNTA(Q11)+COUNTA(T11:W11)+COUNTA(Y11:AC11)=0,"",IF(OR(NOT(ISNUMBER(D11)),NOT(ISNUMBER(E11)),NOT(ISNUMBER(F11)),NOT(ISNUMBER(G11)),NOT(ISNUMBER(H11)),NOT(ISNUMBER(I11)),NOT(ISNUMBER(J11)),NOT(ISNUMBER(K11)),AD11<>"OK"),"Not feasible",IF(OR(D11<E11,F11<G11,H11<I11,J11<K11,AND(L11="Yes",OR(M11<>"Yes",N11<>"Yes")),AND(Y11="Yes",OR(Z11<>"Yes",AA11<>"Yes")),AB11<>"Yes",AC11<>"Yes"),"Not feasible",IF(OR(L11="Yes",Y11="Yes"),"Feasible with verified support","Feasible")))) | R11: =IF(AND(P11="",Q11=""),"",IF(AND(P11<>"",Q11=""),"UNRECORDED",IF(AND(P11="",Q11<>""),"ORPHAN_RECORDED",IF(P11=Q11,"MATCH","MISMATCH")))) | S11: =IF(OR(NOT(ISNUMBER(E11)),NOT(ISNUMBER(G11))),"",E11+G11) | X11: =IF(A11="","",IF(AND(W11="Completed",OR(P11="Feasible",P11="Feasible with verified support")),"Completed feasible",IF(OR(P11="Not feasible",W11="Stopped before rating",W11="Aborted during review"),"Infeasible or aborted","Incomplete"))) | AD11: =IF(COUNTA(A11:O11)+COUNTA(Q11)+COUNTA(T11:W11)+COUNTA(Y11:AC11)=0,"",IF(AND(COUNTIF(Vocabulary!$J$5:$J$6,L11)=1,COUNTIF(Vocabulary!$J$5:$J$6,M11)=1,COUNTIF(Vocabulary!$J$5:$J$6,N11)=1,COUNTIF(Vocabulary!$J$5:$J$6,Y11)=1,COUNTIF(Vocabulary!$J$5:$J$6,Z11)=1,COUNTIF(Vocabulary!$J$5:$J$6,AA11)=1,COUNTIF(Vocabulary!$J$5:$J$6,AB11)=1,COUNTIF(Vocabulary!$J$5:$J$6,AC11)=1),"OK","UNRECOGNISED_BURDEN_VALUE"))
P12: =IF(COUNTA(A12:O12)+COUNTA(Q12)+COUNTA(T12:W12)+COUNTA(Y12:AC12)=0,"",IF(OR(NOT(ISNUMBER(D12)),NOT(ISNUMBER(E12)),NOT(ISNUMBER(F12)),NOT(ISNUMBER(G12)),NOT(ISNUMBER(H12)),NOT(ISNUMBER(I12)),NOT(ISNUMBER(J12)),NOT(ISNUMBER(K12)),AD12<>"OK"),"Not feasible",IF(OR(D12<E12,F12<G12,H12<I12,J12<K12,AND(L12="Yes",OR(M12<>"Yes",N12<>"Yes")),AND(Y12="Yes",OR(Z12<>"Yes",AA12<>"Yes")),AB12<>"Yes",AC12<>"Yes"),"Not feasible",IF(OR(L12="Yes",Y12="Yes"),"Feasible with verified support","Feasible")))) | R12: =IF(AND(P12="",Q12=""),"",IF(AND(P12<>"",Q12=""),"UNRECORDED",IF(AND(P12="",Q12<>""),"ORPHAN_RECORDED",IF(P12=Q12,"MATCH","MISMATCH")))) | S12: =IF(OR(NOT(ISNUMBER(E12)),NOT(ISNUMBER(G12))),"",E12+G12) | X12: =IF(A12="","",IF(AND(W12="Completed",OR(P12="Feasible",P12="Feasible with verified support")),"Completed feasible",IF(OR(P12="Not feasible",W12="Stopped before rating",W12="Aborted during review"),"Infeasible or aborted","Incomplete"))) | AD12: =IF(COUNTA(A12:O12)+COUNTA(Q12)+COUNTA(T12:W12)+COUNTA(Y12:AC12)=0,"",IF(AND(COUNTIF(Vocabulary!$J$5:$J$6,L12)=1,COUNTIF(Vocabulary!$J$5:$J$6,M12)=1,COUNTIF(Vocabulary!$J$5:$J$6,N12)=1,COUNTIF(Vocabulary!$J$5:$J$6,Y12)=1,COUNTIF(Vocabulary!$J$5:$J$6,Z12)=1,COUNTIF(Vocabulary!$J$5:$J$6,AA12)=1,COUNTIF(Vocabulary!$J$5:$J$6,AB12)=1,COUNTIF(Vocabulary!$J$5:$J$6,AC12)=1),"OK","UNRECOGNISED_BURDEN_VALUE"))
P13: =IF(COUNTA(A13:O13)+COUNTA(Q13)+COUNTA(T13:W13)+COUNTA(Y13:AC13)=0,"",IF(OR(NOT(ISNUMBER(D13)),NOT(ISNUMBER(E13)),NOT(ISNUMBER(F13)),NOT(ISNUMBER(G13)),NOT(ISNUMBER(H13)),NOT(ISNUMBER(I13)),NOT(ISNUMBER(J13)),NOT(ISNUMBER(K13)),AD13<>"OK"),"Not feasible",IF(OR(D13<E13,F13<G13,H13<I13,J13<K13,AND(L13="Yes",OR(M13<>"Yes",N13<>"Yes")),AND(Y13="Yes",OR(Z13<>"Yes",AA13<>"Yes")),AB13<>"Yes",AC13<>"Yes"),"Not feasible",IF(OR(L13="Yes",Y13="Yes"),"Feasible with verified support","Feasible")))) | R13: =IF(AND(P13="",Q13=""),"",IF(AND(P13<>"",Q13=""),"UNRECORDED",IF(AND(P13="",Q13<>""),"ORPHAN_RECORDED",IF(P13=Q13,"MATCH","MISMATCH")))) | S13: =IF(OR(NOT(ISNUMBER(E13)),NOT(ISNUMBER(G13))),"",E13+G13) | X13: =IF(A13="","",IF(AND(W13="Completed",OR(P13="Feasible",P13="Feasible with verified support")),"Completed feasible",IF(OR(P13="Not feasible",W13="Stopped before rating",W13="Aborted during review"),"Infeasible or aborted","Incomplete"))) | AD13: =IF(COUNTA(A13:O13)+COUNTA(Q13)+COUNTA(T13:W13)+COUNTA(Y13:AC13)=0,"",IF(AND(COUNTIF(Vocabulary!$J$5:$J$6,L13)=1,COUNTIF(Vocabulary!$J$5:$J$6,M13)=1,COUNTIF(Vocabulary!$J$5:$J$6,N13)=1,COUNTIF(Vocabulary!$J$5:$J$6,Y13)=1,COUNTIF(Vocabulary!$J$5:$J$6,Z13)=1,COUNTIF(Vocabulary!$J$5:$J$6,AA13)=1,COUNTIF(Vocabulary!$J$5:$J$6,AB13)=1,COUNTIF(Vocabulary!$J$5:$J$6,AC13)=1),"OK","UNRECOGNISED_BURDEN_VALUE"))
P14: =IF(COUNTA(A14:O14)+COUNTA(Q14)+COUNTA(T14:W14)+COUNTA(Y14:AC14)=0,"",IF(OR(NOT(ISNUMBER(D14)),NOT(ISNUMBER(E14)),NOT(ISNUMBER(F14)),NOT(ISNUMBER(G14)),NOT(ISNUMBER(H14)),NOT(ISNUMBER(I14)),NOT(ISNUMBER(J14)),NOT(ISNUMBER(K14)),AD14<>"OK"),"Not feasible",IF(OR(D14<E14,F14<G14,H14<I14,J14<K14,AND(L14="Yes",OR(M14<>"Yes",N14<>"Yes")),AND(Y14="Yes",OR(Z14<>"Yes",AA14<>"Yes")),AB14<>"Yes",AC14<>"Yes"),"Not feasible",IF(OR(L14="Yes",Y14="Yes"),"Feasible with verified support","Feasible")))) | R14: =IF(AND(P14="",Q14=""),"",IF(AND(P14<>"",Q14=""),"UNRECORDED",IF(AND(P14="",Q14<>""),"ORPHAN_RECORDED",IF(P14=Q14,"MATCH","MISMATCH")))) | S14: =IF(OR(NOT(ISNUMBER(E14)),NOT(ISNUMBER(G14))),"",E14+G14) | X14: =IF(A14="","",IF(AND(W14="Completed",OR(P14="Feasible",P14="Feasible with verified support")),"Completed feasible",IF(OR(P14="Not feasible",W14="Stopped before rating",W14="Aborted during review"),"Infeasible or aborted","Incomplete"))) | AD14: =IF(COUNTA(A14:O14)+COUNTA(Q14)+COUNTA(T14:W14)+COUNTA(Y14:AC14)=0,"",IF(AND(COUNTIF(Vocabulary!$J$5:$J$6,L14)=1,COUNTIF(Vocabulary!$J$5:$J$6,M14)=1,COUNTIF(Vocabulary!$J$5:$J$6,N14)=1,COUNTIF(Vocabulary!$J$5:$J$6,Y14)=1,COUNTIF(Vocabulary!$J$5:$J$6,Z14)=1,COUNTIF(Vocabulary!$J$5:$J$6,AA14)=1,COUNTIF(Vocabulary!$J$5:$J$6,AB14)=1,COUNTIF(Vocabulary!$J$5:$J$6,AC14)=1),"OK","UNRECOGNISED_BURDEN_VALUE"))
P15: =IF(COUNTA(A15:O15)+COUNTA(Q15)+COUNTA(T15:W15)+COUNTA(Y15:AC15)=0,"",IF(OR(NOT(ISNUMBER(D15)),NOT(ISNUMBER(E15)),NOT(ISNUMBER(F15)),NOT(ISNUMBER(G15)),NOT(ISNUMBER(H15)),NOT(ISNUMBER(I15)),NOT(ISNUMBER(J15)),NOT(ISNUMBER(K15)),AD15<>"OK"),"Not feasible",IF(OR(D15<E15,F15<G15,H15<I15,J15<K15,AND(L15="Yes",OR(M15<>"Yes",N15<>"Yes")),AND(Y15="Yes",OR(Z15<>"Yes",AA15<>"Yes")),AB15<>"Yes",AC15<>"Yes"),"Not feasible",IF(OR(L15="Yes",Y15="Yes"),"Feasible with verified support","Feasible")))) | R15: =IF(AND(P15="",Q15=""),"",IF(AND(P15<>"",Q15=""),"UNRECORDED",IF(AND(P15="",Q15<>""),"ORPHAN_RECORDED",IF(P15=Q15,"MATCH","MISMATCH")))) | S15: =IF(OR(NOT(ISNUMBER(E15)),NOT(ISNUMBER(G15))),"",E15+G15) | X15: =IF(A15="","",IF(AND(W15="Completed",OR(P15="Feasible",P15="Feasible with verified support")),"Completed feasible",IF(OR(P15="Not feasible",W15="Stopped before rating",W15="Aborted during review"),"Infeasible or aborted","Incomplete"))) | AD15: =IF(COUNTA(A15:O15)+COUNTA(Q15)+COUNTA(T15:W15)+COUNTA(Y15:AC15)=0,"",IF(AND(COUNTIF(Vocabulary!$J$5:$J$6,L15)=1,COUNTIF(Vocabulary!$J$5:$J$6,M15)=1,COUNTIF(Vocabulary!$J$5:$J$6,N15)=1,COUNTIF(Vocabulary!$J$5:$J$6,Y15)=1,COUNTIF(Vocabulary!$J$5:$J$6,Z15)=1,COUNTIF(Vocabulary!$J$5:$J$6,AA15)=1,COUNTIF(Vocabulary!$J$5:$J$6,AB15)=1,COUNTIF(Vocabulary!$J$5:$J$6,AC15)=1),"OK","UNRECOGNISED_BURDEN_VALUE"))
P16: =IF(COUNTA(A16:O16)+COUNTA(Q16)+COUNTA(T16:W16)+COUNTA(Y16:AC16)=0,"",IF(OR(NOT(ISNUMBER(D16)),NOT(ISNUMBER(E16)),NOT(ISNUMBER(F16)),NOT(ISNUMBER(G16)),NOT(ISNUMBER(H16)),NOT(ISNUMBER(I16)),NOT(ISNUMBER(J16)),NOT(ISNUMBER(K16)),AD16<>"OK"),"Not feasible",IF(OR(D16<E16,F16<G16,H16<I16,J16<K16,AND(L16="Yes",OR(M16<>"Yes",N16<>"Yes")),AND(Y16="Yes",OR(Z16<>"Yes",AA16<>"Yes")),AB16<>"Yes",AC16<>"Yes"),"Not feasible",IF(OR(L16="Yes",Y16="Yes"),"Feasible with verified support","Feasible")))) | R16: =IF(AND(P16="",Q16=""),"",IF(AND(P16<>"",Q16=""),"UNRECORDED",IF(AND(P16="",Q16<>""),"ORPHAN_RECORDED",IF(P16=Q16,"MATCH","MISMATCH")))) | S16: =IF(OR(NOT(ISNUMBER(E16)),NOT(ISNUMBER(G16))),"",E16+G16) | X16: =IF(A16="","",IF(AND(W16="Completed",OR(P16="Feasible",P16="Feasible with verified support")),"Completed feasible",IF(OR(P16="Not feasible",W16="Stopped before rating",W16="Aborted during review"),"Infeasible or aborted","Incomplete"))) | AD16: =IF(COUNTA(A16:O16)+COUNTA(Q16)+COUNTA(T16:W16)+COUNTA(Y16:AC16)=0,"",IF(AND(COUNTIF(Vocabulary!$J$5:$J$6,L16)=1,COUNTIF(Vocabulary!$J$5:$J$6,M16)=1,COUNTIF(Vocabulary!$J$5:$J$6,N16)=1,COUNTIF(Vocabulary!$J$5:$J$6,Y16)=1,COUNTIF(Vocabulary!$J$5:$J$6,Z16)=1,COUNTIF(Vocabulary!$J$5:$J$6,AA16)=1,COUNTIF(Vocabulary!$J$5:$J$6,AB16)=1,COUNTIF(Vocabulary!$J$5:$J$6,AC16)=1),"OK","UNRECOGNISED_BURDEN_VALUE"))
P17: =IF(COUNTA(A17:O17)+COUNTA(Q17)+COUNTA(T17:W17)+COUNTA(Y17:AC17)=0,"",IF(OR(NOT(ISNUMBER(D17)),NOT(ISNUMBER(E17)),NOT(ISNUMBER(F17)),NOT(ISNUMBER(G17)),NOT(ISNUMBER(H17)),NOT(ISNUMBER(I17)),NOT(ISNUMBER(J17)),NOT(ISNUMBER(K17)),AD17<>"OK"),"Not feasible",IF(OR(D17<E17,F17<G17,H17<I17,J17<K17,AND(L17="Yes",OR(M17<>"Yes",N17<>"Yes")),AND(Y17="Yes",OR(Z17<>"Yes",AA17<>"Yes")),AB17<>"Yes",AC17<>"Yes"),"Not feasible",IF(OR(L17="Yes",Y17="Yes"),"Feasible with verified support","Feasible")))) | R17: =IF(AND(P17="",Q17=""),"",IF(AND(P17<>"",Q17=""),"UNRECORDED",IF(AND(P17="",Q17<>""),"ORPHAN_RECORDED",IF(P17=Q17,"MATCH","MISMATCH")))) | S17: =IF(OR(NOT(ISNUMBER(E17)),NOT(ISNUMBER(G17))),"",E17+G17) | X17: =IF(A17="","",IF(AND(W17="Completed",OR(P17="Feasible",P17="Feasible with verified support")),"Completed feasible",IF(OR(P17="Not feasible",W17="Stopped before rating",W17="Aborted during review"),"Infeasible or aborted","Incomplete"))) | AD17: =IF(COUNTA(A17:O17)+COUNTA(Q17)+COUNTA(T17:W17)+COUNTA(Y17:AC17)=0,"",IF(AND(COUNTIF(Vocabulary!$J$5:$J$6,L17)=1,COUNTIF(Vocabulary!$J$5:$J$6,M17)=1,COUNTIF(Vocabulary!$J$5:$J$6,N17)=1,COUNTIF(Vocabulary!$J$5:$J$6,Y17)=1,COUNTIF(Vocabulary!$J$5:$J$6,Z17)=1,COUNTIF(Vocabulary!$J$5:$J$6,AA17)=1,COUNTIF(Vocabulary!$J$5:$J$6,AB17)=1,COUNTIF(Vocabulary!$J$5:$J$6,AC17)=1),"OK","UNRECOGNISED_BURDEN_VALUE"))
... P250: =IF(COUNTA(A250:O250)+COUNTA(Q250)+COUNTA(T250:W250)+COUNTA(Y250:AC250)=0,"",IF(OR(NOT(ISNUMBER(D250)),NOT(ISNUMBER(E250)),NOT(ISNUMBER(F250)),NOT(ISNUMBER(G250)),NOT(ISNUMBER(H250)),NOT(ISNUMBER(I250)),NOT(ISNUMBER(J250)),NOT(ISNUMBER(K250)),AD250<>"OK"),"Not feasible",IF(OR(D250<E250,F250<G250,H250<I250,J250<K250,AND(L250="Yes",OR(M250<>"Yes",N250<>"Yes")),AND(Y250="Yes",OR(Z250<>"Yes",AA250<>"Yes")),AB250<>"Yes",AC250<>"Yes"),"Not feasible",IF(OR(L250="Yes",Y250="Yes"),"Feasible with verified support","Feasible")))) | R250: =IF(AND(P250="",Q250=""),"",IF(AND(P250<>"",Q250=""),"UNRECORDED",IF(AND(P250="",Q250<>""),"ORPHAN_RECORDED",IF(P250=Q250,"MATCH","MISMATCH")))) | S250: =IF(OR(NOT(ISNUMBER(E250)),NOT(ISNUMBER(G250))),"",E250+G250) | X250: =IF(A250="","",IF(AND(W250="Completed",OR(P250="Feasible",P250="Feasible with verified support")),"Completed feasible",IF(OR(P250="Not feasible",W250="Stopped before rating",W250="Aborted during review"),"Infeasible or aborted","Incomplete"))) | AD250: =IF(COUNTA(A250:O250)+COUNTA(Q250)+COUNTA(T250:W250)+COUNTA(Y250:AC250)=0,"",IF(AND(COUNTIF(Vocabulary!$J$5:$J$6,L250)=1,COUNTIF(Vocabulary!$J$5:$J$6,M250)=1,COUNTIF(Vocabulary!$J$5:$J$6,N250)=1,COUNTIF(Vocabulary!$J$5:$J$6,Y250)=1,COUNTIF(Vocabulary!$J$5:$J$6,Z250)=1,COUNTIF(Vocabulary!$J$5:$J$6,AA250)=1,COUNTIF(Vocabulary!$J$5:$J$6,AB250)=1,COUNTIF(Vocabulary!$J$5:$J$6,AC250)=1),"OK","UNRECOGNISED_BURDEN_VALUE"))

Sheet Decision_Value
A1: Decision Value and Downstream Effects - AF v6.2
A3: Record_ID | B3: Case_ID | C3: Comparator_Arm | D3: Baseline_Decision | E3: AF_Decision | F3: Decision_Changed | G3: Baseline_Confidence | H3: AF_Confidence | I3: Baseline_Time_Hours | J3: AF_Time_Hours | K3: Incremental_Time_Hours | L3: Defects_Discovered | M3: False_Clearances_Prevented | N3: False_Rejections_Created | O3: Uncertainty_Improved | P3: Affected_Party_Value_0_10 | Q3: Net_Value_Assessment | R3: Adverse_Effects | S3: Continuation_Decision | T3: Followup_Date
A4: DV-ILL-001 | B4: CASE-ILL-001 | C4: Domain standard of care | D4: Proceed to procurement | E4: Pause pending remedy evidence | F4: =IF(OR(D4="",E4=""),"",IF(D4=E4,"No","Yes")) | G4: 0.65 | H4: 0.78 | I4: 8 | J4: 31 | K4: =IF(OR(I4="",J4=""),"",J4-I4) | L4: 2 | M4: 1 | N4: 0 | O4: Yes | P4: 8 | Q4: Positive | S4: Retain | T4: 2027-02-11
A5: DV-ILL-002 | B5: CASE-ILL-NULL | C5: Structured checklist | D5: Request more evidence | E5: Request more evidence | F5: =IF(OR(D5="",E5=""),"",IF(D5=E5,"No","Yes")) | G5: 0.7 | H5: 0.7 | I5: 9 | J5: 24 | K5: =IF(OR(I5="",J5=""),"",J5-I5) | L5: 0 | M5: 0 | N5: 0 | O5: No | P5: 5 | Q5: Neutral | R5: Additional burden without decision change | S5: Revise | T5: 2027-02-11
A6: DV-ILL-003 | B6: CASE-ILL-ADVERSE | C6: Audit-theatre decoy | D6: Do not approve | E6: Conditional approval | F6: =IF(OR(D6="",E6=""),"",IF(D6=E6,"No","Yes")) | G6: 0.82 | H6: 0.76 | I6: 7 | J6: 29 | K6: =IF(OR(I6="",J6=""),"",J6-I6) | L6: 0 | M6: 0 | N6: 1 | O6: No | P6: 2 | Q6: Negative | R6: False clearance and increased documentation burden | S6: Restrict | T6: 2027-02-11
F7: =IF(OR(D7="",E7=""),"",IF(D7=E7,"No","Yes")) | K7: =IF(OR(I7="",J7=""),"",J7-I7)
F8: =IF(OR(D8="",E8=""),"",IF(D8=E8,"No","Yes")) | K8: =IF(OR(I8="",J8=""),"",J8-I8)
F9: =IF(OR(D9="",E9=""),"",IF(D9=E9,"No","Yes")) | K9: =IF(OR(I9="",J9=""),"",J9-I9)
F10: =IF(OR(D10="",E10=""),"",IF(D10=E10,"No","Yes")) | K10: =IF(OR(I10="",J10=""),"",J10-I10)
F11: =IF(OR(D11="",E11=""),"",IF(D11=E11,"No","Yes")) | K11: =IF(OR(I11="",J11=""),"",J11-I11)
F12: =IF(OR(D12="",E12=""),"",IF(D12=E12,"No","Yes")) | K12: =IF(OR(I12="",J12=""),"",J12-I12)
F13: =IF(OR(D13="",E13=""),"",IF(D13=E13,"No","Yes")) | K13: =IF(OR(I13="",J13=""),"",J13-I13)
F14: =IF(OR(D14="",E14=""),"",IF(D14=E14,"No","Yes")) | K14: =IF(OR(I14="",J14=""),"",J14-I14)
F15: =IF(OR(D15="",E15=""),"",IF(D15=E15,"No","Yes")) | K15: =IF(OR(I15="",J15=""),"",J15-I15)
F16: =IF(OR(D16="",E16=""),"",IF(D16=E16,"No","Yes")) | K16: =IF(OR(I16="",J16=""),"",J16-I16)
F17: =IF(OR(D17="",E17=""),"",IF(D17=E17,"No","Yes")) | K17: =IF(OR(I17="",J17=""),"",J17-I17)
F18: =IF(OR(D18="",E18=""),"",IF(D18=E18,"No","Yes")) | K18: =IF(OR(I18="",J18=""),"",J18-I18)
... F250: =IF(OR(D250="",E250=""),"",IF(D250=E250,"No","Yes")) | K250: =IF(OR(I250="",J250=""),"",J250-I250)

Sheet Reliability
A1: Independent Pre-Discussion Reliability Record - AF v6.2
A3: Study_ID | B3: Case_ID | C3: Criterion_or_Outcome | D3: Reviewer_A | E3: Reviewer_B | F3: Reviewer_A_Rating | G3: Reviewer_B_Rating | H3: Exact_Agreement | I3: Within_One_Category | J3: A_Confidence | K3: B_Confidence | L3: Discussion_Changed_A | M3: Discussion_Changed_B | N3: Final_Adjudicated | O3: Architecture_Family | P3: Language | Q3: Documentation_Intensity | R3: Notes | S3: Decision_Layer | T3: Rating_Deposit_A_ID | U3: Rating_Deposit_B_ID | V3: Criterion_Order_A | W3: Criterion_Order_B | X3: Global_Impression_A_Pre | Y3: Global_Impression_B_Pre | Z3: AI_Assistance_A | AA3: AI_Assistance_B | AB3: Independent_For_Reliability | AC3: Layer_Agreement_Eligible
A4: AF-EXT-ILL | B4: CASE-ILL-001 | C4: C0 | D4: R-01 | E4: R-02 | F4: 3 | G4: 3 | H4: =IF(OR(F4="",G4=""),"",IF(F4=G4,1,0)) | I4: =IF(OR(F4="",G4=""),"",IF(ABS(F4-G4)<=1,1,0)) | J4: High | K4: Moderate | L4: No | M4: No | N4: 3 | O4: legal-institutional | P4: English | Q4: High | R4: Illustrative | S4: Stage A criterion | T4: DEP-ILL-001 | U4: DEP-ILL-002 | V4: C3,C0,C5,C1,C4,C2 | W4: C2,C4,C1,C5,C0,C3 | X4: 3 | Y4: 3 | Z4: None | AA4: Retrieval/formatting only | AB4: Yes | AC4: =IF(A4="","",IF(AND(AB4="Yes",T4<>"",U4<>""),"Yes","No"))
A5: AF-EXT-ILL | B5: CASE-ILL-001 | C5: C1 | D5: R-01 | E5: R-02 | F5: 3 | G5: 2 | H5: =IF(OR(F5="",G5=""),"",IF(F5=G5,1,0)) | I5: =IF(OR(F5="",G5=""),"",IF(ABS(F5-G5)<=1,1,0)) | J5: High | K5: Moderate | L5: No | M5: Yes | N5: 3 | O5: legal-institutional | P5: English | Q5: High | R5: Illustrative | S5: Stage A criterion | T5: DEP-ILL-004 | U5: DEP-ILL-005 | V5: C3,C0,C5,C1,C4,C2 | W5: C2,C4,C1,C5,C0,C3 | X5: 3 | Y5: 2 | Z5: None | AA5: None | AB5: Yes | AC5: =IF(A5="","",IF(AND(AB5="Yes",T5<>"",U5<>""),"Yes","No"))
A6: AF-EXT-ILL | B6: CASE-ILL-001 | C6: Final Stage A | D6: R-01 | E6: R-02 | F6: 1 | G6: 1 | H6: =IF(OR(F6="",G6=""),"",IF(F6=G6,1,0)) | I6: =IF(OR(F6="",G6=""),"",IF(ABS(F6-G6)<=1,1,0)) | J6: High | K6: High | L6: No | M6: No | N6: 1 | O6: legal-institutional | P6: English | Q6: High | R6: Illustrative; numeric code is preregistered and final-layer only | S6: Stage A final | T6: DEP-ILL-006 | U6: DEP-ILL-007 | X6: 3 | Y6: 3 | Z6: None | AA6: None | AB6: Yes | AC6: =IF(A6="","",IF(AND(AB6="Yes",T6<>"",U6<>""),"Yes","No"))
A7: AF-EXT-ILL | B7: CASE-ILL-002 | C7: Rights robustness | D7: R-01 | E7: R-02 | F7: 2 | G7: 3 | H7: =IF(OR(F7="",G7=""),"",IF(F7=G7,1,0)) | I7: =IF(OR(F7="",G7=""),"",IF(ABS(F7-G7)<=1,1,0)) | J7: Moderate | K7: Moderate | L7: No | M7: No | N7: 2 | O7: technical | P7: English | Q7: Moderate | R7: Illustrative Stage B dimension | S7: Stage B dimension | T7: DEP-ILL-008 | U7: DEP-ILL-009 | V7: randomized | W7: randomized | X7: 2 | Y7: 3 | Z7: None | AA7: Material assistance generated draft rating - excluded from human reliability | AB7: No | AC7: =IF(A7="","",IF(AND(AB7="Yes",T7<>"",U7<>""),"Yes","No"))
H8: =IF(OR(F8="",G8=""),"",IF(F8=G8,1,0)) | I8: =IF(OR(F8="",G8=""),"",IF(ABS(F8-G8)<=1,1,0)) | AC8: =IF(A8="","",IF(AND(AB8="Yes",T8<>"",U8<>""),"Yes","No"))
H9: =IF(OR(F9="",G9=""),"",IF(F9=G9,1,0)) | I9: =IF(OR(F9="",G9=""),"",IF(ABS(F9-G9)<=1,1,0)) | AC9: =IF(A9="","",IF(AND(AB9="Yes",T9<>"",U9<>""),"Yes","No"))
H10: =IF(OR(F10="",G10=""),"",IF(F10=G10,1,0)) | I10: =IF(OR(F10="",G10=""),"",IF(ABS(F10-G10)<=1,1,0)) | AC10: =IF(A10="","",IF(AND(AB10="Yes",T10<>"",U10<>""),"Yes","No"))
H11: =IF(OR(F11="",G11=""),"",IF(F11=G11,1,0)) | I11: =IF(OR(F11="",G11=""),"",IF(ABS(F11-G11)<=1,1,0)) | AC11: =IF(A11="","",IF(AND(AB11="Yes",T11<>"",U11<>""),"Yes","No"))
H12: =IF(OR(F12="",G12=""),"",IF(F12=G12,1,0)) | I12: =IF(OR(F12="",G12=""),"",IF(ABS(F12-G12)<=1,1,0)) | AC12: =IF(A12="","",IF(AND(AB12="Yes",T12<>"",U12<>""),"Yes","No"))
H13: =IF(OR(F13="",G13=""),"",IF(F13=G13,1,0)) | I13: =IF(OR(F13="",G13=""),"",IF(ABS(F13-G13)<=1,1,0)) | AC13: =IF(A13="","",IF(AND(AB13="Yes",T13<>"",U13<>""),"Yes","No"))
H14: =IF(OR(F14="",G14=""),"",IF(F14=G14,1,0)) | I14: =IF(OR(F14="",G14=""),"",IF(ABS(F14-G14)<=1,1,0)) | AC14: =IF(A14="","",IF(AND(AB14="Yes",T14<>"",U14<>""),"Yes","No"))
H15: =IF(OR(F15="",G15=""),"",IF(F15=G15,1,0)) | I15: =IF(OR(F15="",G15=""),"",IF(ABS(F15-G15)<=1,1,0)) | AC15: =IF(A15="","",IF(AND(AB15="Yes",T15<>"",U15<>""),"Yes","No"))
H16: =IF(OR(F16="",G16=""),"",IF(F16=G16,1,0)) | I16: =IF(OR(F16="",G16=""),"",IF(ABS(F16-G16)<=1,1,0)) | AC16: =IF(A16="","",IF(AND(AB16="Yes",T16<>"",U16<>""),"Yes","No"))
H17: =IF(OR(F17="",G17=""),"",IF(F17=G17,1,0)) | I17: =IF(OR(F17="",G17=""),"",IF(ABS(F17-G17)<=1,1,0)) | AC17: =IF(A17="","",IF(AND(AB17="Yes",T17<>"",U17<>""),"Yes","No"))
H18: =IF(OR(F18="",G18=""),"",IF(F18=G18,1,0)) | I18: =IF(OR(F18="",G18=""),"",IF(ABS(F18-G18)<=1,1,0)) | AC18: =IF(A18="","",IF(AND(AB18="Yes",T18<>"",U18<>""),"Yes","No"))
H19: =IF(OR(F19="",G19=""),"",IF(F19=G19,1,0)) | I19: =IF(OR(F19="",G19=""),"",IF(ABS(F19-G19)<=1,1,0)) | AC19: =IF(A19="","",IF(AND(AB19="Yes",T19<>"",U19<>""),"Yes","No"))
... H250: =IF(OR(F250="",G250=""),"",IF(F250=G250,1,0)) | I250: =IF(OR(F250="",G250=""),"",IF(ABS(F250-G250)<=1,1,0)) | AC250: =IF(A250="","",IF(AND(AB250="Yes",T250<>"",U250<>""),"Yes","No"))

Sheet Dashboard
A1: AF v6.2 Pilot Dashboard - Descriptive Aggregation Only
A3: KPI | B3: Formula / value | C3: Interpretation | D3: Boundary | F3: Exception class | G3: Count
A4: Candidate records | B4: =COUNTIF(Candidate_Register!A4:A250,"<>") | C4: Count of registered candidate records | D4: Not a validation sample-size claim | F4: Stage A integrity | G4: =B7
A5: Incomplete or unrecognized profile routings | B5: =COUNTIF(Profile_Routing!M4:M250,"Undetermined - incomplete routing")+COUNTIF(Profile_Routing!M4:M250,"Undetermined - unrecognized routing value") | C5: Routing records requiring repair | D5: Cannot default downward to AF-Lite | F5: Invalid public strings | G5: =B14
A6: Stage A review records | B6: =COUNTIF(Stage_A!A4:A250,"<>") | C6: Count of review identifiers | D6: Does not establish reliability or validity | F6: Independence integrity | G6: =B15
A7: Stage A status-integrity exceptions | B7: =COUNTIF(Stage_A!S4:S250,"MISMATCH")+COUNTIF(Stage_A!S4:S250,"UNRECORDED")+COUNTIF(Stage_A!S4:S250,"ORPHAN_RECORDED") | C7: Derived/recorded reconciliation failures | D7: Resolve before reporting | F7: Unknown independence controls | G7: =B16
A8: Derived Stage-A admissible | B8: =COUNTIF(Stage_A!Q4:Q250,"Stage-A admissible - scoped")+COUNTIF(Stage_A!Q4:Q250,"Stage-A admissible - scoped, control-dependent") | C8: Both bounded admissibility outcomes | D8: Not certification or authorization | F8: Burden infeasible | G8: =B18
A9: Control-dependent admissible | B9: =COUNTIF(Stage_A!Q4:Q250,"Stage-A admissible - scoped, control-dependent") | C9: Admissible only while named controls hold | D9: Must preserve conditions, expiry and requalification | F9: Invalid reliability records | G9: =B26
A10: Non-admissible - patchable | B10: =COUNTIF(Stage_A!Q4:Q250,"Stage-A non-admissible - patchable") | C10: Material patchable defects | D10: Not global invalidity | F10: Capacity overflow | G10: =B35
A11: Non-admissible - unpatchable | B11: =COUNTIF(Stage_A!Q4:Q250,"Stage-A non-admissible - unpatchable for stated claim") | C11: Claim/scope cannot survive established defect | D11: Requires a new review object
A12: Indeterminate or protocol refusal | B12: =COUNTIF(Stage_A!Q4:Q250,"Indeterminate - insufficient evidence")+COUNTIF(Stage_A!Q4:Q250,"Protocol refusal to evaluate") | C12: Evidence or administration limitation | D12: Must not be converted to pass or failure
A13: Administrative Stage A dispositions | B13: =COUNTIF(Stage_A!Q4:Q250,"Out of scope")+COUNTIF(Stage_A!Q4:Q250,"Withdrawn")+COUNTIF(Stage_A!Q4:Q250,"Not reviewed") | C13: Non-substantive dispositions | D13: No conformity inference
A14: Invalid public status strings | B14: =COUNTIF(Stage_A!AG4:AG250,"INVALID_OR_INCOMPLETE") | C14: Token/version/CL-basis boundary failed | D14: Public export prohibited
A15: Independence reconciliation exceptions | B15: =COUNTIF(Independence!P4:P250,"MISMATCH")+COUNTIF(Independence!P4:P250,"UNRECORDED")+COUNTIF(Independence!P4:P250,"ORPHAN_RECORDED") | C15: Derived/recorded independence drift | D15: Resolve before any independence claim
A16: Unrecognized independence controls | B16: =COUNTIF(Independence!X4:X250,"UNRECOGNISED_CONTROL_VALUE") | C16: Vocabulary violation in control fields | D16: Routes to Indeterminate
A17: Independence inadequate or indeterminate | B17: =COUNTIF(Independence!O4:O250,"Inadequate")+COUNTIF(Independence!O4:O250,"Indeterminate") | C17: Capture, protection or evidence limitation | D17: Cannot support an independence claim
A18: Burden not feasible | B18: =COUNTIF(Burden_Log!P4:P250,"Not feasible") | C18: Conjunctive capacity/access/translation/custody/governance gate failed | D18: No false-green override
A19: Mean burden - completed feasible | B19: =IFERROR(SUMIF(Burden_Log!X4:X250,"Completed feasible",Burden_Log!V4:V250)/COUNTIF(Burden_Log!X4:X250,"Completed feasible"),"") | C19: Average 0-10 among completed-feasible cases | D19: Do not blend with stopped or infeasible cases
A20: Mean burden - infeasible or aborted | B20: =IFERROR(SUMIF(Burden_Log!X4:X250,"Infeasible or aborted",Burden_Log!V4:V250)/COUNTIF(Burden_Log!X4:X250,"Infeasible or aborted"),"") | C20: Average 0-10 among infeasible/aborted attempts | D20: May reveal protocol burden harm
A21: Stage A criterion exact agreement - raw | B21: =IFERROR(SUMIFS(Reliability!H4:H250,Reliability!S4:S250,"Stage A criterion",Reliability!AC4:AC250,"Yes")/COUNTIFS(Reliability!S4:S250,"Stage A criterion",Reliability!AC4:AC250,"Yes"),"") | C21: Descriptive raw agreement only | D21: Never blend with final or Stage B layers
A22: Stage A final exact agreement - raw | B22: =IFERROR(SUMIFS(Reliability!H4:H250,Reliability!S4:S250,"Stage A final",Reliability!AC4:AC250,"Yes")/COUNTIFS(Reliability!S4:S250,"Stage A final",Reliability!AC4:AC250,"Yes"),"") | C22: Descriptive raw agreement only | D22: Not a reliability coefficient
A23: Stage B dimension exact agreement - raw | B23: =IFERROR(SUMIFS(Reliability!H4:H250,Reliability!S4:S250,"Stage B dimension",Reliability!AC4:AC250,"Yes")/COUNTIFS(Reliability!S4:S250,"Stage B dimension",Reliability!AC4:AC250,"Yes"),"") | C23: Report by dimension in analysis | D23: No mixed-layer average
A24: Stage B final exact agreement - raw | B24: =IFERROR(SUMIFS(Reliability!H4:H250,Reliability!S4:S250,"Stage B final",Reliability!AC4:AC250,"Yes")/COUNTIFS(Reliability!S4:S250,"Stage B final",Reliability!AC4:AC250,"Yes"),"") | C24: Final relation only | D24: No mixing with ordinal dimensions
A25: Imported external reliability results | B25: =COUNTIF(Reliability_Results!A5:A250,"<>")-COUNTIF(Reliability_Results!A5:A250,"RESULT-TEMPLATE") | C25: Versioned coefficient/interval records | D25: Count is not evidence of adequacy
A26: Invalid external reliability records | B26: =COUNTIF(Reliability_Results!R5:R250,"INVALID_OR_INCOMPLETE") | C26: Invalid interval or incomplete provenance | D26: Adverse coefficients remain recordable
A27: Positive decision-value assessments | B27: =COUNTIF(Decision_Value!Q4:Q250,"Positive") | C27: Positive net assessment count | D27: Must be accompanied by null and adverse counts
A28: Neutral or negative decision-value assessments | B28: =COUNTIF(Decision_Value!Q4:Q250,"Neutral")+COUNTIF(Decision_Value!Q4:Q250,"Negative") | C28: Null/adverse assessments | D28: First-class results
A29: Rejected or non-immutable deposits | B29: =COUNTIF(Rating_Deposits!M5:M250,"No")+COUNTIF(Rating_Deposits!P5:P250,"Rejected") | C29: Deposit-integrity exceptions | D29: Excluded from independence-based reliability
A30: Perturbations proposed | B30: =COUNTIF(Perturbation_Register!A5:A250,"<>") | C30: All populated proposals | D30: Proposals do not enter replay automatically
A31: Perturbations admitted | B31: =COUNTIF(Perturbation_Register!O5:O250,"Admitted") | C31: Evidence-supported admitted alternatives | D31: Admission tests supportability, not correctness
A32: Perturbations rejected | B32: =COUNTIF(Perturbation_Register!O5:O250,"Rejected") | C32: Rejected with reasons and appeal status | D32: Cannot suppress supported dissent
A33: Reversal-capable admissions | B33: =COUNTIFS(Perturbation_Register!O5:O250,"Admitted",Perturbation_Register!R5:R250,"Yes") | C33: Admitted alternatives capable of changing relation | D33: Report with base and perturbed relation
A34: Study-readiness mismatches | B34: =COUNTIF(Study_Readiness!G4:G250,"MISMATCH") | C34: Derived and recorded readiness differ | D34: Resolve before readiness claim
A35: Rows beyond configured capacity | B35: =COUNTIF(Profile_Routing!A251:A1000,"<>")+COUNTIF(Candidate_Register!A251:A1000,"<>")+COUNTIF(Stage_A!A251:A1000,"<>")+COUNTIF(Independence!A251:A1000,"<>")+COUNTIF(Burden_Log!A251:A1000,"<>")+COUNTIF(Decision_Value!A251:A1000,"<>")+COUNTIF(Reliability!A251:A1000,"<>")+COUNTIF(Perturbation_Register!A251:A1000,"<>") | C35: Records entered outside configured tables | D35: Move into configured rows before analysis
A37: Dashboard boundary: descriptive aggregates do not establish immutable deposits, inter-reviewer reliability, construct validity, constitutional legitimacy, legal conformity, community legitimacy, due diligence, foreseeability, certification, procurement defensibility or deployment authorization.

Sheet Scenario_Register
A1: Frozen Scenario-Set Register - AF v6.2
A3: Scenario_Set_ID | B3: Set_Version | C3: Scenario_ID | D3: Domain | E3: Declared_Function | F3: Intended_Difficulty | G3: Architecture_Equivalence_Criteria | H3: Calibration_Status | I3: Calibration_Evidence_Refs | J3: Content_SHA256 | K3: Retired | L3: Retirement_Reason | M3: Frozen_At_UTC
A4: SCENSET-ILL-001 | B4: 1.0.0 | C4: SCEN-ILL-001 | D4: Public benefits | E4: Test missing-evidence refusal and appeal | F4: Moderate | G4: Same decision stakes, evidence maturity, time budget, and available remedy routes across architecture families | H4: Synthetic calibration only | I4: CAL-ILL-001 | J4: illustrative-sha256-not-for-production | K4: No | M4: 46245
A5: SCENSET-ILL-001 | B5: 1.0.0 | C5: SCEN-ILL-002 | D5: Procurement | E5: Test audit-theatre susceptibility | F5: High | G5: Equivalent documentary volume but different causal control quality | H5: Synthetic calibration only | I5: CAL-ILL-002 | J5: illustrative-sha256-not-for-production | K5: No | M5: 46245

Sheet Rating_Deposits
A1: Immutable Pre-Discussion Rating Deposit Import - AF v6.2
A2: Boundary: this sheet imports metadata from an independently controlled system with an audit trail. Entry into this workbook alone does not establish immutability, timestamp priority, reviewer independence, or absence of post-discussion editing.
A4: Deposit_ID | B4: Study_ID | C4: Case_ID | D4: Reviewer_ID | E4: Decision_Layer | F4: Target_ID | G4: Rating_Value | H4: Confidence | I4: Submitted_At_UTC | J4: Content_SHA256 | K4: Signature_or_Audit_Proof | L4: Repository_or_System | M4: Immutable_Before_Discussion | N4: Supersedes_Deposit_ID | O4: AI_Assistance_Disclosure | P4: Deposit_Status
A5: DEP-ILL-001 | B5: AF-EXT-ILL | C5: CASE-ILL-001 | D5: R-01 | E5: Stage A criterion | F5: C0 | G5: 3 | H5: High | I5: '2026-08-11T08:00:00Z | J5: illustrative-sha256-001 | K5: illustrative signed commit | L5: Independent host repository | M5: Yes | O5: None | P5: Illustrative
A6: DEP-ILL-002 | B6: AF-EXT-ILL | C6: CASE-ILL-001 | D6: R-02 | E6: Stage A criterion | F6: C0 | G6: 3 | H6: Moderate | I6: '2026-08-11T08:01:00Z | J6: illustrative-sha256-002 | K6: illustrative REDCap audit event | L6: Independent REDCap project | M6: Yes | O6: Retrieval/formatting only | P6: Illustrative
A7: DEP-ILL-003 | B7: AF-EXT-ILL | C7: CASE-ILL-001 | D7: R-03 | E7: Stage A final | F7: final_stage_a | G7: 1 | H7: High | I7: '2026-08-11T08:02:00Z | J7: illustrative-sha256-003 | K7: missing production proof | L7: Shared spreadsheet only | M7: No | O7: Material assistance generated draft rating - excluded from human reliability | P7: Rejected example

Sheet Codebook
A1: AF v6.2 Canonical Tokens and Workbook Semantics
A3: Domain | B3: Human-readable value | C3: Canonical token | D3: Blank-row rule | E3: Meaning boundary
A4: Configuration | B4: Protocol version | C4: AF v6.2 | D4: Never hard-code in formulas | E4: Vocabulary!B5 controls
A5: Configuration | B5: Constitutional legitimacy basis | C5: CL1 self-assessment; CL2 design materials only | D5: Must accompany public Stage A strings | E5: Does not establish plural constitutional legitimacy
A6: Stage A public | B6: Stage-A admissible - scoped | C6: stage_a_admissible_scoped | D6: Blank if no review | E6: Eligibility only; not certification, due diligence or authorization
A7: Stage A public | B7: Stage-A admissible - scoped, control-dependent | C7: stage_a_admissible_scoped_control_dependent | D7: Blank if no review | E7: Depends on named, monitored, expiring and requalified controls
A8: Migration alias | B8: deprecated v5.8 controlled status | C8: stage_a_admissible_scoped_with_verified_controls | D8: Never generated by v6.1 | E8: Preserve source record and add migration provenance
A9: Stage A public | B9: Stage-A non-admissible - patchable | C9: stage_a_non_admissible_patchable | D9: Blank if no review | E9: Material patchable defect
A10: Stage A public | B10: Stage-A non-admissible - unpatchable for stated claim | C10: stage_a_non_admissible_unpatchable_for_stated_claim | D10: Blank if no review | E10: Stated claim cannot survive defect
A11: Stage A public | B11: Indeterminate - insufficient evidence | C11: indeterminate_insufficient_evidence | D11: Blank if no review | E11: No warranted positive or negative conclusion
A12: Stage A public | B12: Protocol refusal to evaluate | C12: protocol_refusal_to_evaluate | D12: Partial or invalid rows fail closed | E12: Administration, authority, burden or vocabulary failure
A13: Stage A public | B13: Out of scope | C13: out_of_scope | D13: Derived from administrative disposition | E13: No protocol judgment
A14: Stage A public | B14: Withdrawn | C14: withdrawn | D14: Derived from administrative disposition | E14: No conformity inference
... A28: Floor tier | B28: Not ordinarily floor-linked | C28: N | D28: Comparative unless new defect emerges | E28: No automatic Stage A re-entry

Sheet Reliability_Results
A1: Externally Computed Reliability Results - AF v6.2
A2: Import only results produced from eligible immutable pre-discussion deposits under a versioned analysis script. Negative coefficients and confidence bounds are valid adverse results. The workbook validates the record but does not compute the coefficient.
A4: Result_ID | B4: Study_ID | C4: Decision_Layer | D4: Target_ID | E4: Coefficient | F4: Weighting | G4: Estimate | H4: CI_Lower | I4: CI_Upper | J4: Confidence_Level_Proportion | K4: Bootstrap_Replicates | L4: Eligible_Deposits | M4: Excluded_Deposits | N4: Analysis_Script_SHA256 | O4: Software_and_Version | P4: Generated_At_UTC | Q4: Interval_Check | R4: Result_Record_Check
A5: RESULT-TEMPLATE | C5: Stage A criterion | D5: C0 | E5: Gwet AC1 | F5: Unweighted | J5: 0.95 | Q5: =IF(OR(A5="",A5="RESULT-TEMPLATE"),"",IF(AND(ISNUMBER(G5),ISNUMBER(H5),ISNUMBER(I5),H5<=G5,G5<=I5),"VALID","INVALID_INTERVAL")) | R5: =IF(OR(A5="",A5="RESULT-TEMPLATE"),"",IF(AND(C5<>"",E5<>"",F5<>"",J5<>"",N5<>"",O5<>"",P5<>"",Q5="VALID"),"VALID","INVALID_OR_INCOMPLETE"))
Q6: =IF(OR(A6="",A6="RESULT-TEMPLATE"),"",IF(AND(ISNUMBER(G6),ISNUMBER(H6),ISNUMBER(I6),H6<=G6,G6<=I6),"VALID","INVALID_INTERVAL")) | R6: =IF(OR(A6="",A6="RESULT-TEMPLATE"),"",IF(AND(C6<>"",E6<>"",F6<>"",J6<>"",N6<>"",O6<>"",P6<>"",Q6="VALID"),"VALID","INVALID_OR_INCOMPLETE"))
Q7: =IF(OR(A7="",A7="RESULT-TEMPLATE"),"",IF(AND(ISNUMBER(G7),ISNUMBER(H7),ISNUMBER(I7),H7<=G7,G7<=I7),"VALID","INVALID_INTERVAL")) | R7: =IF(OR(A7="",A7="RESULT-TEMPLATE"),"",IF(AND(C7<>"",E7<>"",F7<>"",J7<>"",N7<>"",O7<>"",P7<>"",Q7="VALID"),"VALID","INVALID_OR_INCOMPLETE"))
Q8: =IF(OR(A8="",A8="RESULT-TEMPLATE"),"",IF(AND(ISNUMBER(G8),ISNUMBER(H8),ISNUMBER(I8),H8<=G8,G8<=I8),"VALID","INVALID_INTERVAL")) | R8: =IF(OR(A8="",A8="RESULT-TEMPLATE"),"",IF(AND(C8<>"",E8<>"",F8<>"",J8<>"",N8<>"",O8<>"",P8<>"",Q8="VALID"),"VALID","INVALID_OR_INCOMPLETE"))
Q9: =IF(OR(A9="",A9="RESULT-TEMPLATE"),"",IF(AND(ISNUMBER(G9),ISNUMBER(H9),ISNUMBER(I9),H9<=G9,G9<=I9),"VALID","INVALID_INTERVAL")) | R9: =IF(OR(A9="",A9="RESULT-TEMPLATE"),"",IF(AND(C9<>"",E9<>"",F9<>"",J9<>"",N9<>"",O9<>"",P9<>"",Q9="VALID"),"VALID","INVALID_OR_INCOMPLETE"))
Q10: =IF(OR(A10="",A10="RESULT-TEMPLATE"),"",IF(AND(ISNUMBER(G10),ISNUMBER(H10),ISNUMBER(I10),H10<=G10,G10<=I10),"VALID","INVALID_INTERVAL")) | R10: =IF(OR(A10="",A10="RESULT-TEMPLATE"),"",IF(AND(C10<>"",E10<>"",F10<>"",J10<>"",N10<>"",O10<>"",P10<>"",Q10="VALID"),"VALID","INVALID_OR_INCOMPLETE"))
Q11: =IF(OR(A11="",A11="RESULT-TEMPLATE"),"",IF(AND(ISNUMBER(G11),ISNUMBER(H11),ISNUMBER(I11),H11<=G11,G11<=I11),"VALID","INVALID_INTERVAL")) | R11: =IF(OR(A11="",A11="RESULT-TEMPLATE"),"",IF(AND(C11<>"",E11<>"",F11<>"",J11<>"",N11<>"",O11<>"",P11<>"",Q11="VALID"),"VALID","INVALID_OR_INCOMPLETE"))
Q12: =IF(OR(A12="",A12="RESULT-TEMPLATE"),"",IF(AND(ISNUMBER(G12),ISNUMBER(H12),ISNUMBER(I12),H12<=G12,G12<=I12),"VALID","INVALID_INTERVAL")) | R12: =IF(OR(A12="",A12="RESULT-TEMPLATE"),"",IF(AND(C12<>"",E12<>"",F12<>"",J12<>"",N12<>"",O12<>"",P12<>"",Q12="VALID"),"VALID","INVALID_OR_INCOMPLETE"))
Q13: =IF(OR(A13="",A13="RESULT-TEMPLATE"),"",IF(AND(ISNUMBER(G13),ISNUMBER(H13),ISNUMBER(I13),H13<=G13,G13<=I13),"VALID","INVALID_INTERVAL")) | R13: =IF(OR(A13="",A13="RESULT-TEMPLATE"),"",IF(AND(C13<>"",E13<>"",F13<>"",J13<>"",N13<>"",O13<>"",P13<>"",Q13="VALID"),"VALID","INVALID_OR_INCOMPLETE"))
Q14: =IF(OR(A14="",A14="RESULT-TEMPLATE"),"",IF(AND(ISNUMBER(G14),ISNUMBER(H14),ISNUMBER(I14),H14<=G14,G14<=I14),"VALID","INVALID_INTERVAL")) | R14: =IF(OR(A14="",A14="RESULT-TEMPLATE"),"",IF(AND(C14<>"",E14<>"",F14<>"",J14<>"",N14<>"",O14<>"",P14<>"",Q14="VALID"),"VALID","INVALID_OR_INCOMPLETE"))
Q15: =IF(OR(A15="",A15="RESULT-TEMPLATE"),"",IF(AND(ISNUMBER(G15),ISNUMBER(H15),ISNUMBER(I15),H15<=G15,G15<=I15),"VALID","INVALID_INTERVAL")) | R15: =IF(OR(A15="",A15="RESULT-TEMPLATE"),"",IF(AND(C15<>"",E15<>"",F15<>"",J15<>"",N15<>"",O15<>"",P15<>"",Q15="VALID"),"VALID","INVALID_OR_INCOMPLETE"))
Q16: =IF(OR(A16="",A16="RESULT-TEMPLATE"),"",IF(AND(ISNUMBER(G16),ISNUMBER(H16),ISNUMBER(I16),H16<=G16,G16<=I16),"VALID","INVALID_INTERVAL")) | R16: =IF(OR(A16="",A16="RESULT-TEMPLATE"),"",IF(AND(C16<>"",E16<>"",F16<>"",J16<>"",N16<>"",O16<>"",P16<>"",Q16="VALID"),"VALID","INVALID_OR_INCOMPLETE"))
Q17: =IF(OR(A17="",A17="RESULT-TEMPLATE"),"",IF(AND(ISNUMBER(G17),ISNUMBER(H17),ISNUMBER(I17),H17<=G17,G17<=I17),"VALID","INVALID_INTERVAL")) | R17: =IF(OR(A17="",A17="RESULT-TEMPLATE"),"",IF(AND(C17<>"",E17<>"",F17<>"",J17<>"",N17<>"",O17<>"",P17<>"",Q17="VALID"),"VALID","INVALID_OR_INCOMPLETE"))
... Q250: =IF(OR(A250="",A250="RESULT-TEMPLATE"),"",IF(AND(ISNUMBER(G250),ISNUMBER(H250),ISNUMBER(I250),H250<=G250,G250<=I250),"VALID","INVALID_INTERVAL")) | R250: =IF(OR(A250="",A250="RESULT-TEMPLATE"),"",IF(AND(C250<>"",E250<>"",F250<>"",J250<>"",N250<>"",O250<>"",P250<>"",Q250="VALID"),"VALID","INVALID_OR_INCOMPLETE"))

Sheet Study_Readiness
A1: AF v6.2 Study Readiness and Material-Construction Gate
A3: Tier | B3: Minimum_Required_Objects | C3: Current_AF_v6_2_State | D3: Evidence_Refs | E3: Derived_Status | F3: Recorded_Status | G3: Status_Match
A4: Design-ready | B4: Protocol; templates; scenario governance; training, analysis, burden and publication specifications | C4: Present | D4: AF v6.2 package | E4: =IF(A4="","",IF(C4="Present","Ready","Not ready")) | F4: Ready | G4: =IF(OR(E4="",F4=""),"",IF(E4=F4,"MATCH","MISMATCH"))
A5: Materials-ready | B5: Frozen 20-case library; hashes; practice bank; qualification rubric; deposit system; scripts; capacity plan | C5: Not constituted | E5: =IF(A5="","",IF(C5="Present","Ready","Not ready")) | F5: Not ready | G5: =IF(OR(E5="",F5=""),"",IF(E5=F5,"MATCH","MISMATCH"))
A6: Shadow-ready | B6: Independent host; qualified reviewers; conflicts; custody; deposits; appeal; unconditional publication | C6: Not constituted | E6: =IF(A6="","",IF(C6="Present","Ready","Not ready")) | F6: Not ready | G6: =IF(OR(E6="",F6=""),"",IF(E6=F6,"MATCH","MISMATCH"))
A7: Pilot-ready | B7: Live-scope legal/ethical/affected-party review; protected reporting; adverse-event plan; remedies; funded stopping rules | C7: Not constituted | E7: =IF(A7="","",IF(C7="Present","Ready","Not ready")) | F7: Not ready | G7: =IF(OR(E7="",F7=""),"",IF(E7=F7,"MATCH","MISMATCH"))
A8: Replication-ready | B8: Frozen post-pilot package; second-host plan; transport verification | C8: Not applicable before pilot | E8: =IF(A8="","",IF(C8="Present","Ready","Not ready")) | F8: Not ready | G8: =IF(OR(E8="",F8=""),"",IF(E8=F8,"MATCH","MISMATCH"))
E9: =IF(A9="","",IF(C9="Present","Ready","Not ready")) | G9: =IF(OR(E9="",F9=""),"",IF(E9=F9,"MATCH","MISMATCH"))
E10: =IF(A10="","",IF(C10="Present","Ready","Not ready")) | G10: =IF(OR(E10="",F10=""),"",IF(E10=F10,"MATCH","MISMATCH"))
E11: =IF(A11="","",IF(C11="Present","Ready","Not ready")) | G11: =IF(OR(E11="",F11=""),"",IF(E11=F11,"MATCH","MISMATCH"))
E12: =IF(A12="","",IF(C12="Present","Ready","Not ready")) | G12: =IF(OR(E12="",F12=""),"",IF(E12=F12,"MATCH","MISMATCH"))
E13: =IF(A13="","",IF(C13="Present","Ready","Not ready")) | G13: =IF(OR(E13="",F13=""),"",IF(E13=F13,"MATCH","MISMATCH"))
E14: =IF(A14="","",IF(C14="Present","Ready","Not ready")) | G14: =IF(OR(E14="",F14=""),"",IF(E14=F14,"MATCH","MISMATCH"))
E15: =IF(A15="","",IF(C15="Present","Ready","Not ready")) | G15: =IF(OR(E15="",F15=""),"",IF(E15=F15,"MATCH","MISMATCH"))
E16: =IF(A16="","",IF(C16="Present","Ready","Not ready")) | G16: =IF(OR(E16="",F16=""),"",IF(E16=F16,"MATCH","MISMATCH"))
E17: =IF(A17="","",IF(C17="Present","Ready","Not ready")) | G17: =IF(OR(E17="",F17=""),"",IF(E17=F17,"MATCH","MISMATCH"))
E18: =IF(A18="","",IF(C18="Present","Ready","Not ready")) | G18: =IF(OR(E18="",F18=""),"",IF(E18=F18,"MATCH","MISMATCH"))
E19: =IF(A19="","",IF(C19="Present","Ready","Not ready")) | G19: =IF(OR(E19="",F19=""),"",IF(E19=F19,"MATCH","MISMATCH"))
E20: =IF(A20="","",IF(C20="Present","Ready","Not ready")) | G20: =IF(OR(E20="",F20=""),"",IF(E20=F20,"MATCH","MISMATCH"))
... E250: =IF(A250="","",IF(C250="Present","Ready","Not ready")) | G250: =IF(OR(E250="",F250=""),"",IF(E250=F250,"MATCH","MISMATCH"))

Sheet Perturbation_Register
A1: AF v6.2 Perturbation Proposal, Admission, and Replay Register
A2: A proposal is not self-executing. Only admitted alternatives enter the relation set. Admission requires evidence plus second independent reviewer concurrence or a non-proposing independent adjudicator.
A4: Proposal_ID | B4: Study_ID | C4: Comparison_ID | D4: Candidate_ID | E4: Dimension | F4: Recorded_Category | G4: Proposed_Category | H4: Anchor_Conflict | I4: Evidence_Ref | J4: Material_To_Relation | K4: Proposer_ID | L4: Proposed_At_UTC | M4: Second_Reviewer_ID | N4: Adjudicator_ID | O4: Admission_Status | P4: Admission_Reason | Q4: Dependence_Group_ID | R4: Reversal_Capable | S4: Base_Relation | T4: Perturbed_Relation | U4: Relation_Changed | V4: Appeal_Status | W4: Final_Record_Status | X4: Duplicate_or_Strategic_Flag | Y4: C2_D05_Status
A5: P-ILL-001 | B5: AF-P0-ILL | C5: CMP-ILL-001 | D5: CAND-E | E5: Audit completeness | F5: 4 | G5: 3 | H5: Narrower interpretation of replay evidence | I5: EVID-ILL-101 | J5: Yes | K5: R-01 | L5: '2026-08-12T08:00:00Z | M5: R-03 | O5: Admitted | P5: Second reviewer confirms anchor tension | R5: No | S5: A dominates B | T5: A dominates B | U5: =IF(OR(S5="",T5=""),"",IF(S5=T5,"No","Yes")) | V5: Not appealed | W5: Illustrative | X5: No | Y5: =IF(A5="","",IF(AND(O5="Rejected",X5="Yes"),"Potential unsupported-perturbation inflation",IF(AND(O5="Admitted",OR(M5<>"",N5<>"")),"No unsupported-perturbation defect indicated","Admission integrity incomplete")))
A6: P-ILL-002 | B6: AF-P0-ILL | C6: CMP-ILL-001 | D6: CAND-F | E6: Ecological adequacy | F6: 3 | G6: 4 | H6: Additional verified horizon evidence | I6: EVID-ILL-102 | J6: Yes | K6: R-02 | L6: '2026-08-12T08:05:00Z | N6: ADJ-01 | O6: Admitted | P6: Independent adjudicator finds proposal evidence-supported | R6: Yes | S6: A dominates B | T6: Crossing | U6: =IF(OR(S6="",T6=""),"",IF(S6=T6,"No","Yes")) | V6: Not appealed | W6: Illustrative | X6: No | Y6: =IF(A6="","",IF(AND(O6="Rejected",X6="Yes"),"Potential unsupported-perturbation inflation",IF(AND(O6="Admitted",OR(M6<>"",N6<>"")),"No unsupported-perturbation defect indicated","Admission integrity incomplete")))
A7: P-ILL-003 | B7: AF-P0-ILL | C7: CMP-ILL-001 | D7: CAND-F | E7: Ecological adequacy | F7: 3 | G7: 4 | H7: Duplicate of P-ILL-002 | I7: EVID-ILL-102 | J7: Yes | K7: R-04 | L7: '2026-08-12T08:06:00Z | N7: ADJ-01 | O7: Rejected | P7: Duplicate causal proposal | Q7: DG-ILL-01 | R7: Yes | S7: A dominates B | U7: =IF(OR(S7="",T7=""),"",IF(S7=T7,"No","Yes")) | V7: Not appealed | W7: Illustrative | X7: Yes | Y7: =IF(A7="","",IF(AND(O7="Rejected",X7="Yes"),"Potential unsupported-perturbation inflation",IF(AND(O7="Admitted",OR(M7<>"",N7<>"")),"No unsupported-perturbation defect indicated","Admission integrity incomplete")))
U8: =IF(OR(S8="",T8=""),"",IF(S8=T8,"No","Yes")) | Y8: =IF(A8="","",IF(AND(O8="Rejected",X8="Yes"),"Potential unsupported-perturbation inflation",IF(AND(O8="Admitted",OR(M8<>"",N8<>"")),"No unsupported-perturbation defect indicated","Admission integrity incomplete")))
U9: =IF(OR(S9="",T9=""),"",IF(S9=T9,"No","Yes")) | Y9: =IF(A9="","",IF(AND(O9="Rejected",X9="Yes"),"Potential unsupported-perturbation inflation",IF(AND(O9="Admitted",OR(M9<>"",N9<>"")),"No unsupported-perturbation defect indicated","Admission integrity incomplete")))
U10: =IF(OR(S10="",T10=""),"",IF(S10=T10,"No","Yes")) | Y10: =IF(A10="","",IF(AND(O10="Rejected",X10="Yes"),"Potential unsupported-perturbation inflation",IF(AND(O10="Admitted",OR(M10<>"",N10<>"")),"No unsupported-perturbation defect indicated","Admission integrity incomplete")))
U11: =IF(OR(S11="",T11=""),"",IF(S11=T11,"No","Yes")) | Y11: =IF(A11="","",IF(AND(O11="Rejected",X11="Yes"),"Potential unsupported-perturbation inflation",IF(AND(O11="Admitted",OR(M11<>"",N11<>"")),"No unsupported-perturbation defect indicated","Admission integrity incomplete")))
U12: =IF(OR(S12="",T12=""),"",IF(S12=T12,"No","Yes")) | Y12: =IF(A12="","",IF(AND(O12="Rejected",X12="Yes"),"Potential unsupported-perturbation inflation",IF(AND(O12="Admitted",OR(M12<>"",N12<>"")),"No unsupported-perturbation defect indicated","Admission integrity incomplete")))
U13: =IF(OR(S13="",T13=""),"",IF(S13=T13,"No","Yes")) | Y13: =IF(A13="","",IF(AND(O13="Rejected",X13="Yes"),"Potential unsupported-perturbation inflation",IF(AND(O13="Admitted",OR(M13<>"",N13<>"")),"No unsupported-perturbation defect indicated","Admission integrity incomplete")))
U14: =IF(OR(S14="",T14=""),"",IF(S14=T14,"No","Yes")) | Y14: =IF(A14="","",IF(AND(O14="Rejected",X14="Yes"),"Potential unsupported-perturbation inflation",IF(AND(O14="Admitted",OR(M14<>"",N14<>"")),"No unsupported-perturbation defect indicated","Admission integrity incomplete")))
U15: =IF(OR(S15="",T15=""),"",IF(S15=T15,"No","Yes")) | Y15: =IF(A15="","",IF(AND(O15="Rejected",X15="Yes"),"Potential unsupported-perturbation inflation",IF(AND(O15="Admitted",OR(M15<>"",N15<>"")),"No unsupported-perturbation defect indicated","Admission integrity incomplete")))
U16: =IF(OR(S16="",T16=""),"",IF(S16=T16,"No","Yes")) | Y16: =IF(A16="","",IF(AND(O16="Rejected",X16="Yes"),"Potential unsupported-perturbation inflation",IF(AND(O16="Admitted",OR(M16<>"",N16<>"")),"No unsupported-perturbation defect indicated","Admission integrity incomplete")))
U17: =IF(OR(S17="",T17=""),"",IF(S17=T17,"No","Yes")) | Y17: =IF(A17="","",IF(AND(O17="Rejected",X17="Yes"),"Potential unsupported-perturbation inflation",IF(AND(O17="Admitted",OR(M17<>"",N17<>"")),"No unsupported-perturbation defect indicated","Admission integrity incomplete")))
